Workbook
Name AnnualProductiveHours: [1]Instructions!$H$11
Name AnnualProductiveHours: [2]Instructions!$G$13
Name AnnualProductiveHours: [2]Instructions!$G$13
Name AnnualProductiveHours: [2]Instructions!$G$13
Name AnnualProductiveHours: Instructions!$H$12

Sheet Instructions
A1: Instructions
A2: ="Solicitation Number: "&Instructions!H9&"" -> Solicitation Number: W91CRB-25-R-0002
A3: ="Name of Action: "&Instructions!H10 -> Name of Action: Force Development
A4: ="Prime Contractor/Subcontractor Name/Division: "&Instructions!H15 -> Prime Contractor/Subcontractor Name/Division:
A5: ="Period of Performance: "&Instructions!H11 -> Period of Performance:
A6: ="Date of Proposal:"&IF(ISBLANK(Instructions!H18)," TBD",(TEXT(Instructions!H18," mm/dd/yyyy"))) -> Date of Proposal: TBD
G8: Government Inputs
G9: Solicitation Number: | H9: W91CRB-25-R-0002
G10: Name of Action: | H10: Force Development
G11: Period of Performance:
G12: Annual Productive Hours: | H12: =1920 -> 1920
G14: Offeror Inputs
G15: Prime Contractor/Subcontractor Name/Division:
G16: Street Address:
G17: City, State and Zip Code:
G18: Date of Proposal

Sheet Section B
A1: Section B - Supplies or Services Costs and/or Prices
A2: ="Solicitation Number: "&Instructions!H9&"" -> Solicitation Number: W91CRB-25-R-0002
A3: ="Name of Action: "&Instructions!H10 -> Name of Action: Force Development
A4: ="Prime Contractor/Subcontractor Name/Division: "&Instructions!H15 -> Prime Contractor/Subcontractor Name/Division:
A5: ="Period of Performance: "&Instructions!H11 -> Period of Performance:
A6: ="Date of Proposal:"&IF(ISBLANK(Instructions!H18)," TBD",(TEXT(Instructions!H18," mm/dd/yyyy"))) -> Date of Proposal: TBD
A7: (The format below is a sample. Propose in the actual format of the Section B contained in the solicitation)
A9: Base Period
A10: CLIN | B10: SUPPLIES/SERVICES | C10: QTY | D10: UNIT | E10: UNIT PRICE | F10: AMOUNT
A11: 0001 | B11: Transition-In Labor - Base Period (1 Month) | C11: 1 | D11: Each | E11: 0
B12: Labor - CPFF | E12: Cost | F12: ='Phase-in & OES 52.217-8 Labor'!N26 -> 0 | G12: From Labor Worksheet
E13: Fixed Fee | F13: ='Phase-in & OES 52.217-8 Labor'!O26 -> 0
E14: Cost Plus Fixed Fee | F14: =SUM(F12:F13) -> 0
A16: CLIN | B16: SUPPLIES/SERVICES | C16: QTY | D16: UNIT | E16: UNIT PRICE | F16: AMOUNT
A17: 0002 | B17: Regular Labor - Base Period (11 Months) | C17: 1 | D17: Each | E17: 0
B18: Labor - CPFF | E18: Cost | F18: ='Regular Labor Detail'!N26 -> 0 | G18: From Labor Worksheet
E19: Fixed Fee | F19: ='Regular Labor Detail'!O26 -> 0
E20: Cost Plus Fixed Fee | F20: =SUM(F18:F19) -> 0
A22: CLIN | B22: SUPPLIES/SERVICES | C22: QTY | D22: UNIT | E22: UNIT PRICE | F22: AMOUNT
A23: 0005 | B23: Optional Surge Labor - Base Period (FD, PAE, CAA) | C23: 1 | D23: Each | E23: 0
B24: Labor - CPFF | E24: Cost | F24: ='Surge Labor Detail'!N26 -> 0 | G24: From Labor Worksheet
E25: Fixed Fee | F25: ='Surge Labor Detail'!O26 -> 0
E26: Cost Plus Fixed Fee | F26: =SUM(F24:F25) -> 0
A28: CLIN | B28: SUPPLIES/SERVICES | C28: QTY | D28: UNIT | E28: UNIT PRICE | F28: AMOUNT
A29: 0004 | B29: Travel & ODCs Base Period | C29: 1 | D29: Each | E29: 0
B30: COST | D30: ODCs= | F30: ='ODC Cost Detail'!C10 -> 100000 | G30: From Cost Summary Worksheet
D31: Burden/G&A = | E31: ='ODC Cost Detail'!D10 -> 0 | F31: ='ODC Cost Detail'!E10 -> 0 | G31: From Cost Summary WorkWorksheet and ODC Cost Detail WorkWorksheet
D32: Subtotal ODC Ceiling | F32: =SUM(F30:F31) -> 100000
A34: Option Year (OY) 1
A35: CLIN | B35: SUPPLIES/SERVICES | C35: QTY | D35: UNIT | E35: UNIT PRICE | F35: AMOUNT
A36: 1001 | B36: Regular Labor - OY1 | C36: 1 | D36: Each | E36: 0
B37: Labor - CPFF | E37: Cost | F37: ='Regular Labor Detail'!N66 -> 0 | G37: From Labor Worksheet
E38: Fixed Fee | F38: ='Regular Labor Detail'!O66 -> 0
E39: Cost Plus Fixed Fee | F39: =SUM(F37:F38) -> 0
A41: CLIN | B41: SUPPLIES/SERVICES | C41: QTY | D41: UNIT | E41: UNIT PRICE | F41: AMOUNT
A42: 1004 | B42: Optional Surge Labor - OY1 (FD, PAE, CAA) | C42: 1 | D42: Each | E42: 0
B43: Labor - CPFF | E43: Cost | F43: ='Surge Labor Detail'!N66 -> 0 | G43: From Labor Worksheet
E44: Fixed Fee | F44: ='Surge Labor Detail'!O66 -> 0
E45: Cost Plus Fixed Fee | F45: =SUM(F43:F44) -> 0
A47: CLIN | B47: SUPPLIES/SERVICES | C47: QTY | D47: UNIT | E47: UNIT PRICE | F47: AMOUNT
A48: 1003 | B48: Travel & ODCs OY1 | C48: 1 | D48: Each | E48: 0
B49: COST | D49: ODCs= | F49: ='ODC Cost Detail'!C11 -> 100000 | G49: From Cost Summary Worksheet
D50: Burden/G&A = | E50: ='ODC Cost Detail'!D35 -> 0 | F50: ='ODC Cost Detail'!E11 -> 0 | G50: From Cost Summary WorkWorksheet and ODC Cost Detail WorkWorksheet
D51: Subtotal ODC Ceiling | F51: =SUM(F49:F50) -> 100000
A53: OY2
A54: CLIN | B54: SUPPLIES/SERVICES | C54: QTY | D54: UNIT | E54: UNIT PRICE | F54: AMOUNT
A55: 2001 | B55: Regular Labor - OY2 | C55: 1 | D55: Each | E55: 0
B56: Labor - CPFF | E56: Cost | F56: ='Regular Labor Detail'!N86 -> 0 | G56: From Labor Worksheet
E57: Fixed Fee | F57: ='Regular Labor Detail'!O86 -> 0
E58: Cost Plus Fixed Fee | F58: =SUM(F56:F57) -> 0
A60: CLIN | B60: SUPPLIES/SERVICES | C60: QTY | D60: UNIT | E60: UNIT PRICE | F60: AMOUNT
A61: 2004 | B61: Optional Surge Labor - OY2 (FD, PAE, CAA) | C61: 1 | D61: Each | E61: 0
B62: Labor - CPFF | E62: Cost | F62: ='Surge Labor Detail'!N86 -> 0 | G62: From Labor Worksheet
E63: Fixed Fee | F63: ='Surge Labor Detail'!O86 -> 0
E64: Cost Plus Fixed Fee | F64: =SUM(F62:F63) -> 0
A66: CLIN | B66: SUPPLIES/SERVICES | C66: QTY | D66: UNIT | E66: UNIT PRICE | F66: AMOUNT
A67: 2003 | B67: Travel & ODCs OY2 | C67: 1 | D67: Each | E67: 0
B68: COST | D68: ODCs= | F68: ='ODC Cost Detail'!C12 -> 100000 | G68: From Cost Summary Worksheet
D69: Burden/G&A = | E69: ='ODC Cost Detail'!D54 -> 0 | F69: ='ODC Cost Detail'!E12 -> 0 | G69: From Cost Summary WorkWorksheet and ODC Cost Detail WorkWorksheet
D70: Subtotal ODC Ceiling | F70: =SUM(F68:F69) -> 100000
A72: OY3
A73: CLIN | B73: SUPPLIES/SERVICES | C73: QTY | D73: UNIT | E73: UNIT PRICE | F73: AMOUNT
A74: 3001 | B74: Regular Labor - OY3 | C74: 1 | D74: Each | E74: 0
B75: Labor - CPFF | E75: Cost | F75: ='Regular Labor Detail'!N106 -> 0 | G75: From Labor Worksheet
E76: Fixed Fee | F76: ='Regular Labor Detail'!O106 -> 0
E77: Cost Plus Fixed Fee | F77: =SUM(F75:F76) -> 0
A79: CLIN | B79: SUPPLIES/SERVICES | C79: QTY | D79: UNIT | E79: UNIT PRICE | F79: AMOUNT
A80: 3004 | B80: Optional Surge Labor - OY3 (FD, PAE, CAA) | C80: 1 | D80: Each | E80: 0
B81: Labor - CPFF | E81: Cost | F81: ='Surge Labor Detail'!N106 -> 0 | G81: From Labor Worksheet
E82: Fixed Fee | F82: ='Surge Labor Detail'!O106 -> 0
E83: Cost Plus Fixed Fee | F83: =SUM(F81:F82) -> 0
A85: CLIN | B85: SUPPLIES/SERVICES | C85: QTY | D85: UNIT | E85: UNIT PRICE | F85: AMOUNT
A86: 3003 | B86: Travel & ODCs OY3 | C86: 1 | D86: Each | E86: 0
B87: COST | D87: ODCs= | F87: ='ODC Cost Detail'!C13 -> 100000 | G87: From Cost Summary Worksheet
D88: Burden/G&A = | E88: ='ODC Cost Detail'!D73 -> 0 | F88: ='ODC Cost Detail'!E13 -> 0 | G88: From Cost Summary WorkWorksheet and ODC Cost Detail WorkWorksheet
D89: Subtotal ODC Ceiling | F89: =SUM(F87:F88) -> 100000
A91: OY4
A92: CLIN | B92: SUPPLIES/SERVICES | C92: QTY | D92: UNIT | E92: UNIT PRICE | F92: AMOUNT
A93: 4001 | B93: Regular Labor - OY4 | C93: 1 | D93: Each | E93: 0
B94: Labor - CPFF | E94: Cost | F94: ='Regular Labor Detail'!N126 -> 0 | G94: From Labor Worksheet
E95: Fixed Fee | F95: ='Regular Labor Detail'!O126 -> 0
E96: Cost Plus Fixed Fee | F96: =SUM(F94:F95) -> 0
A98: CLIN | B98: SUPPLIES/SERVICES | C98: QTY | D98: UNIT | E98: UNIT PRICE | F98: AMOUNT
A99: 4004 | B99: Optional Surge Labor - OY4 (FD, PAE, CAA) | C99: 1 | D99: Each | E99: 0
B100: Labor - CPFF | E100: Cost | F100: ='Surge Labor Detail'!N126 -> 0 | G100: From Labor Worksheet
E101: Fixed Fee | F101: ='Surge Labor Detail'!O126 -> 0
E102: Cost Plus Fixed Fee | F102: =SUM(F100:F101) -> 0
A104: CLIN | B104: SUPPLIES/SERVICES | C104: QTY | D104: UNIT | E104: UNIT PRICE | F104: AMOUNT
A105: 4003 | B105: Travel & ODCs OY4 | C105: 1 | D105: Each | E105: 0
B106: COST | D106: ODCs= | F106: ='ODC Cost Detail'!C14 -> 100000 | G106: From Cost Summary Worksheet
D107: Burden/G&A = | E107: ='ODC Cost Detail'!D92 -> 0 | F107: ='ODC Cost Detail'!E14 -> 0 | G107: From Cost Summary WorkWorksheet and ODC Cost Detail WorkWorksheet
D108: Subtotal ODC Ceiling | F108: =SUM(F106:F107) -> 100000
A110: Option to Extend Services (OES) - 6 months
A111: CLIN | B111: SUPPLIES/SERVICES | C111: QTY | D111: UNIT | E111: UNIT PRICE | F111: AMOUNT
A112: 5001 | B112: Regular Labor - 6 Month OES | C112: 1 | D112: Each | E112: 0
B113: Labor - CPFF | E113: Cost | F113: ='Phase-in & OES 52.217-8 Labor'!N66 -> 0
E114: Fixed Fee | F114: ='Phase-in & OES 52.217-8 Labor'!O66 -> 0
E115: Cost Plus Fixed Fee | F115: =F113+F114 -> 0
A117: CLIN | B117: SUPPLIES/SERVICES | C117: QTY | D117: UNIT | E117: UNIT PRICE | F117: AMOUNT
A118: 5004 | B118: Optional Surge Labor - OES (FD, PAE, CAA) | C118: 1 | D118: Each | E118: 0
...

Sheet Cost Summary
A1: Cost Summary Spreadsheet
A2: ="Solicitation Number: "&Instructions!H9&"" -> Solicitation Number: W91CRB-25-R-0002
A3: ="Name of Action: "&Instructions!H10 -> Name of Action: Force Development
A4: ="Prime Contractor/Subcontractor Name/Division: "&Instructions!H15 -> Prime Contractor/Subcontractor Name/Division:
A5: ="Period of Performance: "&Instructions!H11 -> Period of Performance:
A6: ="Date of Proposal:"&IF(ISBLANK(Instructions!H18)," TBD",(TEXT(Instructions!H18," mm/dd/yyyy"))) -> Date of Proposal: TBD
A8: =Instructions!H10 -> Force Development | B8: Transition-In | C8: Base period | D8: Option Year 1 | E8: OY2 | F8: OY3 | G8: OY4 | H8: OES IAW FAR 52.217-8 | I8: Total
A9: Labor & Subcontract Labor Hours | B9: ='Phase-in & OES 52.217-8 Labor'!G26 -> 2652 | C9: ='Regular Labor Detail'!G26+'Surge Labor Detail'!G26 -> 120016 | D9: =+'Regular Labor Detail'!$G66+'Surge Labor Detail'!G66 -> 144730 | E9: =+'Regular Labor Detail'!$G86+'Surge Labor Detail'!G86 -> 154130 | F9: =+'Regular Labor Detail'!$G106+'Surge Labor Detail'!G106 -> 161650 | G9: =+'Regular Labor Detail'!$G126+'Surge Labor Detail'!G126 -> 161650 | H9: ='Phase-in & OES 52.217-8 Labor'!G66+'Phase-in & OES 52.217-8 Labor'!G86 -> 80825 | I9: =SUM(B9:H9) -> 825653 | J9: From Labor Cost Detail Worksheet
A10: Direct & Indirect Labor & Subcontract Labor Costs (less G&A) | B10: ='Phase-in & OES 52.217-8 Labor'!L26 -> 0 | C10: ='Regular Labor Detail'!L26+'Surge Labor Detail'!L26 -> 0 | D10: =+'Regular Labor Detail'!$L66+'Surge Labor Detail'!L66 -> 0 | E10: =+'Regular Labor Detail'!$L86+'Surge Labor Detail'!L86 -> 0 | F10: =+'Regular Labor Detail'!$L106+'Surge Labor Detail'!L106 -> 0 | G10: =+'Regular Labor Detail'!$L126+'Surge Labor Detail'!L126 -> 0 | H10: ='Phase-in & OES 52.217-8 Labor'!L66+'Phase-in & OES 52.217-8 Labor'!L86 -> 0 | I10: =SUM(B10:H10) -> 0 | J10: From Labor Cost Detail Worksheet
A11: G&A Costs | B11: ='Phase-in & OES 52.217-8 Labor'!M26 -> 0 | C11: ='Regular Labor Detail'!M26+'Surge Labor Detail'!M26 -> 0 | D11: =+'Regular Labor Detail'!$M66+'Surge Labor Detail'!M66 -> 0 | E11: =+'Regular Labor Detail'!$M86+'Surge Labor Detail'!M86 -> 0 | F11: =+'Regular Labor Detail'!$M106+'Surge Labor Detail'!M106 -> 0 | G11: =+'Regular Labor Detail'!$M126+'Surge Labor Detail'!M126 -> 0 | H11: ='Phase-in & OES 52.217-8 Labor'!M66+'Phase-in & OES 52.217-8 Labor'!M86 -> 0 | I11: =SUM(B11:H11) -> 0 | J11: From Labor Cost Detail Worksheet
A12: Direct & Indirect Labor & Subcontract Labor Costs (Less Fee) | B12: =SUM(B10:B11) -> 0 | C12: =SUM(C10:C11) -> 0 | D12: =SUM(D10:D11) -> 0 | E12: =SUM(E10:E11) -> 0 | F12: =SUM(F10:F11) -> 0 | G12: =SUM(G10:G11) -> 0 | H12: =SUM(H10:H11) -> 0 | I12: =SUM(I10:I11) -> 0
A13: Profit/Fee | B13: ='Phase-in & OES 52.217-8 Labor'!O26 -> 0 | C13: ='Regular Labor Detail'!O26+'Surge Labor Detail'!O26 -> 0 | D13: =+'Regular Labor Detail'!$O66+'Surge Labor Detail'!O66 -> 0 | E13: =+'Regular Labor Detail'!$O86+'Surge Labor Detail'!O86 -> 0 | F13: =+'Regular Labor Detail'!$O106+'Surge Labor Detail'!O106 -> 0 | G13: =+'Regular Labor Detail'!$O126+'Surge Labor Detail'!O126 -> 0 | H13: ='Phase-in & OES 52.217-8 Labor'!O66+'Phase-in & OES 52.217-8 Labor'!O86 -> 0 | I13: =SUM(B13:H13) -> 0 | J13: From Labor Cost Detail Worksheet
A14: Total Cost Plus Fixed Fee (Labor) | B14: =SUM(B12:B13) -> 0 | C14: =SUM(C12:C13) -> 0 | D14: =SUM(D12:D13) -> 0 | E14: =SUM(E12:E13) -> 0 | F14: =SUM(F12:F13) -> 0 | G14: =SUM(G12:G13) -> 0 | H14: =SUM(H12:H13) -> 0 | I14: =SUM(I12:I13) -> 0
A15: Travel & Other Direct Costs (ODCs) | C15: ='ODC Cost Detail'!C10 -> 100000 | D15: =+'ODC Cost Detail'!C11 -> 100000 | E15: =+'ODC Cost Detail'!C12 -> 100000 | F15: =+'ODC Cost Detail'!C13 -> 100000 | G15: =+'ODC Cost Detail'!C14 -> 100000 | H15: ='ODC Cost Detail'!C15 -> 50000 | I15: =SUM(B15:H15) -> 550000 | J15: From ODC Cost Detail Sheet
A16: G&A Burden on ODCs | C16: =+'ODC Cost Detail'!E10 -> 0 | D16: =+'ODC Cost Detail'!E11 -> 0 | E16: =+'ODC Cost Detail'!E12 -> 0 | F16: =+'ODC Cost Detail'!E13 -> 0 | G16: =+'ODC Cost Detail'!E14 -> 0 | H16: ='ODC Cost Detail'!E15 -> 0 | I16: =SUM(B16:H16) -> 0 | J16: From ODC Cost Detail Sheet
A17: Total Cost (Travel & ODCs) | C17: =SUM(C15:C16) -> 100000 | D17: =SUM(D15:D16) -> 100000 | E17: =SUM(E15:E16) -> 100000 | F17: =SUM(F15:F16) -> 100000 | G17: =SUM(G15:G16) -> 100000 | H17: =SUM(H15:H16) -> 50000 | I17: =SUM(I15:I16) -> 550000
A18: Total Cost Plus Fixed Fee | C18: =+C14+C17 -> 100000 | D18: =+D14+D17 -> 100000 | E18: =+E14+E17 -> 100000 | F18: =+F14+F17 -> 100000 | G18: =+G14+G17 -> 100000 | H18: =+H14+H17 -> 50000 | I18: =+I14+I17 -> 550000

Sheet Indirect Rate Summary
A1: Indirect Rate Summary Spreadsheet
A2: ="Solicitation Number: "&Instructions!H9&"" -> Solicitation Number: W91CRB-25-R-0002
A3: ="Name of Action: "&Instructions!H10 -> Name of Action: Force Development
A4: ="Prime Contractor/Subcontractor Name/Division: "&Instructions!H15 -> Prime Contractor/Subcontractor Name/Division:
A5: ="Period of Performance: "&Instructions!H11 -> Period of Performance:
A6: ="Date of Proposal:"&IF(ISBLANK(Instructions!H18)," TBD",(TEXT(Instructions!H18," mm/dd/yyyy"))) -> Date of Proposal: TBD
A8: Entity | B8: Contract Type | C8: Fringe Rate | D8: Overhead Rate | E8: G&A Rate | F8: Proposed Fee Rate | G8: % of Effort Performed by Prime and Subs Based on Labor Hours
A9: Base Year (Including Transition In)
A10: PRIME CONTRACTOR | B10: CPFF | C10: 0 | D10: 0 | E10: 0 | F10: 0 | G10: 0
A11: SUBCONTRACTOR 1 | C11: 0 | D11: 0 | E11: 0 | F11: 0 | G11: 0
A12: SUBCONTRACTOR 2 | C12: 0 | D12: 0 | E12: 0 | F12: 0 | G12: 0
A13: SUBCONTRACTOR 3 | C13: 0 | D13: 0 | E13: 0 | F13: 0 | G13: 0
A14: ETC | C14: 0 | D14: 0 | E14: 0 | F14: 0 | G14: 0
G15: =SUM(G10:G14) -> 0 | H15: (i.e. 100%)
A16: Option Year (OY) 1
A17: PRIME CONTRACTOR | B17: CPFF | C17: 0 | D17: 0 | E17: 0 | F17: 0 | G17: 0
A18: SUBCONTRACTOR 1 | C18: 0 | D18: 0 | E18: 0 | F18: 0 | G18: 0
A19: SUBCONTRACTOR 2 | C19: 0 | D19: 0 | E19: 0 | F19: 0 | G19: 0
A20: SUBCONTRACTOR 3 | C20: 0 | D20: 0 | E20: 0 | F20: 0 | G20: 0
A21: ETC | C21: 0 | D21: 0 | E21: 0 | F21: 0 | G21: 0
G22: =SUM(G17:G21) -> 0 | H22: (i.e. 100%)
A23: OY2
A24: PRIME CONTRACTOR | B24: CPFF | C24: 0 | D24: 0 | E24: 0 | F24: 0 | G24: 0
A25: SUBCONTRACTOR 1 | C25: 0 | D25: 0 | E25: 0 | F25: 0 | G25: 0
A26: SUBCONTRACTOR 2 | C26: 0 | D26: 0 | E26: 0 | F26: 0 | G26: 0
A27: SUBCONTRACTOR 3 | C27: 0 | D27: 0 | E27: 0 | F27: 0 | G27: 0
A28: ETC | C28: 0 | D28: 0 | E28: 0 | F28: 0 | G28: 0
G29: =SUM(G24:G28) -> 0 | H29: (i.e. 100%)
A30: OY3
A31: PRIME CONTRACTOR | B31: CPFF | C31: 0 | D31: 0 | E31: 0 | F31: 0 | G31: 0
A32: SUBCONTRACTOR 1 | C32: 0 | D32: 0 | E32: 0 | F32: 0 | G32: 0
A33: SUBCONTRACTOR 2 | C33: 0 | D33: 0 | E33: 0 | F33: 0 | G33: 0
A34: SUBCONTRACTOR 3 | C34: 0 | D34: 0 | E34: 0 | F34: 0 | G34: 0
A35: ETC | C35: 0 | D35: 0 | E35: 0 | F35: 0 | G35: 0
G36: =SUM(G31:G35) -> 0
A37: OY4
A38: PRIME CONTRACTOR | B38: CPFF | C38: 0 | D38: 0 | E38: 0 | F38: 0 | G38: 0
A39: SUBCONTRACTOR 1 | C39: 0 | D39: 0 | E39: 0 | F39: 0 | G39: 0
A40: SUBCONTRACTOR 2 | C40: 0 | D40: 0 | E40: 0 | F40: 0 | G40: 0
A41: SUBCONTRACTOR 3 | C41: 0 | D41: 0 | E41: 0 | F41: 0 | G41: 0
A42: ETC | C42: 0 | D42: 0 | E42: 0 | F42: 0 | G42: 0
G43: =SUM(G38:G42) -> 0
A46: Please enter corresponding indirect rates for the prime and each subcontractor for each of the periods.
A48: Subcontractors may provide data separately in the above format for proprietary reasons.
A50: Provide the necessary narrative describing how the rates were derived and applied, the composition of the allocation pools & bases, and provide any supporting forward rate agreements and DCAA/DCMA agreements/reports.
A53: If rates proposed are based on other than actual rates, please state the reason(s).
A55: Sample Fringe, Overhead, and G&A worksheet schedules follow this tab.

Sheet Direct Labor Rate Schedule
A1: Direct Labor Rate Schedule
A2: ="Solicitation Number: "&Instructions!H9&"" -> Solicitation Number: W91CRB-25-R-0002
A3: ="Name of Action: "&Instructions!H10 -> Name of Action: Force Development
A4: ="Prime Contractor/Subcontractor Name/Division: "&Instructions!H15 -> Prime Contractor/Subcontractor Name/Division:
A5: ="Period of Performance: "&Instructions!H11 -> Period of Performance:
A6: ="Date of Proposal:"&IF(ISBLANK(Instructions!H18)," TBD",(TEXT(Instructions!H18," mm/dd/yyyy"))) -> Date of Proposal: TBD
F8: Base Year and Transition-In | G8: Option Year (OY) 1 | I8: OY2 | K8: OY3 | M8: OY4 and Optional Extension of Services IAW FAR 52.217-8
A9: Labor Categories | B9: Location | C9: Labor Type | D9: SCA Identifier | E9: Cost Realism Basis for Rate Proposed | F9: Proposed Labor Rate | G9: Escalation | H9: Proposed Labor Rate | I9: Escalation | J9: Proposed Labor Rate | K9: Escalation | L9: Proposed Labor Rate | M9: Escalation | N9: Proposed Labor Rate
A11: Program Manager | H11: =IFERROR((ROUND(F11*(1+G11),2)),0) -> 0 | J11: =IFERROR((ROUND(H11*(1+I11),2)),0) -> 0 | L11: =IFERROR((ROUND(J11*(1+K11),2)),0) -> 0 | N11: =IFERROR((ROUND(L11*(1+M11),2)),0) -> 0
A12: Senior Analyst | H12: =IFERROR((ROUND(F12*(1+G12),2)),0) -> 0 | J12: =IFERROR((ROUND(H12*(1+I12),2)),0) -> 0 | L12: =IFERROR((ROUND(J12*(1+K12),2)),0) -> 0 | N12: =IFERROR((ROUND(L12*(1+M12),2)),0) -> 0
A13: Analyst | H13: =IFERROR((ROUND(F13*(1+G13),2)),0) -> 0 | J13: =IFERROR((ROUND(H13*(1+I13),2)),0) -> 0 | L13: =IFERROR((ROUND(J13*(1+K13),2)),0) -> 0 | N13: =IFERROR((ROUND(L13*(1+M13),2)),0) -> 0
A14: Junior Analyst | H14: =IFERROR((ROUND(F14*(1+G14),2)),0) -> 0 | J14: =IFERROR((ROUND(H14*(1+I14),2)),0) -> 0 | L14: =IFERROR((ROUND(J14*(1+K14),2)),0) -> 0 | N14: =IFERROR((ROUND(L14*(1+M14),2)),0) -> 0
A15: Senior Operations Research Analyst | H15: =IFERROR((ROUND(F15*(1+G15),2)),0) -> 0 | J15: =IFERROR((ROUND(H15*(1+I15),2)),0) -> 0 | L15: =IFERROR((ROUND(J15*(1+K15),2)),0) -> 0 | N15: =IFERROR((ROUND(L15*(1+M15),2)),0) -> 0
A16: Operations Research Analyst | H16: =IFERROR((ROUND(F16*(1+G16),2)),0) -> 0 | J16: =IFERROR((ROUND(H16*(1+I16),2)),0) -> 0 | L16: =IFERROR((ROUND(J16*(1+K16),2)),0) -> 0 | N16: =IFERROR((ROUND(L16*(1+M16),2)),0) -> 0
A17: Graphics Design Senior Analyst | H17: =IFERROR((ROUND(F17*(1+G17),2)),0) -> 0 | J17: =IFERROR((ROUND(H17*(1+I17),2)),0) -> 0 | L17: =IFERROR((ROUND(J17*(1+K17),2)),0) -> 0 | N17: =IFERROR((ROUND(L17*(1+M17),2)),0) -> 0
A18: Force Documentation Senior Analyst | H18: =IFERROR((ROUND(F18*(1+G18),2)),0) -> 0 | J18: =IFERROR((ROUND(H18*(1+I18),2)),0) -> 0 | L18: =IFERROR((ROUND(J18*(1+K18),2)),0) -> 0 | N18: =IFERROR((ROUND(L18*(1+M18),2)),0) -> 0
H19: =IFERROR((ROUND(F19*(1+G19),2)),0) -> 0 | J19: =IFERROR((ROUND(H19*(1+I19),2)),0) -> 0 | L19: =IFERROR((ROUND(J19*(1+K19),2)),0) -> 0 | N19: =IFERROR((ROUND(L19*(1+M19),2)),0) -> 0
H20: =IFERROR((ROUND(F20*(1+G20),2)),0) -> 0 | J20: =IFERROR((ROUND(H20*(1+I20),2)),0) -> 0 | L20: =IFERROR((ROUND(J20*(1+K20),2)),0) -> 0 | N20: =IFERROR((ROUND(L20*(1+M20),2)),0) -> 0
H21: =IFERROR((ROUND(F21*(1+G21),2)),0) -> 0 | J21: =IFERROR((ROUND(H21*(1+I21),2)),0) -> 0 | L21: =IFERROR((ROUND(J21*(1+K21),2)),0) -> 0 | N21: =IFERROR((ROUND(L21*(1+M21),2)),0) -> 0
H22: =IFERROR((ROUND(F22*(1+G22),2)),0) -> 0 | J22: =IFERROR((ROUND(H22*(1+I22),2)),0) -> 0 | L22: =IFERROR((ROUND(J22*(1+K22),2)),0) -> 0 | N22: =IFERROR((ROUND(L22*(1+M22),2)),0) -> 0
H23: =IFERROR((ROUND(F23*(1+G23),2)),0) -> 0 | J23: =IFERROR((ROUND(H23*(1+I23),2)),0) -> 0 | L23: =IFERROR((ROUND(J23*(1+K23),2)),0) -> 0 | N23: =IFERROR((ROUND(L23*(1+M23),2)),0) -> 0
H24: =IFERROR((ROUND(F24*(1+G24),2)),0) -> 0 | J24: =IFERROR((ROUND(H24*(1+I24),2)),0) -> 0 | L24: =IFERROR((ROUND(J24*(1+K24),2)),0) -> 0 | N24: =IFERROR((ROUND(L24*(1+M24),2)),0) -> 0

Sheet Regular Labor Detail
A1: Labor Cost Detail Spreadsheet
A2: ="Solicitation Number: "&Instructions!H9&"" -> Solicitation Number: W91CRB-25-R-0002
A3: ="Name of Action: "&Instructions!H10 -> Name of Action: Force Development
A4: ="Prime Contractor/Subcontractor Name/Division: "&Instructions!H15 -> Prime Contractor/Subcontractor Name/Division:
A5: ="Period of Performance: "&Instructions!H11 -> Period of Performance:
A6: ="Date of Proposal:"&IF(ISBLANK(Instructions!H18)," TBD",(TEXT(Instructions!H18," mm/dd/yyyy"))) -> Date of Proposal: TBD
A7: ="Annual Productive Hours: "&AnnualProductiveHours -> Annual Productive Hours: 1920
G9: Direct Labor | I9: Indirect Cost
C10: CLIN 0001-2 Base Period (11 Months) | I10: ='Indirect Rate Summary'!C10 -> 0 | J10: ='Indirect Rate Summary'!D10 -> 0 | M10: ='Indirect Rate Summary'!E10 -> 0 | O10: ='Indirect Rate Summary'!F10 -> 0
A11: Location (Note 1) | B11: Labor Type (Note 2) | C11: Labor Categories (Note 3) | D11: Effort To Be Performed By The Prime (P) or Subcontractor (S) (Note 4) | E11: If Column D=S, Enter Name of Subcontractor(s) (Note 5) | F11: FTEs (Note 6) | G11: Total Productive Hours (Note 7) | H11: Hourly Base Pay Rate (Note 8) | I11: Fringe (Note 9) | J11: Overhead (Note 10) | K11: Prime/Sub Hourly Rate Before Application Of Prime G&A & Fee (IF Col C=S Enter Sub Rate) (Note 11) | L11: Total Prime & Sub Labor Before Prime G&A & Fee | M11: G&A (Note 12) | N11: Total Cost | O11: Fee | P11: Total Price | Q11: Proposal Fully Burdened Hourly Billing Rate | R11: Wrap Rate
A12: a | B12: b | C12: c | D12: d | E12: e | F12: f | G12: g | H12: h | I12: i | J12: j | K12: k = h + i + j | L12: l = g x k | M12: m | N12: n = l + o | O12: o | P12: p = n + o | Q12: q = p/g | R12: r = q/h
A13: =IF('Direct Labor Rate Schedule'!$A$10="","",'Direct Labor Rate Schedule'!$A$10)
A14: =IF('Direct Labor Rate Schedule'!B18="","",'Direct Labor Rate Schedule'!B11) | B14: ='Direct Labor Rate Schedule'!C11 -> 0 | C14: ='Direct Labor Rate Schedule'!A11 -> Program Manager | D14: Enter P or S | F14: =(G14/AnnualProductiveHours) -> 0.89791667 | G14: 1724 | H14: ='Direct Labor Rate Schedule'!F11 -> 0 | I14: =ROUND((+H14*$I$10),2) -> 0 | J14: =ROUND((+H14*$J$10),2) -> 0 | K14: =+H14+SUM(I14:J14) -> 0 | L14: =ROUND((+G14*K14),2) -> 0 | M14: =ROUND((+L14*$M$10),2) -> 0 | N14: =SUM(L14:M14) -> 0 | O14: =ROUND((+N14*$O$10),2) -> 0 | P14: =SUM(N14:O14) -> 0 | Q14: =IFERROR((+P14/G14),"") -> 0 | R14: =IFERROR(Q14/H14-1,"")
A15: =IF('Direct Labor Rate Schedule'!B19="","",'Direct Labor Rate Schedule'!B12) | B15: ='Direct Labor Rate Schedule'!C12 -> 0 | C15: ='Direct Labor Rate Schedule'!A12 -> Senior Analyst | D15: Enter P or S | F15: =(G15/AnnualProductiveHours) -> 44.964583 | G15: 86332 | H15: ='Direct Labor Rate Schedule'!F12 -> 0 | I15: =ROUND((+H15*$I$10),2) -> 0 | J15: =ROUND((+H15*$J$10),2) -> 0 | K15: =+H15+SUM(I15:J15) -> 0 | L15: =ROUND((+G15*K15),2) -> 0 | M15: =ROUND((+L15*$M$10),2) -> 0 | N15: =SUM(L15:M15) -> 0 | O15: =ROUND((+N15*$O$10),2) -> 0 | P15: =SUM(N15:O15) -> 0 | Q15: =IFERROR((+P15/G15),"") -> 0 | R15: =IFERROR(Q15/H15-1,"")
A16: =IF('Direct Labor Rate Schedule'!B20="","",'Direct Labor Rate Schedule'!B13) | B16: ='Direct Labor Rate Schedule'!C13 -> 0 | C16: ='Direct Labor Rate Schedule'!A13 -> Analyst | D16: Enter P or S | F16: =(G16/AnnualProductiveHours) -> 2.9375 | G16: 5640 | H16: ='Direct Labor Rate Schedule'!F13 -> 0 | I16: =ROUND((+H16*$I$10),2) -> 0 | J16: =ROUND((+H16*$J$10),2) -> 0 | K16: =+H16+SUM(I16:J16) -> 0 | L16: =ROUND((+G16*K16),2) -> 0 | M16: =ROUND((+L16*$M$10),2) -> 0 | N16: =SUM(L16:M16) -> 0 | O16: =ROUND((+N16*$O$10),2) -> 0 | P16: =SUM(N16:O16) -> 0 | Q16: =IFERROR((+P16/G16),"") -> 0 | R16: =IFERROR(Q16/H16-1,"")
A17: =IF('Direct Labor Rate Schedule'!B21="","",'Direct Labor Rate Schedule'!B14) | B17: ='Direct Labor Rate Schedule'!C14 -> 0 | C17: ='Direct Labor Rate Schedule'!A14 -> Junior Analyst | D17: Enter P or S | F17: =(G17/AnnualProductiveHours) -> 2.9375 | G17: 5640 | H17: ='Direct Labor Rate Schedule'!F14 -> 0 | I17: =ROUND((+H17*$I$10),2) -> 0 | J17: =ROUND((+H17*$J$10),2) -> 0 | K17: =+H17+SUM(I17:J17) -> 0 | L17: =ROUND((+G17*K17),2) -> 0 | M17: =ROUND((+L17*$M$10),2) -> 0 | N17: =SUM(L17:M17) -> 0 | O17: =ROUND((+N17*$O$10),2) -> 0 | P17: =SUM(N17:O17) -> 0 | Q17: =IFERROR((+P17/G17),"") -> 0 | R17: =IFERROR(Q17/H17-1,"")
A18: =IF('Direct Labor Rate Schedule'!B22="","",'Direct Labor Rate Schedule'!B15) | B18: ='Direct Labor Rate Schedule'!C15 -> 0 | C18: ='Direct Labor Rate Schedule'!A15 -> Senior Operations Research Analyst | D18: Enter P or S | F18: =(G18/AnnualProductiveHours) -> 2.9375 | G18: 5640 | H18: ='Direct Labor Rate Schedule'!F15 -> 0 | I18: =ROUND((+H18*$I$10),2) -> 0 | J18: =ROUND((+H18*$J$10),2) -> 0 | K18: =+H18+SUM(I18:J18) -> 0 | L18: =ROUND((+G18*K18),2) -> 0 | M18: =ROUND((+L18*$M$10),2) -> 0 | N18: =SUM(L18:M18) -> 0 | O18: =ROUND((+N18*$O$10),2) -> 0 | P18: =SUM(N18:O18) -> 0 | Q18: =IFERROR((+P18/G18),"") -> 0 | R18: =IFERROR(Q18/H18-1,"")
A19: =IF('Direct Labor Rate Schedule'!B23="","",'Direct Labor Rate Schedule'!B16) | B19: ='Direct Labor Rate Schedule'!C16 -> 0 | C19: ='Direct Labor Rate Schedule'!A16 -> Operations Research Analyst | D19: Enter P or S | F19: =(G19/AnnualProductiveHours) -> 1.9583333 | G19: 3760 | H19: ='Direct Labor Rate Schedule'!F16 -> 0 | I19: =ROUND((+H19*$I$10),2) -> 0 | J19: =ROUND((+H19*$J$10),2) -> 0 | K19: =+H19+SUM(I19:J19) -> 0 | L19: =ROUND((+G19*K19),2) -> 0 | M19: =ROUND((+L19*$M$10),2) -> 0 | N19: =SUM(L19:M19) -> 0 | O19: =ROUND((+N19*$O$10),2) -> 0 | P19: =SUM(N19:O19) -> 0 | Q19: =IFERROR((+P19/G19),"") -> 0 | R19: =IFERROR(Q19/H19-1,"")
A20: =IF('Direct Labor Rate Schedule'!B24="","",'Direct Labor Rate Schedule'!B17) | B20: ='Direct Labor Rate Schedule'!C17 -> 0 | C20: ='Direct Labor Rate Schedule'!A17 -> Graphics Design Senior Analyst | D20: Enter P or S | F20: =(G20/AnnualProductiveHours) -> 0.97916667 | G20: 1880 | H20: ='Direct Labor Rate Schedule'!F17 -> 0 | I20: =ROUND((+H20*$I$10),2) -> 0 | J20: =ROUND((+H20*$J$10),2) -> 0 | K20: =+H20+SUM(I20:J20) -> 0 | L20: =ROUND((+G20*K20),2) -> 0 | M20: =ROUND((+L20*$M$10),2) -> 0 | N20: =SUM(L20:M20) -> 0 | O20: =ROUND((+N20*$O$10),2) -> 0 | P20: =SUM(N20:O20) -> 0 | Q20: =IFERROR((+P20/G20),"") -> 0 | R20: =IFERROR(Q20/H20-1,"")
A21: =IF('Direct Labor Rate Schedule'!B25="","",'Direct Labor Rate Schedule'!B18) | B21: ='Direct Labor Rate Schedule'!C18 -> 0 | C21: ='Direct Labor Rate Schedule'!A18 -> Force Documentation Senior Analyst | D21: Enter P or S | F21: =(G21/AnnualProductiveHours) -> 0.97916667 | G21: 1880 | H21: ='Direct Labor Rate Schedule'!F18 -> 0 | I21: =ROUND((+H21*$I$10),2) -> 0 | J21: =ROUND((+H21*$J$10),2) -> 0 | K21: =+H21+SUM(I21:J21) -> 0 | L21: =ROUND((+G21*K21),2) -> 0 | M21: =ROUND((+L21*$M$10),2) -> 0 | N21: =SUM(L21:M21) -> 0 | O21: =ROUND((+N21*$O$10),2) -> 0 | P21: =SUM(N21:O21) -> 0 | Q21: =IFERROR((+P21/G21),"") -> 0 | R21: =IFERROR(Q21/H21-1,"")
A22: =IF('Direct Labor Rate Schedule'!B26="","",'Direct Labor Rate Schedule'!B19) | B22: ='Direct Labor Rate Schedule'!C19 -> 0 | C22: ='Direct Labor Rate Schedule'!A19 -> 0 | D22: Enter P or S | F22: =(G22/AnnualProductiveHours) -> 0 | G22: 0 | H22: ='Direct Labor Rate Schedule'!F19 -> 0 | I22: =ROUND((+H22*$I$10),2) -> 0 | J22: =ROUND((+H22*$J$10),2) -> 0 | K22: =+H22+SUM(I22:J22) -> 0 | L22: =ROUND((+G22*K22),2) -> 0 | M22: =ROUND((+L22*$M$10),2) -> 0 | N22: =SUM(L22:M22) -> 0 | O22: =ROUND((+N22*$O$10),2) -> 0 | P22: =SUM(N22:O22) -> 0 | Q22: =IFERROR((+P22/G22),"") | R22: =IFERROR(Q22/H22-1,"")
A23: =IF('Direct Labor Rate Schedule'!B27="","",'Direct Labor Rate Schedule'!B20) | B23: ='Direct Labor Rate Schedule'!C20 -> 0 | C23: ='Direct Labor Rate Schedule'!A20 -> 0 | D23: Enter P or S | F23: =(G23/AnnualProductiveHours) -> 0 | G23: 0 | H23: ='Direct Labor Rate Schedule'!F20 -> 0 | I23: =ROUND((+H23*$I$10),2) -> 0 | J23: =ROUND((+H23*$J$10),2) -> 0 | K23: =+H23+SUM(I23:J23) -> 0 | L23: =ROUND((+G23*K23),2) -> 0 | M23: =ROUND((+L23*$M$10),2) -> 0 | N23: =SUM(L23:M23) -> 0 | O23: =ROUND((+N23*$O$10),2) -> 0 | P23: =SUM(N23:O23) -> 0 | Q23: =IFERROR((+P23/G23),"") | R23: =IFERROR(Q23/H23-1,"")
A24: =IF('Direct Labor Rate Schedule'!B28="","",'Direct Labor Rate Schedule'!B21) | B24: ='Direct Labor Rate Schedule'!C21 -> 0 | C24: ='Direct Labor Rate Schedule'!A21 -> 0 | D24: Enter P or S | F24: =(G24/AnnualProductiveHours) -> 0 | G24: 0 | H24: ='Direct Labor Rate Schedule'!F21 -> 0 | I24: =ROUND((+H24*$I$10),2) -> 0 | J24: =ROUND((+H24*$J$10),2) -> 0 | K24: =+H24+SUM(I24:J24) -> 0 | L24: =ROUND((+G24*K24),2) -> 0 | M24: =ROUND((+L24*$M$10),2) -> 0 | N24: =SUM(L24:M24) -> 0 | O24: =ROUND((+N24*$O$10),2) -> 0 | P24: =SUM(N24:O24) -> 0 | Q24: =IFERROR((+P24/G24),"") | R24: =IFERROR(Q24/H24-1,"")
A25: =IF('Direct Labor Rate Schedule'!B29="","",'Direct Labor Rate Schedule'!B22) | B25: ='Direct Labor Rate Schedule'!C22 -> 0 | C25: ='Direct Labor Rate Schedule'!A22 -> 0 | D25: Enter P or S | F25: =(G25/AnnualProductiveHours) -> 0 | G25: 0 | H25: ='Direct Labor Rate Schedule'!F22 -> 0 | I25: =ROUND((+H25*$I$10),2) -> 0 | J25: =ROUND((+H25*$J$10),2) -> 0 | K25: =+H25+SUM(I25:J25) -> 0 | L25: =ROUND((+G25*K25),2) -> 0 | M25: =ROUND((+L25*$M$10),2) -> 0 | N25: =SUM(L25:M25) -> 0 | O25: =ROUND((+N25*$O$10),2) -> 0 | P25: =SUM(N25:O25) -> 0 | Q25: =IFERROR((+P25/G25),"") | R25: =IFERROR(Q25/H25-1,"")
A26: Total: | F26: =SUM(F14:F25) -> 58.591667 | G26: =SUM(G14:G25) -> 112496 | H26: =SUMPRODUCT(H14:H25,$G14:$G25) -> 0 | I26: =SUMPRODUCT(I14:I25,$G14:$G25) -> 0 | J26: =SUMPRODUCT(J14:J25,$G14:$G25) -> 0 | K26: =SUMPRODUCT(K14:K25,$G14:$G25) -> 0 | L26: =SUM(L14:L25) -> 0 | M26: =SUM(M14:M25) -> 0 | N26: =SUM(N14:N25) -> 0 | O26: =SUM(O14:O25) -> 0 | P26: =SUM(P14:P25) -> 0 | Q26: =SUMPRODUCT(Q14:Q25,$G14:$G25) -> 0
A27: Weighted Average: | G27: =G26/SUM(F14:F25) -> 1920 | H27: =H26/$G26 -> 0 | I27: =I26/$G26 -> 0 | J27: =J26/$G26 -> 0 | K27: =K26/$G26 -> 0 | L27: =L26/$G26 -> 0 | M27: =M26/$G26 -> 0 | N27: =N26/$G26 -> 0 | O27: =O26/$G26 -> 0 | ... Q27: =Q26/$G26 -> 0 | R27: =Q27/H27 -> #DIV/0!
G29: Direct Cost | I29: Indirect Cost
I30: ='Indirect Rate Summary'!C10 -> 0 | J30: ='Indirect Rate Summary'!D10 -> 0 | M30: ='Indirect Rate Summary'!E10 -> 0 | O30: ='Indirect Rate Summary'!F10 -> 0
A31: =+A11 -> Location (Note 1) | B31: =+B11 -> Labor Type (Note 2) | C31: =+C11 -> Labor Categories (Note 3) | D31: =+D11 -> Effort To Be Performed By The Prime (P) or Subcontractor (S) (Note 4) | E31: =+E11 -> If Column D=S, Enter Name of Subcontractor(s) (Note 5) | F31: =+F11 -> FTEs (Note 6) | G31: =+G11 -> Total Productive Hours (Note 7) | H31: =+H11 -> Hourly Base Pay Rate (Note 8) | ... R31: =+R11 -> Wrap Rate
A32: =+A12 -> a | B32: =+B12 -> b | C32: =+C12 -> c | D32: =+D12 -> d | E32: =+E12 -> e | F32: =+F12 -> f | G32: =+G12 -> g | H32: =+H12 -> h | ... R32: =+R12 -> r = q/h
A33: =IF('Direct Labor Rate Schedule'!$A$10="","",'Direct Labor Rate Schedule'!$A$10)
A34: =A14 | B34: =B14 -> 0 | C34: =C14 -> Program Manager | D34: Enter P or S | F34: =(G34/AnnualProductiveHours)*(12/11) -> 0 | H34: ='Direct Labor Rate Schedule'!F11 -> 0 | I34: =ROUND((+H34*$I$30),2) -> 0 | J34: =ROUND((+H34*$J$30),2) -> 0 | K34: =+H34+SUM(I34:J34) -> 0 | L34: =ROUND((+G34*K34),2) -> 0 | M34: =ROUND((+L34*$M$30),2) -> 0 | N34: =SUM(L34:M34) -> 0 | O34: =ROUND((+N34*$O$30),2) -> 0 | P34: =SUM(N34:O34) -> 0 | Q34: =IFERROR((+P34/G34),"") | R34: =IFERROR(Q34/H34-1,"")
A35: =A15 | B35: =B15 -> 0 | C35: =C15 -> Senior Analyst | D35: Enter P or S | F35: =(G35/AnnualProductiveHours)*(12/11) -> 0 | H35: ='Direct Labor Rate Schedule'!F12 -> 0 | I35: =ROUND((+H35*$I$30),2) -> 0 | J35: =ROUND((+H35*$J$30),2) -> 0 | K35: =+H35+SUM(I35:J35) -> 0 | L35: =ROUND((+G35*K35),2) -> 0 | M35: =ROUND((+L35*$M$30),2) -> 0 | N35: =SUM(L35:M35) -> 0 | O35: =ROUND((+N35*$O$30),2) -> 0 | P35: =SUM(N35:O35) -> 0 | Q35: =IFERROR((+P35/G35),"") | R35: =IFERROR(Q35/H35-1,"")
A36: =A16 | B36: =B16 -> 0 | C36: =C16 -> Analyst | D36: Enter P or S | F36: =(G36/AnnualProductiveHours)*(12/11) -> 0 | H36: ='Direct Labor Rate Schedule'!F13 -> 0 | I36: =ROUND((+H36*$I$30),2) -> 0 | J36: =ROUND((+H36*$J$30),2) -> 0 | K36: =+H36+SUM(I36:J36) -> 0 | L36: =ROUND((+G36*K36),2) -> 0 | M36: =ROUND((+L36*$M$30),2) -> 0 | N36: =SUM(L36:M36) -> 0 | O36: =ROUND((+N36*$O$30),2) -> 0 | P36: =SUM(N36:O36) -> 0 | Q36: =IFERROR((+P36/G36),"") | R36: =IFERROR(Q36/H36-1,"")
A37: =A17 | B37: =B17 -> 0 | C37: =C17 -> Junior Analyst | D37: Enter P or S | F37: =(G37/AnnualProductiveHours)*(12/11) -> 0 | H37: ='Direct Labor Rate Schedule'!F14 -> 0 | I37: =ROUND((+H37*$I$30),2) -> 0 | J37: =ROUND((+H37*$J$30),2) -> 0 | K37: =+H37+SUM(I37:J37) -> 0 | L37: =ROUND((+G37*K37),2) -> 0 | M37: =ROUND((+L37*$M$30),2) -> 0 | N37: =SUM(L37:M37) -> 0 | O37: =ROUND((+N37*$O$30),2) -> 0 | P37: =SUM(N37:O37) -> 0 | Q37: =IFERROR((+P37/G37),"") | R37: =IFERROR(Q37/H37-1,"")
A38: =A18 | B38: =B18 -> 0 | C38: =C18 -> Senior Operations Research Analyst | D38: Enter P or S | F38: =(G38/AnnualProductiveHours)*(12/11) -> 0 | H38: ='Direct Labor Rate Schedule'!F15 -> 0 | I38: =ROUND((+H38*$I$30),2) -> 0 | J38: =ROUND((+H38*$J$30),2) -> 0 | K38: =+H38+SUM(I38:J38) -> 0 | L38: =ROUND((+G38*K38),2) -> 0 | M38: =ROUND((+L38*$M$30),2) -> 0 | N38: =SUM(L38:M38) -> 0 | O38: =ROUND((+N38*$O$30),2) -> 0 | P38: =SUM(N38:O38) -> 0 | Q38: =IFERROR((+P38/G38),"") | R38: =IFERROR(Q38/H38-1,"")
A39: =A19 | B39: =B19 -> 0 | C39: =C19 -> Operations Research Analyst | D39: Enter P or S | F39: =(G39/AnnualProductiveHours)*(12/11) -> 0 | H39: ='Direct Labor Rate Schedule'!F16 -> 0 | I39: =ROUND((+H39*$I$30),2) -> 0 | J39: =ROUND((+H39*$J$30),2) -> 0 | K39: =+H39+SUM(I39:J39) -> 0 | L39: =ROUND((+G39*K39),2) -> 0 | M39: =ROUND((+L39*$M$30),2) -> 0 | N39: =SUM(L39:M39) -> 0 | O39: =ROUND((+N39*$O$30),2) -> 0 | P39: =SUM(N39:O39) -> 0 | Q39: =IFERROR((+P39/G39),"") | R39: =IFERROR(Q39/H39-1,"")
A40: =A20 | B40: =B20 -> 0 | C40: =C20 -> Graphics Design Senior Analyst | D40: Enter P or S | F40: =(G40/AnnualProductiveHours)*(12/11) -> 0 | H40: ='Direct Labor Rate Schedule'!F17 -> 0 | I40: =ROUND((+H40*$I$30),2) -> 0 | J40: =ROUND((+H40*$J$30),2) -> 0 | K40: =+H40+SUM(I40:J40) -> 0 | L40: =ROUND((+G40*K40),2) -> 0 | M40: =ROUND((+L40*$M$30),2) -> 0 | N40: =SUM(L40:M40) -> 0 | O40: =ROUND((+N40*$O$30),2) -> 0 | P40: =SUM(N40:O40) -> 0 | Q40: =IFERROR((+P40/G40),"") | R40: =IFERROR(Q40/H40-1,"")
A41: =A21 | B41: =B21 -> 0 | C41: =C21 -> Force Documentation Senior Analyst | D41: Enter P or S | F41: =(G41/AnnualProductiveHours)*(12/11) -> 0 | H41: ='Direct Labor Rate Schedule'!F18 -> 0 | I41: =ROUND((+H41*$I$30),2) -> 0 | J41: =ROUND((+H41*$J$30),2) -> 0 | K41: =+H41+SUM(I41:J41) -> 0 | L41: =ROUND((+G41*K41),2) -> 0 | M41: =ROUND((+L41*$M$30),2) -> 0 | N41: =SUM(L41:M41) -> 0 | O41: =ROUND((+N41*$O$30),2) -> 0 | P41: =SUM(N41:O41) -> 0 | Q41: =IFERROR((+P41/G41),"") | R41: =IFERROR(Q41/H41-1,"")
A42: =A22 | B42: =B22 -> 0 | C42: =C22 -> 0 | D42: Enter P or S | F42: =(G42/AnnualProductiveHours)*(12/11) -> 0 | H42: ='Direct Labor Rate Schedule'!F19 -> 0 | I42: =ROUND((+H42*$I$30),2) -> 0 | J42: =ROUND((+H42*$J$30),2) -> 0 | K42: =+H42+SUM(I42:J42) -> 0 | L42: =ROUND((+G42*K42),2) -> 0 | M42: =ROUND((+L42*$M$30),2) -> 0 | N42: =SUM(L42:M42) -> 0 | O42: =ROUND((+N42*$O$30),2) -> 0 | P42: =SUM(N42:O42) -> 0 | Q42: =IFERROR((+P42/G42),"") | R42: =IFERROR(Q42/H42-1,"")
A43: =A23 | B43: =B23 -> 0 | C43: =C23 -> 0 | D43: Enter P or S | F43: =(G43/AnnualProductiveHours)*(12/11) -> 0 | H43: ='Direct Labor Rate Schedule'!F20 -> 0 | I43: =ROUND((+H43*$I$30),2) -> 0 | J43: =ROUND((+H43*$J$30),2) -> 0 | K43: =+H43+SUM(I43:J43) -> 0 | L43: =ROUND((+G43*K43),2) -> 0 | M43: =ROUND((+L43*$M$30),2) -> 0 | N43: =SUM(L43:M43) -> 0 | O43: =ROUND((+N43*$O$30),2) -> 0 | P43: =SUM(N43:O43) -> 0 | Q43: =IFERROR((+P43/G43),"") | R43: =IFERROR(Q43/H43-1,"")
A44: =A24 | B44: =B24 -> 0 | C44: =C24 -> 0 | D44: Enter P or S | F44: =(G44/AnnualProductiveHours)*(12/11) -> 0 | H44: ='Direct Labor Rate Schedule'!F21 -> 0 | I44: =ROUND((+H44*$I$30),2) -> 0 | J44: =ROUND((+H44*$J$30),2) -> 0 | K44: =+H44+SUM(I44:J44) -> 0 | L44: =ROUND((+G44*K44),2) -> 0 | M44: =ROUND((+L44*$M$30),2) -> 0 | N44: =SUM(L44:M44) -> 0 | O44: =ROUND((+N44*$O$30),2) -> 0 | P44: =SUM(N44:O44) -> 0 | Q44: =IFERROR((+P44/G44),"") | R44: =IFERROR(Q44/H44-1,"")
A45: =A25 | B45: =B25 -> 0 | C45: =C25 -> 0 | D45: Enter P or S | F45: =(G45/AnnualProductiveHours)*(12/11) -> 0 | H45: ='Direct Labor Rate Schedule'!F22 -> 0 | I45: =ROUND((+H45*$I$30),2) -> 0 | J45: =ROUND((+H45*$J$30),2) -> 0 | K45: =+H45+SUM(I45:J45) -> 0 | L45: =ROUND((+G45*K45),2) -> 0 | M45: =ROUND((+L45*$M$30),2) -> 0 | N45: =SUM(L45:M45) -> 0 | O45: =ROUND((+N45*$O$30),2) -> 0 | P45: =SUM(N45:O45) -> 0 | Q45: =IFERROR((+P45/G45),"") | R45: =IFERROR(Q45/H45-1,"")
A46: Total: | F46: =SUM(F34:F45) -> 0 | G46: =SUM(G34:G45) -> 0 | H46: =SUMPRODUCT(H34:H45,$G34:$G45) -> 0 | I46: =SUMPRODUCT(I34:I45,$G34:$G45) -> 0 | J46: =SUMPRODUCT(J34:J45,$G34:$G45) -> 0 | K46: =SUMPRODUCT(K34:K45,$G34:$G45) -> 0 | L46: =SUM(L34:L45) -> 0 | M46: =SUM(M34:M45) -> 0 | N46: =SUM(N34:N45) -> 0 | O46: =SUM(O34:O45) -> 0 | P46: =SUM(P34:P45) -> 0 | Q46: =SUMPRODUCT(Q34:Q45,$G34:$G45) -> 0
A47: Weighted Average: | G47: =G46/SUM(F34:F45) -> #DIV/0! | H47: =H46/$G46 -> #DIV/0! | I47: =I46/$G46 -> #DIV/0! | J47: =J46/$G46 -> #DIV/0! | K47: =K46/$G46 -> #DIV/0! | L47: =L46/$G46 -> #DIV/0! | M47: =M46/$G46 -> #DIV/0! | N47: =N46/$G46 -> #DIV/0! | O47: =O46/$G46 -> #DIV/0! | ... Q47: =Q46/$G46 -> #DIV/0! | R47: =Q47/H47 -> #DIV/0!
G49: Direct Cost | I49: Indirect Cost
C50: CLIN 1001 - OY1 Labor | I50: ='Indirect Rate Summary'!C17 -> 0 | J50: ='Indirect Rate Summary'!D17 -> 0 | M50: ='Indirect Rate Summary'!E17 -> 0 | O50: ='Indirect Rate Summary'!F17 -> 0
A51: =+A31 -> Location (Note 1) | B51: =+B31 -> Labor Type (Note 2) | C51: =+C31 -> Labor Categories (Note 3) | D51: =+D31 -> Effort To Be Performed By The Prime (P) or Subcontractor (S) (Note 4) | E51: =+E31 -> If Column D=S, Enter Name of Subcontractor(s) (Note 5) | F51: =+F31 -> FTEs (Note 6) | G51: =+G31 -> Total Productive Hours (Note 7) | H51: =+H31 -> Hourly Base Pay Rate (Note 8) | ... R51: =+R31 -> Wrap Rate
A52: =+A32 -> a | B52: =+B32 -> b | C52: =+C32 -> c | D52: =+D32 -> d | E52: =+E32 -> e | F52: =+F32 -> f | G52: =+G32 -> g | H52: =+H32 -> h | ... R52: =+R32 -> r = q/h
A53: =IF('Direct Labor Rate Schedule'!$A$10="","",'Direct Labor Rate Schedule'!$A$10)
A54: =A34 | B54: =B34 -> 0 | C54: =C34 -> Program Manager | D54: Enter P or S | F54: =G54/AnnualProductiveHours -> 0.97916667 | G54: 1880 | H54: ='Direct Labor Rate Schedule'!H11 -> 0 | I54: =ROUND((+H54*$I$50),2) -> 0 | J54: =ROUND((+H54*$J$50),2) -> 0 | K54: =+H54+SUM(I54:J54) -> 0 | L54: =ROUND((+G54*K54),2) -> 0 | M54: =ROUND((+L54*$M$50),2) -> 0 | N54: =SUM(L54:M54) -> 0 | O54: =ROUND((+N54*$O$50),2) -> 0 | P54: =SUM(N54:O54) -> 0 | Q54: =IFERROR((+P54/G54),"") -> 0 | R54: =IFERROR(Q54/H54-1,"")
A55: =A35 | B55: =B35 -> 0 | C55: =C35 -> Senior Analyst | D55: Enter P or S | F55: =G55/AnnualProductiveHours -> 46.005208 | G55: 88330 | H55: ='Direct Labor Rate Schedule'!H12 -> 0 | I55: =ROUND((+H55*$I$50),2) -> 0 | J55: =ROUND((+H55*$J$50),2) -> 0 | K55: =+H55+SUM(I55:J55) -> 0 | L55: =ROUND((+G55*K55),2) -> 0 | M55: =ROUND((+L55*$M$50),2) -> 0 | N55: =SUM(L55:M55) -> 0 | O55: =ROUND((+N55*$O$50),2) -> 0 | P55: =SUM(N55:O55) -> 0 | Q55: =IFERROR((+P55/G55),"") -> 0 | R55: =IFERROR(Q55/H55-1,"")
A56: =A36 | B56: =B36 -> 0 | C56: =C36 -> Analyst | D56: Enter P or S | F56: =G56/AnnualProductiveHours -> 2.9375 | G56: 5640 | H56: ='Direct Labor Rate Schedule'!H13 -> 0 | I56: =ROUND((+H56*$I$50),2) -> 0 | J56: =ROUND((+H56*$J$50),2) -> 0 | K56: =+H56+SUM(I56:J56) -> 0 | L56: =ROUND((+G56*K56),2) -> 0 | M56: =ROUND((+L56*$M$50),2) -> 0 | N56: =SUM(L56:M56) -> 0 | O56: =ROUND((+N56*$O$50),2) -> 0 | P56: =SUM(N56:O56) -> 0 | Q56: =IFERROR((+P56/G56),"") -> 0 | R56: =IFERROR(Q56/H56-1,"")
A57: =A37 | B57: =B37 -> 0 | C57: =C37 -> Junior Analyst | D57: Enter P or S | F57: =G57/AnnualProductiveHours -> 2.9375 | G57: 5640 | H57: ='Direct Labor Rate Schedule'!H14 -> 0 | I57: =ROUND((+H57*$I$50),2) -> 0 | J57: =ROUND((+H57*$J$50),2) -> 0 | K57: =+H57+SUM(I57:J57) -> 0 | L57: =ROUND((+G57*K57),2) -> 0 | M57: =ROUND((+L57*$M$50),2) -> 0 | N57: =SUM(L57:M57) -> 0 | O57: =ROUND((+N57*$O$50),2) -> 0 | P57: =SUM(N57:O57) -> 0 | Q57: =IFERROR((+P57/G57),"") -> 0 | R57: =IFERROR(Q57/H57-1,"")
A58: =A38 | B58: =B38 -> 0 | C58: =C38 -> Senior Operations Research Analyst | D58: Enter P or S | F58: =G58/AnnualProductiveHours -> 2.9375 | G58: 5640 | H58: ='Direct Labor Rate Schedule'!H15 -> 0 | I58: =ROUND((+H58*$I$50),2) -> 0 | J58: =ROUND((+H58*$J$50),2) -> 0 | K58: =+H58+SUM(I58:J58) -> 0 | L58: =ROUND((+G58*K58),2) -> 0 | M58: =ROUND((+L58*$M$50),2) -> 0 | N58: =SUM(L58:M58) -> 0 | O58: =ROUND((+N58*$O$50),2) -> 0 | P58: =SUM(N58:O58) -> 0 | Q58: =IFERROR((+P58/G58),"") -> 0 | R58: =IFERROR(Q58/H58-1,"")
A59: =A39 | B59: =B39 -> 0 | C59: =C39 -> Operations Research Analyst | D59: Enter P or S | F59: =G59/AnnualProductiveHours -> 1.9583333 | G59: 3760 | H59: ='Direct Labor Rate Schedule'!H16 -> 0 | I59: =ROUND((+H59*$I$50),2) -> 0 | J59: =ROUND((+H59*$J$50),2) -> 0 | K59: =+H59+SUM(I59:J59) -> 0 | L59: =ROUND((+G59*K59),2) -> 0 | M59: =ROUND((+L59*$M$50),2) -> 0 | N59: =SUM(L59:M59) -> 0 | O59: =ROUND((+N59*$O$50),2) -> 0 | P59: =SUM(N59:O59) -> 0 | Q59: =IFERROR((+P59/G59),"") -> 0 | R59: =IFERROR(Q59/H59-1,"")
A60: =A40 | B60: =B40 -> 0 | C60: =C40 -> Graphics Design Senior Analyst | D60: Enter P or S | F60: =G60/AnnualProductiveHours -> 0.97916667 | G60: 1880 | H60: ='Direct Labor Rate Schedule'!H17 -> 0 | I60: =ROUND((+H60*$I$50),2) -> 0 | J60: =ROUND((+H60*$J$50),2) -> 0 | K60: =+H60+SUM(I60:J60) -> 0 | L60: =ROUND((+G60*K60),2) -> 0 | M60: =ROUND((+L60*$M$50),2) -> 0 | N60: =SUM(L60:M60) -> 0 | O60: =ROUND((+N60*$O$50),2) -> 0 | P60: =SUM(N60:O60) -> 0 | Q60: =IFERROR((+P60/G60),"") -> 0 | R60: =IFERROR(Q60/H60-1,"")
A61: =A41 | B61: =B41 -> 0 | C61: =C41 -> Force Documentation Senior Analyst | D61: Enter P or S | F61: =G61/AnnualProductiveHours -> 0.97916667 | G61: 1880 | H61: ='Direct Labor Rate Schedule'!H18 -> 0 | I61: =ROUND((+H61*$I$50),2) -> 0 | J61: =ROUND((+H61*$J$50),2) -> 0 | K61: =+H61+SUM(I61:J61) -> 0 | L61: =ROUND((+G61*K61),2) -> 0 | M61: =ROUND((+L61*$M$50),2) -> 0 | N61: =SUM(L61:M61) -> 0 | O61: =ROUND((+N61*$O$50),2) -> 0 | P61: =SUM(N61:O61) -> 0 | Q61: =IFERROR((+P61/G61),"") -> 0 | R61: =IFERROR(Q61/H61-1,"")
A62: =A42 | B62: =B42 -> 0 | C62: =C42 -> 0 | D62: Enter P or S | F62: =G62/AnnualProductiveHours -> 0 | G62: 0 | H62: ='Direct Labor Rate Schedule'!H19 -> 0 | I62: =ROUND((+H62*$I$50),2) -> 0 | J62: =ROUND((+H62*$J$50),2) -> 0 | K62: =+H62+SUM(I62:J62) -> 0 | L62: =ROUND((+G62*K62),2) -> 0 | M62: =ROUND((+L62*$M$50),2) -> 0 | N62: =SUM(L62:M62) -> 0 | O62: =ROUND((+N62*$O$50),2) -> 0 | P62: =SUM(N62:O62) -> 0 | Q62: =IFERROR((+P62/G62),"") | R62: =IFERROR(Q62/H62-1,"")
A63: =A43 | B63: =B43 -> 0 | C63: =C43 -> 0 | D63: Enter P or S | F63: =G63/AnnualProductiveHours -> 0 | G63: 0 | H63: ='Direct Labor Rate Schedule'!H20 -> 0 | I63: =ROUND((+H63*$I$50),2) -> 0 | J63: =ROUND((+H63*$J$50),2) -> 0 | K63: =+H63+SUM(I63:J63) -> 0 | L63: =ROUND((+G63*K63),2) -> 0 | M63: =ROUND((+L63*$M$50),2) -> 0 | N63: =SUM(L63:M63) -> 0 | O63: =ROUND((+N63*$O$50),2) -> 0 | P63: =SUM(N63:O63) -> 0 | Q63: =IFERROR((+P63/G63),"") | R63: =IFERROR(Q63/H63-1,"")
A64: =A44 | B64: =B44 -> 0 | C64: =C44 -> 0 | D64: Enter P or S | F64: =G64/AnnualProductiveHours -> 0 | G64: 0 | H64: ='Direct Labor Rate Schedule'!H21 -> 0 | I64: =ROUND((+H64*$I$50),2) -> 0 | J64: =ROUND((+H64*$J$50),2) -> 0 | K64: =+H64+SUM(I64:J64) -> 0 | L64: =ROUND((+G64*K64),2) -> 0 | M64: =ROUND((+L64*$M$50),2) -> 0 | N64: =SUM(L64:M64) -> 0 | O64: =ROUND((+N64*$O$50),2) -> 0 | P64: =SUM(N64:O64) -> 0 | Q64: =IFERROR((+P64/G64),"") | R64: =IFERROR(Q64/H64-1,"")
A65: =A45 | B65: =B45 -> 0 | C65: =C45 -> 0 | D65: Enter P or S | F65: =G65/AnnualProductiveHours -> 0 | G65: 0 | H65: ='Direct Labor Rate Schedule'!H22 -> 0 | I65: =ROUND((+H65*$I$50),2) -> 0 | J65: =ROUND((+H65*$J$50),2) -> 0 | K65: =+H65+SUM(I65:J65) -> 0 | L65: =ROUND((+G65*K65),2) -> 0 | M65: =ROUND((+L65*$M$50),2) -> 0 | N65: =SUM(L65:M65) -> 0 | O65: =ROUND((+N65*$O$50),2) -> 0 | P65: =SUM(N65:O65) -> 0 | Q65: =IFERROR((+P65/G65),"") | R65: =IFERROR(Q65/H65-1,"")
A66: Total: | F66: =SUM(F54:F65) -> 59.713542 | G66: =SUM(G54:G65) -> 114650 | H66: =SUMPRODUCT(H54:H65,$G54:$G65) -> 0 | I66: =SUMPRODUCT(I54:I65,$G54:$G65) -> 0 | J66: =SUMPRODUCT(J54:J65,$G54:$G65) -> 0 | K66: =SUMPRODUCT(K54:K65,$G54:$G65) -> 0 | L66: =SUM(L54:L65) -> 0 | M66: =SUM(M54:M65) -> 0 | N66: =SUM(N54:N65) -> 0 | O66: =SUM(O54:O65) -> 0 | P66: =SUM(P54:P65) -> 0 | Q66: =SUMPRODUCT(Q54:Q65,$G54:$G65) -> 0
A67: Weighted Average: | G67: =G66/SUM(F54:F65) -> 1920 | H67: =H66/$G66 -> 0 | I67: =I66/$G66 -> 0 | J67: =J66/$G66 -> 0 | K67: =K66/$G66 -> 0 | L67: =L66/$G66 -> 0 | M67: =M66/$G66 -> 0 | N67: =N66/$G66 -> 0 | O67: =O66/$G66 -> 0 | ... Q67: =Q66/$G66 -> 0 | R67: =Q67/H67 -> #DIV/0!
G69: Direct Cost | I69: Indirect Cost
C70: CLIN 2001 - OY2 Labor | I70: ='Indirect Rate Summary'!C24 -> 0 | J70: ='Indirect Rate Summary'!D24 -> 0 | M70: ='Indirect Rate Summary'!E24 -> 0 | O70: ='Indirect Rate Summary'!F24 -> 0
A71: =+A51 -> Location (Note 1) | B71: =+B51 -> Labor Type (Note 2) | C71: =+C51 -> Labor Categories (Note 3) | D71: =+D51 -> Effort To Be Performed By The Prime (P) or Subcontractor (S) (Note 4) | E71: =+E51 -> If Column D=S, Enter Name of Subcontractor(s) (Note 5) | F71: =+F51 -> FTEs (Note 6) | G71: =+G51 -> Total Productive Hours (Note 7) | H71: =+H51 -> Hourly Base Pay Rate (Note 8) | ... R71: =+R51 -> Wrap Rate
A72: =+A52 -> a | B72: =+B52 -> b | C72: =+C52 -> c | D72: =+D52 -> d | E72: =+E52 -> e | F72: =+F52 -> f | G72: =+G52 -> g | H72: =+H52 -> h | ... R72: =+R52 -> r = q/h
A73: =IF('Direct Labor Rate Schedule'!$A$10="","",'Direct Labor Rate Schedule'!$A$10)
A74: =A54 | B74: =B54 -> 0 | C74: =C54 -> Program Manager | D74: Enter P or S | F74: =G74/AnnualProductiveHours -> 0.97916667 | G74: 1880 | H74: ='Direct Labor Rate Schedule'!J11 -> 0 | I74: =ROUND((+H74*$I$70),2) -> 0 | J74: =ROUND((+H74*$J$70),2) -> 0 | K74: =+H74+SUM(I74:J74) -> 0 | L74: =ROUND((+G74*K74),2) -> 0 | M74: =ROUND((+L74*$M$70),2) -> 0 | N74: =SUM(L74:M74) -> 0 | O74: =ROUND((+N74*$O$70),2) -> 0 | P74: =SUM(N74:O74) -> 0 | Q74: =IFERROR((+P74/G74),"") -> 0 | R74: =IFERROR(Q74/H74-1,"")
A75: =A55 | B75: =B55 -> 0 | C75: =C55 -> Senior Analyst | D75: Enter P or S | F75: =G75/AnnualProductiveHours -> 46.005208 | G75: 88330 | H75: ='Direct Labor Rate Schedule'!J12 -> 0 | I75: =ROUND((+H75*$I$70),2) -> 0 | J75: =ROUND((+H75*$J$70),2) -> 0 | K75: =+H75+SUM(I75:J75) -> 0 | L75: =ROUND((+G75*K75),2) -> 0 | M75: =ROUND((+L75*$M$70),2) -> 0 | N75: =SUM(L75:M75) -> 0 | O75: =ROUND((+N75*$O$70),2) -> 0 | P75: =SUM(N75:O75) -> 0 | Q75: =IFERROR((+P75/G75),"") -> 0 | R75: =IFERROR(Q75/H75-1,"")
A76: =A56 | B76: =B56 -> 0 | C76: =C56 -> Analyst | D76: Enter P or S | F76: =G76/AnnualProductiveHours -> 2.9375 | G76: 5640 | H76: ='Direct Labor Rate Schedule'!J13 -> 0 | I76: =ROUND((+H76*$I$70),2) -> 0 | J76: =ROUND((+H76*$J$70),2) -> 0 | K76: =+H76+SUM(I76:J76) -> 0 | L76: =ROUND((+G76*K76),2) -> 0 | M76: =ROUND((+L76*$M$70),2) -> 0 | N76: =SUM(L76:M76) -> 0 | O76: =ROUND((+N76*$O$70),2) -> 0 | P76: =SUM(N76:O76) -> 0 | Q76: =IFERROR((+P76/G76),"") -> 0 | R76: =IFERROR(Q76/H76-1,"")
A77: =A57 | B77: =B57 -> 0 | C77: =C57 -> Junior Analyst | D77: Enter P or S | F77: =G77/AnnualProductiveHours -> 2.9375 | G77: 5640 | H77: ='Direct Labor Rate Schedule'!J14 -> 0 | I77: =ROUND((+H77*$I$70),2) -> 0 | J77: =ROUND((+H77*$J$70),2) -> 0 | K77: =+H77+SUM(I77:J77) -> 0 | L77: =ROUND((+G77*K77),2) -> 0 | M77: =ROUND((+L77*$M$70),2) -> 0 | N77: =SUM(L77:M77) -> 0 | O77: =ROUND((+N77*$O$70),2) -> 0 | P77: =SUM(N77:O77) -> 0 | Q77: =IFERROR((+P77/G77),"") -> 0 | R77: =IFERROR(Q77/H77-1,"")
A78: =A58 | B78: =B58 -> 0 | C78: =C58 -> Senior Operations Research Analyst | D78: Enter P or S | F78: =G78/AnnualProductiveHours -> 2.9375 | G78: 5640 | H78: ='Direct Labor Rate Schedule'!J15 -> 0 | I78: =ROUND((+H78*$I$70),2) -> 0 | J78: =ROUND((+H78*$J$70),2) -> 0 | K78: =+H78+SUM(I78:J78) -> 0 | L78: =ROUND((+G78*K78),2) -> 0 | M78: =ROUND((+L78*$M$70),2) -> 0 | N78: =SUM(L78:M78) -> 0 | O78: =ROUND((+N78*$O$70),2) -> 0 | P78: =SUM(N78:O78) -> 0 | Q78: =IFERROR((+P78/G78),"") -> 0 | R78: =IFERROR(Q78/H78-1,"")
A79: =A59 | B79: =B59 -> 0 | C79: =C59 -> Operations Research Analyst | D79: Enter P or S | F79: =G79/AnnualProductiveHours -> 1.9583333 | G79: 3760 | H79: ='Direct Labor Rate Schedule'!J16 -> 0 | I79: =ROUND((+H79*$I$70),2) -> 0 | J79: =ROUND((+H79*$J$70),2) -> 0 | K79: =+H79+SUM(I79:J79) -> 0 | L79: =ROUND((+G79*K79),2) -> 0 | M79: =ROUND((+L79*$M$70),2) -> 0 | N79: =SUM(L79:M79) -> 0 | O79: =ROUND((+N79*$O$70),2) -> 0 | P79: =SUM(N79:O79) -> 0 | Q79: =IFERROR((+P79/G79),"") -> 0 | R79: =IFERROR(Q79/H79-1,"")
A80: =A60 | B80: =B60 -> 0 | C80: =C60 -> Graphics Design Senior Analyst | D80: Enter P or S | F80: =G80/AnnualProductiveHours -> 0.97916667 | G80: 1880 | H80: ='Direct Labor Rate Schedule'!J17 -> 0 | I80: =ROUND((+H80*$I$70),2) -> 0 | J80: =ROUND((+H80*$J$70),2) -> 0 | K80: =+H80+SUM(I80:J80) -> 0 | L80: =ROUND((+G80*K80),2) -> 0 | M80: =ROUND((+L80*$M$70),2) -> 0 | N80: =SUM(L80:M80) -> 0 | O80: =ROUND((+N80*$O$70),2) -> 0 | P80: =SUM(N80:O80) -> 0 | Q80: =IFERROR((+P80/G80),"") -> 0 | R80: =IFERROR(Q80/H80-1,"")
A81: =A61 | B81: =B61 -> 0 | C81: =C61 -> Force Documentation Senior Analyst | D81: Enter P or S | F81: =G81/AnnualProductiveHours -> 0.97916667 | G81: 1880 | H81: ='Direct Labor Rate Schedule'!J18 -> 0 | I81: =ROUND((+H81*$I$70),2) -> 0 | J81: =ROUND((+H81*$J$70),2) -> 0 | K81: =+H81+SUM(I81:J81) -> 0 | L81: =ROUND((+G81*K81),2) -> 0 | M81: =ROUND((+L81*$M$70),2) -> 0 | N81: =SUM(L81:M81) -> 0 | O81: =ROUND((+N81*$O$70),2) -> 0 | P81: =SUM(N81:O81) -> 0 | Q81: =IFERROR((+P81/G81),"") -> 0 | R81: =IFERROR(Q81/H81-1,"")
A82: =A62 | B82: =B62 -> 0 | C82: =C62 -> 0 | D82: Enter P or S | F82: =G82/AnnualProductiveHours -> 0 | G82: 0 | H82: ='Direct Labor Rate Schedule'!J19 -> 0 | I82: =ROUND((+H82*$I$70),2) -> 0 | J82: =ROUND((+H82*$J$70),2) -> 0 | K82: =+H82+SUM(I82:J82) -> 0 | L82: =ROUND((+G82*K82),2) -> 0 | M82: =ROUND((+L82*$M$70),2) -> 0 | N82: =SUM(L82:M82) -> 0 | O82: =ROUND((+N82*$O$70),2) -> 0 | P82: =SUM(N82:O82) -> 0 | Q82: =IFERROR((+P82/G82),"") | R82: =IFERROR(Q82/H82-1,"")
A83: =A63 | B83: =B63 -> 0 | C83: =C63 -> 0 | D83: Enter P or S | F83: =G83/AnnualProductiveHours -> 0 | G83: 0 | H83: ='Direct Labor Rate Schedule'!J20 -> 0 | I83: =ROUND((+H83*$I$70),2) -> 0 | J83: =ROUND((+H83*$J$70),2) -> 0 | K83: =+H83+SUM(I83:J83) -> 0 | L83: =ROUND((+G83*K83),2) -> 0 | M83: =ROUND((+L83*$M$70),2) -> 0 | N83: =SUM(L83:M83) -> 0 | O83: =ROUND((+N83*$O$70),2) -> 0 | P83: =SUM(N83:O83) -> 0 | Q83: =IFERROR((+P83/G83),"") | R83: =IFERROR(Q83/H83-1,"")
A84: =A64 | B84: =B64 -> 0 | C84: =C64 -> 0 | D84: Enter P or S | F84: =G84/AnnualProductiveHours -> 0 | G84: 0 | H84: ='Direct Labor Rate Schedule'!J21 -> 0 | I84: =ROUND((+H84*$I$70),2) -> 0 | J84: =ROUND((+H84*$J$70),2) -> 0 | K84: =+H84+SUM(I84:J84) -> 0 | L84: =ROUND((+G84*K84),2) -> 0 | M84: =ROUND((+L84*$M$70),2) -> 0 | N84: =SUM(L84:M84) -> 0 | O84: =ROUND((+N84*$O$70),2) -> 0 | P84: =SUM(N84:O84) -> 0 | Q84: =IFERROR((+P84/G84),"") | R84: =IFERROR(Q84/H84-1,"")
A85: =A65 | B85: =B65 -> 0 | C85: =C65 -> 0 | D85: Enter P or S | F85: =G85/AnnualProductiveHours -> 0 | G85: 0 | H85: ='Direct Labor Rate Schedule'!J22 -> 0 | I85: =ROUND((+H85*$I$70),2) -> 0 | J85: =ROUND((+H85*$J$70),2) -> 0 | K85: =+H85+SUM(I85:J85) -> 0 | L85: =ROUND((+G85*K85),2) -> 0 | M85: =ROUND((+L85*$M$70),2) -> 0 | N85: =SUM(L85:M85) -> 0 | O85: =ROUND((+N85*$O$70),2) -> 0 | P85: =SUM(N85:O85) -> 0 | Q85: =IFERROR((+P85/G85),"") | R85: =IFERROR(Q85/H85-1,"")
A86: Total: | F86: =SUM(F74:F85) -> 59.713542 | G86: =SUM(G74:G85) -> 114650 | H86: =SUMPRODUCT(H74:H85,$G74:$G85) -> 0 | I86: =SUMPRODUCT(I74:I85,$G74:$G85) -> 0 | J86: =SUMPRODUCT(J74:J85,$G74:$G85) -> 0 | K86: =SUMPRODUCT(K74:K85,$G74:$G85) -> 0 | L86: =SUM(L74:L85) -> 0 | M86: =SUM(M74:M85) -> 0 | N86: =SUM(N74:N85) -> 0 | O86: =SUM(O74:O85) -> 0 | P86: =SUM(P74:P85) -> 0 | Q86: =SUMPRODUCT(Q74:Q85,$G74:$G85) -> 0
A87: Weighted Average: | G87: =G86/SUM(F74:F85) -> 1920 | H87: =H86/$G86 -> 0 | I87: =I86/$G86 -> 0 | J87: =J86/$G86 -> 0 | K87: =K86/$G86 -> 0 | L87: =L86/$G86 -> 0 | M87: =M86/$G86 -> 0 | N87: =N86/$G86 -> 0 | O87: =O86/$G86 -> 0 | ... Q87: =Q86/$G86 -> 0 | R87: =Q87/H87 -> #DIV/0!
G89: Direct Cost | I89: Indirect Cost
C90: CLIN 3001 - OY3 Labor | I90: ='Indirect Rate Summary'!C31 -> 0 | J90: ='Indirect Rate Summary'!D31 -> 0 | M90: ='Indirect Rate Summary'!E31 -> 0 | O90: ='Indirect Rate Summary'!F31 -> 0
A91: =+A71 -> Location (Note 1) | B91: =+B71 -> Labor Type (Note 2) | C91: =+C71 -> Labor Categories (Note 3) | D91: =+D71 -> Effort To Be Performed By The Prime (P) or Subcontractor (S) (Note 4) | E91: =+E71 -> If Column D=S, Enter Name of Subcontractor(s) (Note 5) | F91: =+F71 -> FTEs (Note 6) | G91: =+G71 -> Total Productive Hours (Note 7) | H91: =+H71 -> Hourly Base Pay Rate (Note 8) | ... R91: =+R71 -> Wrap Rate
A92: =+A72 -> a | B92: =+B72 -> b | C92: =+C72 -> c | D92: =+D72 -> d | E92: =+E72 -> e | F92: =+F72 -> f | G92: =+G72 -> g | H92: =+H72 -> h | ... R92: =+R72 -> r = q/h
A93: =IF('Direct Labor Rate Schedule'!$A$10="","",'Direct Labor Rate Schedule'!$A$10)
A94: =A74 | B94: =B74 -> 0 | C94: =C74 -> Program Manager | D94: Enter P or S | F94: =G94/AnnualProductiveHours -> 0.97916667 | G94: 1880 | H94: ='Direct Labor Rate Schedule'!L11 -> 0 | I94: =ROUND((+H94*$I$90),2) -> 0 | J94: =ROUND((+H94*$J$90),2) -> 0 | K94: =+H94+SUM(I94:J94) -> 0 | L94: =ROUND((+G94*K94),2) -> 0 | M94: =ROUND((+L94*$M$90),2) -> 0 | N94: =SUM(L94:M94) -> 0 | O94: =ROUND((+N94*$O$90),2) -> 0 | P94: =SUM(N94:O94) -> 0 | Q94: =IFERROR((+P94/G94),"") -> 0 | R94: =IFERROR(Q94/H94-1,"")
A95: =A75 | B95: =B75 -> 0 | C95: =C75 -> Senior Analyst | D95: Enter P or S | F95: =G95/AnnualProductiveHours -> 46.005208 | G95: 88330 | H95: ='Direct Labor Rate Schedule'!L12 -> 0 | I95: =ROUND((+H95*$I$90),2) -> 0 | J95: =ROUND((+H95*$J$90),2) -> 0 | K95: =+H95+SUM(I95:J95) -> 0 | L95: =ROUND((+G95*K95),2) -> 0 | M95: =ROUND((+L95*$M$90),2) -> 0 | N95: =SUM(L95:M95) -> 0 | O95: =ROUND((+N95*$O$90),2) -> 0 | P95: =SUM(N95:O95) -> 0 | Q95: =IFERROR((+P95/G95),"") -> 0 | R95: =IFERROR(Q95/H95-1,"")
A96: =A76 | B96: =B76 -> 0 | C96: =C76 -> Analyst | D96: Enter P or S | F96: =G96/AnnualProductiveHours -> 2.9375 | G96: 5640 | H96: ='Direct Labor Rate Schedule'!L13 -> 0 | I96: =ROUND((+H96*$I$90),2) -> 0 | J96: =ROUND((+H96*$J$90),2) -> 0 | K96: =+H96+SUM(I96:J96) -> 0 | L96: =ROUND((+G96*K96),2) -> 0 | M96: =ROUND((+L96*$M$90),2) -> 0 | N96: =SUM(L96:M96) -> 0 | O96: =ROUND((+N96*$O$90),2) -> 0 | P96: =SUM(N96:O96) -> 0 | Q96: =IFERROR((+P96/G96),"") -> 0 | R96: =IFERROR(Q96/H96-1,"")
A97: =A77 | B97: =B77 -> 0 | C97: =C77 -> Junior Analyst | D97: Enter P or S | F97: =G97/AnnualProductiveHours -> 2.9375 | G97: 5640 | H97: ='Direct Labor Rate Schedule'!L14 -> 0 | I97: =ROUND((+H97*$I$90),2) -> 0 | J97: =ROUND((+H97*$J$90),2) -> 0 | K97: =+H97+SUM(I97:J97) -> 0 | L97: =ROUND((+G97*K97),2) -> 0 | M97: =ROUND((+L97*$M$90),2) -> 0 | N97: =SUM(L97:M97) -> 0 | O97: =ROUND((+N97*$O$90),2) -> 0 | P97: =SUM(N97:O97) -> 0 | Q97: =IFERROR((+P97/G97),"") -> 0 | R97: =IFERROR(Q97/H97-1,"")
A98: =A78 | B98: =B78 -> 0 | C98: =C78 -> Senior Operations Research Analyst | D98: Enter P or S | F98: =G98/AnnualProductiveHours -> 2.9375 | G98: 5640 | H98: ='Direct Labor Rate Schedule'!L15 -> 0 | I98: =ROUND((+H98*$I$90),2) -> 0 | J98: =ROUND((+H98*$J$90),2) -> 0 | K98: =+H98+SUM(I98:J98) -> 0 | L98: =ROUND((+G98*K98),2) -> 0 | M98: =ROUND((+L98*$M$90),2) -> 0 | N98: =SUM(L98:M98) -> 0 | O98: =ROUND((+N98*$O$90),2) -> 0 | P98: =SUM(N98:O98) -> 0 | Q98: =IFERROR((+P98/G98),"") -> 0 | R98: =IFERROR(Q98/H98-1,"")
A99: =A79 | B99: =B79 -> 0 | C99: =C79 -> Operations Research Analyst | D99: Enter P or S | F99: =G99/AnnualProductiveHours -> 1.9583333 | G99: 3760 | H99: ='Direct Labor Rate Schedule'!L16 -> 0 | I99: =ROUND((+H99*$I$90),2) -> 0 | J99: =ROUND((+H99*$J$90),2) -> 0 | K99: =+H99+SUM(I99:J99) -> 0 | L99: =ROUND((+G99*K99),2) -> 0 | M99: =ROUND((+L99*$M$90),2) -> 0 | N99: =SUM(L99:M99) -> 0 | O99: =ROUND((+N99*$O$90),2) -> 0 | P99: =SUM(N99:O99) -> 0 | Q99: =IFERROR((+P99/G99),"") -> 0 | R99: =IFERROR(Q99/H99-1,"")
A100: =A80 | B100: =B80 -> 0 | C100: =C80 -> Graphics Design Senior Analyst | D100: Enter P or S | F100: =G100/AnnualProductiveHours -> 0.97916667 | G100: 1880 | H100: ='Direct Labor Rate Schedule'!L17 -> 0 | I100: =ROUND((+H100*$I$90),2) -> 0 | J100: =ROUND((+H100*$J$90),2) -> 0 | K100: =+H100+SUM(I100:J100) -> 0 | L100: =ROUND((+G100*K100),2) -> 0 | M100: =ROUND((+L100*$M$90),2) -> 0 | N100: =SUM(L100:M100) -> 0 | O100: =ROUND((+N100*$O$90),2) -> 0 | P100: =SUM(N100:O100) -> 0 | Q100: =IFERROR((+P100/G100),"") -> 0 | R100: =IFERROR(Q100/H100-1,"")
A101: =A81 | B101: =B81 -> 0 | C101: =C81 -> Force Documentation Senior Analyst | D101: Enter P or S | F101: =G101/AnnualProductiveHours -> 0.97916667 | G101: 1880 | H101: ='Direct Labor Rate Schedule'!L18 -> 0 | I101: =ROUND((+H101*$I$90),2) -> 0 | J101: =ROUND((+H101*$J$90),2) -> 0 | K101: =+H101+SUM(I101:J101) -> 0 | L101: =ROUND((+G101*K101),2) -> 0 | M101: =ROUND((+L101*$M$90),2) -> 0 | N101: =SUM(L101:M101) -> 0 | O101: =ROUND((+N101*$O$90),2) -> 0 | P101: =SUM(N101:O101) -> 0 | Q101: =IFERROR((+P101/G101),"") -> 0 | R101: =IFERROR(Q101/H101-1,"")
A102: =A82 | B102: =B82 -> 0 | C102: =C82 -> 0 | D102: Enter P or S | F102: =G102/AnnualProductiveHours -> 0 | G102: 0 | H102: ='Direct Labor Rate Schedule'!L19 -> 0 | I102: =ROUND((+H102*$I$90),2) -> 0 | J102: =ROUND((+H102*$J$90),2) -> 0 | K102: =+H102+SUM(I102:J102) -> 0 | L102: =ROUND((+G102*K102),2) -> 0 | M102: =ROUND((+L102*$M$90),2) -> 0 | N102: =SUM(L102:M102) -> 0 | O102: =ROUND((+N102*$O$90),2) -> 0 | P102: =SUM(N102:O102) -> 0 | Q102: =IFERROR((+P102/G102),"") | R102: =IFERROR(Q102/H102-1,"")
A103: =A83 | B103: =B83 -> 0 | C103: =C83 -> 0 | D103: Enter P or S | F103: =G103/AnnualProductiveHours -> 0 | G103: 0 | H103: ='Direct Labor Rate Schedule'!L20 -> 0 | I103: =ROUND((+H103*$I$90),2) -> 0 | J103: =ROUND((+H103*$J$90),2) -> 0 | K103: =+H103+SUM(I103:J103) -> 0 | L103: =ROUND((+G103*K103),2) -> 0 | M103: =ROUND((+L103*$M$90),2) -> 0 | N103: =SUM(L103:M103) -> 0 | O103: =ROUND((+N103*$O$90),2) -> 0 | P103: =SUM(N103:O103) -> 0 | Q103: =IFERROR((+P103/G103),"") | R103: =IFERROR(Q103/H103-1,"")
A104: =A84 | B104: =B84 -> 0 | C104: =C84 -> 0 | D104: Enter P or S | F104: =G104/AnnualProductiveHours -> 0 | G104: 0 | H104: ='Direct Labor Rate Schedule'!L21 -> 0 | I104: =ROUND((+H104*$I$90),2) -> 0 | J104: =ROUND((+H104*$J$90),2) -> 0 | K104: =+H104+SUM(I104:J104) -> 0 | L104: =ROUND((+G104*K104),2) -> 0 | M104: =ROUND((+L104*$M$90),2) -> 0 | N104: =SUM(L104:M104) -> 0 | O104: =ROUND((+N104*$O$90),2) -> 0 | P104: =SUM(N104:O104) -> 0 | Q104: =IFERROR((+P104/G104),"") | R104: =IFERROR(Q104/H104-1,"")
A105: =A85 | B105: =B85 -> 0 | C105: =C85 -> 0 | D105: Enter P or S | F105: =G105/AnnualProductiveHours -> 0 | G105: 0 | H105: ='Direct Labor Rate Schedule'!L22 -> 0 | I105: =ROUND((+H105*$I$90),2) -> 0 | J105: =ROUND((+H105*$J$90),2) -> 0 | K105: =+H105+SUM(I105:J105) -> 0 | L105: =ROUND((+G105*K105),2) -> 0 | M105: =ROUND((+L105*$M$90),2) -> 0 | N105: =SUM(L105:M105) -> 0 | O105: =ROUND((+N105*$O$90),2) -> 0 | P105: =SUM(N105:O105) -> 0 | Q105: =IFERROR((+P105/G105),"") | R105: =IFERROR(Q105/H105-1,"")
...

Sheet Surge Labor Detail
A1: Labor Cost Detail Spreadsheet
A2: ="Solicitation Number: "&Instructions!H9&"" -> Solicitation Number: W91CRB-25-R-0002
A3: ="Name of Action: "&Instructions!H10 -> Name of Action: Force Development
A4: ="Prime Contractor/Subcontractor Name/Division: "&Instructions!H15 -> Prime Contractor/Subcontractor Name/Division:
A5: ="Period of Performance: "&Instructions!H11 -> Period of Performance:
A6: ="Date of Proposal:"&IF(ISBLANK(Instructions!H18)," TBD",(TEXT(Instructions!H18," mm/dd/yyyy"))) -> Date of Proposal: TBD
A7: ="Annual Productive Hours: "&AnnualProductiveHours -> Annual Productive Hours: 1920
G9: Direct Labor | I9: Indirect Cost
C10: CLIN 0002 - Base Period Surge Option (FD, PAE, CAA) | I10: ='Indirect Rate Summary'!C10 -> 0 | J10: ='Indirect Rate Summary'!D10 -> 0 | M10: ='Indirect Rate Summary'!E10 -> 0 | O10: ='Indirect Rate Summary'!F10 -> 0
A11: Location (Note 1) | B11: Labor Type (Note 2) | C11: Labor Categories (Note 3) | D11: Effort To Be Performed By The Prime (P) or Subcontractor (S) (Note 4) | E11: If Column D=S, Enter Name of Subcontractor(s) (Note 5) | F11: FTEs (Note 6) | G11: Total Productive Hours (Note 7) | H11: Hourly Base Pay Rate (Note 8) | I11: Fringe (Note 9) | J11: Overhead (Note 10) | K11: Prime/Sub Hourly Rate Before Application Of Prime G&A & Fee (IF Col C=S Enter Sub Rate) (Note 11) | L11: Total Prime & Sub Labor Before Prime G&A & Fee | M11: G&A (Note 12) | N11: Total Cost | O11: Fee | P11: Total Price | Q11: Proposal Fully Burdened Hourly Billing Rate | R11: Wrap Rate
A12: a | B12: b | C12: c | D12: d | E12: e | F12: f | G12: g | H12: h | I12: i | J12: j | K12: k = h + i + j | L12: l = g x k | M12: m | N12: n = l + o | O12: o | P12: p = n + o | Q12: q = p/g | R12: r = q/h
A13: =IF('Direct Labor Rate Schedule'!$A$10="","",'Direct Labor Rate Schedule'!$A$10)
A14: =IF('Direct Labor Rate Schedule'!B18="","",'Direct Labor Rate Schedule'!B11) | B14: ='Direct Labor Rate Schedule'!C11 -> 0 | C14: ='Direct Labor Rate Schedule'!A11 -> Program Manager | D14: Enter P or S | F14: =(G14/AnnualProductiveHours) -> 0 | G14: 0 | H14: ='Direct Labor Rate Schedule'!F11 -> 0 | I14: =ROUND((+H14*$I$10),2) -> 0 | J14: =ROUND((+H14*$J$10),2) -> 0 | K14: =+H14+SUM(I14:J14) -> 0 | L14: =ROUND((+G14*K14),2) -> 0 | M14: =ROUND((+L14*$M$10),2) -> 0 | N14: =SUM(L14:M14) -> 0 | O14: =ROUND((+N14*$O$10),2) -> 0 | P14: =SUM(N14:O14) -> 0 | Q14: =IFERROR((+P14/G14),"") | R14: =IFERROR(Q14/H14-1,"")
A15: =IF('Direct Labor Rate Schedule'!B19="","",'Direct Labor Rate Schedule'!B12) | B15: ='Direct Labor Rate Schedule'!C12 -> 0 | C15: ='Direct Labor Rate Schedule'!A12 -> Senior Analyst | D15: Enter P or S | F15: =(G15/AnnualProductiveHours) -> 0.97916667 | G15: 1880 | H15: ='Direct Labor Rate Schedule'!F12 -> 0 | I15: =ROUND((+H15*$I$10),2) -> 0 | J15: =ROUND((+H15*$J$10),2) -> 0 | K15: =+H15+SUM(I15:J15) -> 0 | L15: =ROUND((+G15*K15),2) -> 0 | M15: =ROUND((+L15*$M$10),2) -> 0 | N15: =SUM(L15:M15) -> 0 | O15: =ROUND((+N15*$O$10),2) -> 0 | P15: =SUM(N15:O15) -> 0 | Q15: =IFERROR((+P15/G15),"") -> 0 | R15: =IFERROR(Q15/H15-1,"")
A16: =IF('Direct Labor Rate Schedule'!B20="","",'Direct Labor Rate Schedule'!B13) | B16: ='Direct Labor Rate Schedule'!C13 -> 0 | C16: ='Direct Labor Rate Schedule'!A13 -> Analyst | D16: Enter P or S | F16: =(G16/AnnualProductiveHours) -> 0.97916667 | G16: 1880 | H16: ='Direct Labor Rate Schedule'!F13 -> 0 | I16: =ROUND((+H16*$I$10),2) -> 0 | J16: =ROUND((+H16*$J$10),2) -> 0 | K16: =+H16+SUM(I16:J16) -> 0 | L16: =ROUND((+G16*K16),2) -> 0 | M16: =ROUND((+L16*$M$10),2) -> 0 | N16: =SUM(L16:M16) -> 0 | O16: =ROUND((+N16*$O$10),2) -> 0 | P16: =SUM(N16:O16) -> 0 | Q16: =IFERROR((+P16/G16),"") -> 0 | R16: =IFERROR(Q16/H16-1,"")
A17: =IF('Direct Labor Rate Schedule'!B21="","",'Direct Labor Rate Schedule'!B14) | B17: ='Direct Labor Rate Schedule'!C14 -> 0 | C17: ='Direct Labor Rate Schedule'!A14 -> Junior Analyst | D17: Enter P or S | F17: =(G17/AnnualProductiveHours) -> 0 | G17: 0 | H17: ='Direct Labor Rate Schedule'!F14 -> 0 | I17: =ROUND((+H17*$I$10),2) -> 0 | J17: =ROUND((+H17*$J$10),2) -> 0 | K17: =+H17+SUM(I17:J17) -> 0 | L17: =ROUND((+G17*K17),2) -> 0 | M17: =ROUND((+L17*$M$10),2) -> 0 | N17: =SUM(L17:M17) -> 0 | O17: =ROUND((+N17*$O$10),2) -> 0 | P17: =SUM(N17:O17) -> 0 | Q17: =IFERROR((+P17/G17),"") | R17: =IFERROR(Q17/H17-1,"")
A18: =IF('Direct Labor Rate Schedule'!B22="","",'Direct Labor Rate Schedule'!B15) | B18: ='Direct Labor Rate Schedule'!C15 -> 0 | C18: ='Direct Labor Rate Schedule'!A15 -> Senior Operations Research Analyst | D18: Enter P or S | F18: =(G18/AnnualProductiveHours) -> 0.97916667 | G18: 1880 | H18: ='Direct Labor Rate Schedule'!F15 -> 0 | I18: =ROUND((+H18*$I$10),2) -> 0 | J18: =ROUND((+H18*$J$10),2) -> 0 | K18: =+H18+SUM(I18:J18) -> 0 | L18: =ROUND((+G18*K18),2) -> 0 | M18: =ROUND((+L18*$M$10),2) -> 0 | N18: =SUM(L18:M18) -> 0 | O18: =ROUND((+N18*$O$10),2) -> 0 | P18: =SUM(N18:O18) -> 0 | Q18: =IFERROR((+P18/G18),"") -> 0 | R18: =IFERROR(Q18/H18-1,"")
A19: =IF('Direct Labor Rate Schedule'!B23="","",'Direct Labor Rate Schedule'!B16) | B19: ='Direct Labor Rate Schedule'!C16 -> 0 | C19: ='Direct Labor Rate Schedule'!A16 -> Operations Research Analyst | D19: Enter P or S | F19: =(G19/AnnualProductiveHours) -> 0.97916667 | G19: 1880 | H19: ='Direct Labor Rate Schedule'!F16 -> 0 | I19: =ROUND((+H19*$I$10),2) -> 0 | J19: =ROUND((+H19*$J$10),2) -> 0 | K19: =+H19+SUM(I19:J19) -> 0 | L19: =ROUND((+G19*K19),2) -> 0 | M19: =ROUND((+L19*$M$10),2) -> 0 | N19: =SUM(L19:M19) -> 0 | O19: =ROUND((+N19*$O$10),2) -> 0 | P19: =SUM(N19:O19) -> 0 | Q19: =IFERROR((+P19/G19),"") -> 0 | R19: =IFERROR(Q19/H19-1,"")
A20: =IF('Direct Labor Rate Schedule'!B24="","",'Direct Labor Rate Schedule'!B17) | B20: ='Direct Labor Rate Schedule'!C17 -> 0 | C20: ='Direct Labor Rate Schedule'!A17 -> Graphics Design Senior Analyst | D20: Enter P or S | F20: =(G20/AnnualProductiveHours) -> 0 | G20: 0 | H20: ='Direct Labor Rate Schedule'!F17 -> 0 | I20: =ROUND((+H20*$I$10),2) -> 0 | J20: =ROUND((+H20*$J$10),2) -> 0 | K20: =+H20+SUM(I20:J20) -> 0 | L20: =ROUND((+G20*K20),2) -> 0 | M20: =ROUND((+L20*$M$10),2) -> 0 | N20: =SUM(L20:M20) -> 0 | O20: =ROUND((+N20*$O$10),2) -> 0 | P20: =SUM(N20:O20) -> 0 | Q20: =IFERROR((+P20/G20),"") | R20: =IFERROR(Q20/H20-1,"")
A21: =IF('Direct Labor Rate Schedule'!B25="","",'Direct Labor Rate Schedule'!B18) | B21: ='Direct Labor Rate Schedule'!C18 -> 0 | C21: ='Direct Labor Rate Schedule'!A18 -> Force Documentation Senior Analyst | D21: Enter P or S | F21: =(G21/AnnualProductiveHours) -> 0 | G21: 0 | H21: ='Direct Labor Rate Schedule'!F18 -> 0 | I21: =ROUND((+H21*$I$10),2) -> 0 | J21: =ROUND((+H21*$J$10),2) -> 0 | K21: =+H21+SUM(I21:J21) -> 0 | L21: =ROUND((+G21*K21),2) -> 0 | M21: =ROUND((+L21*$M$10),2) -> 0 | N21: =SUM(L21:M21) -> 0 | O21: =ROUND((+N21*$O$10),2) -> 0 | P21: =SUM(N21:O21) -> 0 | Q21: =IFERROR((+P21/G21),"") | R21: =IFERROR(Q21/H21-1,"")
A22: =IF('Direct Labor Rate Schedule'!B26="","",'Direct Labor Rate Schedule'!B19) | B22: ='Direct Labor Rate Schedule'!C19 -> 0 | C22: ='Direct Labor Rate Schedule'!A19 -> 0 | D22: Enter P or S | F22: =(G22/AnnualProductiveHours) -> 0 | G22: 0 | H22: ='Direct Labor Rate Schedule'!F19 -> 0 | I22: =ROUND((+H22*$I$10),2) -> 0 | J22: =ROUND((+H22*$J$10),2) -> 0 | K22: =+H22+SUM(I22:J22) -> 0 | L22: =ROUND((+G22*K22),2) -> 0 | M22: =ROUND((+L22*$M$10),2) -> 0 | N22: =SUM(L22:M22) -> 0 | O22: =ROUND((+N22*$O$10),2) -> 0 | P22: =SUM(N22:O22) -> 0 | Q22: =IFERROR((+P22/G22),"") | R22: =IFERROR(Q22/H22-1,"")
A23: =IF('Direct Labor Rate Schedule'!B27="","",'Direct Labor Rate Schedule'!B20) | B23: ='Direct Labor Rate Schedule'!C20 -> 0 | C23: ='Direct Labor Rate Schedule'!A20 -> 0 | D23: Enter P or S | F23: =(G23/AnnualProductiveHours) -> 0 | G23: 0 | H23: ='Direct Labor Rate Schedule'!F20 -> 0 | I23: =ROUND((+H23*$I$10),2) -> 0 | J23: =ROUND((+H23*$J$10),2) -> 0 | K23: =+H23+SUM(I23:J23) -> 0 | L23: =ROUND((+G23*K23),2) -> 0 | M23: =ROUND((+L23*$M$10),2) -> 0 | N23: =SUM(L23:M23) -> 0 | O23: =ROUND((+N23*$O$10),2) -> 0 | P23: =SUM(N23:O23) -> 0 | Q23: =IFERROR((+P23/G23),"") | R23: =IFERROR(Q23/H23-1,"")
A24: =IF('Direct Labor Rate Schedule'!B28="","",'Direct Labor Rate Schedule'!B21) | B24: ='Direct Labor Rate Schedule'!C21 -> 0 | C24: ='Direct Labor Rate Schedule'!A21 -> 0 | D24: Enter P or S | F24: =(G24/AnnualProductiveHours) -> 0 | G24: 0 | H24: ='Direct Labor Rate Schedule'!F21 -> 0 | I24: =ROUND((+H24*$I$10),2) -> 0 | J24: =ROUND((+H24*$J$10),2) -> 0 | K24: =+H24+SUM(I24:J24) -> 0 | L24: =ROUND((+G24*K24),2) -> 0 | M24: =ROUND((+L24*$M$10),2) -> 0 | N24: =SUM(L24:M24) -> 0 | O24: =ROUND((+N24*$O$10),2) -> 0 | P24: =SUM(N24:O24) -> 0 | Q24: =IFERROR((+P24/G24),"") | R24: =IFERROR(Q24/H24-1,"")
A25: =IF('Direct Labor Rate Schedule'!B29="","",'Direct Labor Rate Schedule'!B22) | B25: ='Direct Labor Rate Schedule'!C22 -> 0 | C25: ='Direct Labor Rate Schedule'!A22 -> 0 | D25: Enter P or S | F25: =(G25/AnnualProductiveHours) -> 0 | G25: 0 | H25: ='Direct Labor Rate Schedule'!F22 -> 0 | I25: =ROUND((+H25*$I$10),2) -> 0 | J25: =ROUND((+H25*$J$10),2) -> 0 | K25: =+H25+SUM(I25:J25) -> 0 | L25: =ROUND((+G25*K25),2) -> 0 | M25: =ROUND((+L25*$M$10),2) -> 0 | N25: =SUM(L25:M25) -> 0 | O25: =ROUND((+N25*$O$10),2) -> 0 | P25: =SUM(N25:O25) -> 0 | Q25: =IFERROR((+P25/G25),"") | R25: =IFERROR(Q25/H25-1,"")
A26: Total: | F26: =SUM(F14:F25) -> 3.9166667 | G26: =SUM(G14:G25) -> 7520 | H26: =SUMPRODUCT(H14:H25,$G14:$G25) -> 0 | I26: =SUMPRODUCT(I14:I25,$G14:$G25) -> 0 | J26: =SUMPRODUCT(J14:J25,$G14:$G25) -> 0 | K26: =SUMPRODUCT(K14:K25,$G14:$G25) -> 0 | L26: =SUM(L14:L25) -> 0 | M26: =SUM(M14:M25) -> 0 | N26: =SUM(N14:N25) -> 0 | O26: =SUM(O14:O25) -> 0 | P26: =SUM(P14:P25) -> 0 | Q26: =SUMPRODUCT(Q14:Q25,$G14:$G25) -> 0
A27: Weighted Average: | G27: =G26/SUM(F14:F25) -> 1920 | H27: =H26/$G26 -> 0 | I27: =I26/$G26 -> 0 | J27: =J26/$G26 -> 0 | K27: =K26/$G26 -> 0 | L27: =L26/$G26 -> 0 | M27: =M26/$G26 -> 0 | N27: =N26/$G26 -> 0 | O27: =O26/$G26 -> 0 | ... Q27: =Q26/$G26 -> 0 | R27: =Q27/H27 -> #DIV/0!
G29: Direct Cost | I29: Indirect Cost
I30: ='Indirect Rate Summary'!C10 -> 0 | J30: ='Indirect Rate Summary'!D10 -> 0 | M30: ='Indirect Rate Summary'!E10 -> 0 | O30: ='Indirect Rate Summary'!F10 -> 0
A31: =+A11 -> Location (Note 1) | B31: =+B11 -> Labor Type (Note 2) | C31: =+C11 -> Labor Categories (Note 3) | D31: =+D11 -> Effort To Be Performed By The Prime (P) or Subcontractor (S) (Note 4) | E31: =+E11 -> If Column D=S, Enter Name of Subcontractor(s) (Note 5) | F31: =+F11 -> FTEs (Note 6) | G31: =+G11 -> Total Productive Hours (Note 7) | H31: =+H11 -> Hourly Base Pay Rate (Note 8) | ... R31: =+R11 -> Wrap Rate
A32: =+A12 -> a | B32: =+B12 -> b | C32: =+C12 -> c | D32: =+D12 -> d | E32: =+E12 -> e | F32: =+F12 -> f | G32: =+G12 -> g | H32: =+H12 -> h | ... R32: =+R12 -> r = q/h
A33: =IF('Direct Labor Rate Schedule'!$A$10="","",'Direct Labor Rate Schedule'!$A$10)
A34: =A14 | B34: =B14 -> 0 | C34: =C14 -> Program Manager | D34: Enter P or S | F34: =(G34/AnnualProductiveHours)*(12/11) -> 0 | H34: ='Direct Labor Rate Schedule'!F11 -> 0 | I34: =ROUND((+H34*$I$30),2) -> 0 | J34: =ROUND((+H34*$J$30),2) -> 0 | K34: =+H34+SUM(I34:J34) -> 0 | L34: =ROUND((+G34*K34),2) -> 0 | M34: =ROUND((+L34*$M$30),2) -> 0 | N34: =SUM(L34:M34) -> 0 | O34: =ROUND((+N34*$O$30),2) -> 0 | P34: =SUM(N34:O34) -> 0 | Q34: =IFERROR((+P34/G34),"") | R34: =IFERROR(Q34/H34-1,"")
A35: =A15 | B35: =B15 -> 0 | C35: =C15 -> Senior Analyst | D35: Enter P or S | F35: =(G35/AnnualProductiveHours)*(12/11) -> 0 | H35: ='Direct Labor Rate Schedule'!F12 -> 0 | I35: =ROUND((+H35*$I$30),2) -> 0 | J35: =ROUND((+H35*$J$30),2) -> 0 | K35: =+H35+SUM(I35:J35) -> 0 | L35: =ROUND((+G35*K35),2) -> 0 | M35: =ROUND((+L35*$M$30),2) -> 0 | N35: =SUM(L35:M35) -> 0 | O35: =ROUND((+N35*$O$30),2) -> 0 | P35: =SUM(N35:O35) -> 0 | Q35: =IFERROR((+P35/G35),"") | R35: =IFERROR(Q35/H35-1,"")
A36: =A16 | B36: =B16 -> 0 | C36: =C16 -> Analyst | D36: Enter P or S | F36: =(G36/AnnualProductiveHours)*(12/11) -> 0 | H36: ='Direct Labor Rate Schedule'!F13 -> 0 | I36: =ROUND((+H36*$I$30),2) -> 0 | J36: =ROUND((+H36*$J$30),2) -> 0 | K36: =+H36+SUM(I36:J36) -> 0 | L36: =ROUND((+G36*K36),2) -> 0 | M36: =ROUND((+L36*$M$30),2) -> 0 | N36: =SUM(L36:M36) -> 0 | O36: =ROUND((+N36*$O$30),2) -> 0 | P36: =SUM(N36:O36) -> 0 | Q36: =IFERROR((+P36/G36),"") | R36: =IFERROR(Q36/H36-1,"")
A37: =A17 | B37: =B17 -> 0 | C37: =C17 -> Junior Analyst | D37: Enter P or S | F37: =(G37/AnnualProductiveHours)*(12/11) -> 0 | H37: ='Direct Labor Rate Schedule'!F14 -> 0 | I37: =ROUND((+H37*$I$30),2) -> 0 | J37: =ROUND((+H37*$J$30),2) -> 0 | K37: =+H37+SUM(I37:J37) -> 0 | L37: =ROUND((+G37*K37),2) -> 0 | M37: =ROUND((+L37*$M$30),2) -> 0 | N37: =SUM(L37:M37) -> 0 | O37: =ROUND((+N37*$O$30),2) -> 0 | P37: =SUM(N37:O37) -> 0 | Q37: =IFERROR((+P37/G37),"") | R37: =IFERROR(Q37/H37-1,"")
A38: =A18 | B38: =B18 -> 0 | C38: =C18 -> Senior Operations Research Analyst | D38: Enter P or S | F38: =(G38/AnnualProductiveHours)*(12/11) -> 0 | H38: ='Direct Labor Rate Schedule'!F15 -> 0 | I38: =ROUND((+H38*$I$30),2) -> 0 | J38: =ROUND((+H38*$J$30),2) -> 0 | K38: =+H38+SUM(I38:J38) -> 0 | L38: =ROUND((+G38*K38),2) -> 0 | M38: =ROUND((+L38*$M$30),2) -> 0 | N38: =SUM(L38:M38) -> 0 | O38: =ROUND((+N38*$O$30),2) -> 0 | P38: =SUM(N38:O38) -> 0 | Q38: =IFERROR((+P38/G38),"") | R38: =IFERROR(Q38/H38-1,"")
A39: =A19 | B39: =B19 -> 0 | C39: =C19 -> Operations Research Analyst | D39: Enter P or S | F39: =(G39/AnnualProductiveHours)*(12/11) -> 0 | H39: ='Direct Labor Rate Schedule'!F16 -> 0 | I39: =ROUND((+H39*$I$30),2) -> 0 | J39: =ROUND((+H39*$J$30),2) -> 0 | K39: =+H39+SUM(I39:J39) -> 0 | L39: =ROUND((+G39*K39),2) -> 0 | M39: =ROUND((+L39*$M$30),2) -> 0 | N39: =SUM(L39:M39) -> 0 | O39: =ROUND((+N39*$O$30),2) -> 0 | P39: =SUM(N39:O39) -> 0 | Q39: =IFERROR((+P39/G39),"") | R39: =IFERROR(Q39/H39-1,"")
A40: =A20 | B40: =B20 -> 0 | C40: =C20 -> Graphics Design Senior Analyst | D40: Enter P or S | F40: =(G40/AnnualProductiveHours)*(12/11) -> 0 | H40: ='Direct Labor Rate Schedule'!F17 -> 0 | I40: =ROUND((+H40*$I$30),2) -> 0 | J40: =ROUND((+H40*$J$30),2) -> 0 | K40: =+H40+SUM(I40:J40) -> 0 | L40: =ROUND((+G40*K40),2) -> 0 | M40: =ROUND((+L40*$M$30),2) -> 0 | N40: =SUM(L40:M40) -> 0 | O40: =ROUND((+N40*$O$30),2) -> 0 | P40: =SUM(N40:O40) -> 0 | Q40: =IFERROR((+P40/G40),"") | R40: =IFERROR(Q40/H40-1,"")
A41: =A21 | B41: =B21 -> 0 | C41: =C21 -> Force Documentation Senior Analyst | D41: Enter P or S | F41: =(G41/AnnualProductiveHours)*(12/11) -> 0 | H41: ='Direct Labor Rate Schedule'!F18 -> 0 | I41: =ROUND((+H41*$I$30),2) -> 0 | J41: =ROUND((+H41*$J$30),2) -> 0 | K41: =+H41+SUM(I41:J41) -> 0 | L41: =ROUND((+G41*K41),2) -> 0 | M41: =ROUND((+L41*$M$30),2) -> 0 | N41: =SUM(L41:M41) -> 0 | O41: =ROUND((+N41*$O$30),2) -> 0 | P41: =SUM(N41:O41) -> 0 | Q41: =IFERROR((+P41/G41),"") | R41: =IFERROR(Q41/H41-1,"")
A42: =A22 | B42: =B22 -> 0 | C42: =C22 -> 0 | D42: Enter P or S | F42: =(G42/AnnualProductiveHours)*(12/11) -> 0 | H42: ='Direct Labor Rate Schedule'!F19 -> 0 | I42: =ROUND((+H42*$I$30),2) -> 0 | J42: =ROUND((+H42*$J$30),2) -> 0 | K42: =+H42+SUM(I42:J42) -> 0 | L42: =ROUND((+G42*K42),2) -> 0 | M42: =ROUND((+L42*$M$30),2) -> 0 | N42: =SUM(L42:M42) -> 0 | O42: =ROUND((+N42*$O$30),2) -> 0 | P42: =SUM(N42:O42) -> 0 | Q42: =IFERROR((+P42/G42),"") | R42: =IFERROR(Q42/H42-1,"")
A43: =A23 | B43: =B23 -> 0 | C43: =C23 -> 0 | D43: Enter P or S | F43: =(G43/AnnualProductiveHours)*(12/11) -> 0 | H43: ='Direct Labor Rate Schedule'!F20 -> 0 | I43: =ROUND((+H43*$I$30),2) -> 0 | J43: =ROUND((+H43*$J$30),2) -> 0 | K43: =+H43+SUM(I43:J43) -> 0 | L43: =ROUND((+G43*K43),2) -> 0 | M43: =ROUND((+L43*$M$30),2) -> 0 | N43: =SUM(L43:M43) -> 0 | O43: =ROUND((+N43*$O$30),2) -> 0 | P43: =SUM(N43:O43) -> 0 | Q43: =IFERROR((+P43/G43),"") | R43: =IFERROR(Q43/H43-1,"")
A44: =A24 | B44: =B24 -> 0 | C44: =C24 -> 0 | D44: Enter P or S | F44: =(G44/AnnualProductiveHours)*(12/11) -> 0 | H44: ='Direct Labor Rate Schedule'!F21 -> 0 | I44: =ROUND((+H44*$I$30),2) -> 0 | J44: =ROUND((+H44*$J$30),2) -> 0 | K44: =+H44+SUM(I44:J44) -> 0 | L44: =ROUND((+G44*K44),2) -> 0 | M44: =ROUND((+L44*$M$30),2) -> 0 | N44: =SUM(L44:M44) -> 0 | O44: =ROUND((+N44*$O$30),2) -> 0 | P44: =SUM(N44:O44) -> 0 | Q44: =IFERROR((+P44/G44),"") | R44: =IFERROR(Q44/H44-1,"")
A45: =A25 | B45: =B25 -> 0 | C45: =C25 -> 0 | D45: Enter P or S | F45: =(G45/AnnualProductiveHours)*(12/11) -> 0 | H45: ='Direct Labor Rate Schedule'!F22 -> 0 | I45: =ROUND((+H45*$I$30),2) -> 0 | J45: =ROUND((+H45*$J$30),2) -> 0 | K45: =+H45+SUM(I45:J45) -> 0 | L45: =ROUND((+G45*K45),2) -> 0 | M45: =ROUND((+L45*$M$30),2) -> 0 | N45: =SUM(L45:M45) -> 0 | O45: =ROUND((+N45*$O$30),2) -> 0 | P45: =SUM(N45:O45) -> 0 | Q45: =IFERROR((+P45/G45),"") | R45: =IFERROR(Q45/H45-1,"")
A46: Total: | F46: =SUM(F34:F45) -> 0 | G46: =SUM(G34:G45) -> 0 | H46: =SUMPRODUCT(H34:H45,$G34:$G45) -> 0 | I46: =SUMPRODUCT(I34:I45,$G34:$G45) -> 0 | J46: =SUMPRODUCT(J34:J45,$G34:$G45) -> 0 | K46: =SUMPRODUCT(K34:K45,$G34:$G45) -> 0 | L46: =SUM(L34:L45) -> 0 | M46: =SUM(M34:M45) -> 0 | N46: =SUM(N34:N45) -> 0 | O46: =SUM(O34:O45) -> 0 | P46: =SUM(P34:P45) -> 0 | Q46: =SUMPRODUCT(Q34:Q45,$G34:$G45) -> 0
A47: Weighted Average: | G47: =G46/SUM(F34:F45) -> #DIV/0! | H47: =H46/$G46 -> #DIV/0! | I47: =I46/$G46 -> #DIV/0! | J47: =J46/$G46 -> #DIV/0! | K47: =K46/$G46 -> #DIV/0! | L47: =L46/$G46 -> #DIV/0! | M47: =M46/$G46 -> #DIV/0! | N47: =N46/$G46 -> #DIV/0! | O47: =O46/$G46 -> #DIV/0! | ... Q47: =Q46/$G46 -> #DIV/0! | R47: =Q47/H47 -> #DIV/0!
G49: Direct Cost | I49: Indirect Cost
C50: CLIN 1002 - OY1 Surge Option (FD, PAE, CAA) | I50: ='Indirect Rate Summary'!C17 -> 0 | J50: ='Indirect Rate Summary'!D17 -> 0 | M50: ='Indirect Rate Summary'!E17 -> 0 | O50: ='Indirect Rate Summary'!F17 -> 0
A51: =+A31 -> Location (Note 1) | B51: =+B31 -> Labor Type (Note 2) | C51: =+C31 -> Labor Categories (Note 3) | D51: =+D31 -> Effort To Be Performed By The Prime (P) or Subcontractor (S) (Note 4) | E51: =+E31 -> If Column D=S, Enter Name of Subcontractor(s) (Note 5) | F51: =+F31 -> FTEs (Note 6) | G51: =+G31 -> Total Productive Hours (Note 7) | H51: =+H31 -> Hourly Base Pay Rate (Note 8) | ... R51: =+R31 -> Wrap Rate
A52: =+A32 -> a | B52: =+B32 -> b | C52: =+C32 -> c | D52: =+D32 -> d | E52: =+E32 -> e | F52: =+F32 -> f | G52: =+G32 -> g | H52: =+H32 -> h | ... R52: =+R32 -> r = q/h
A53: =IF('Direct Labor Rate Schedule'!$A$10="","",'Direct Labor Rate Schedule'!$A$10)
A54: =A34 | B54: =B34 -> 0 | C54: =C34 -> Program Manager | D54: Enter P or S | F54: =G54/AnnualProductiveHours -> 0 | G54: 0 | H54: ='Direct Labor Rate Schedule'!H11 -> 0 | I54: =ROUND((+H54*$I$50),2) -> 0 | J54: =ROUND((+H54*$J$50),2) -> 0 | K54: =+H54+SUM(I54:J54) -> 0 | L54: =ROUND((+G54*K54),2) -> 0 | M54: =ROUND((+L54*$M$50),2) -> 0 | N54: =SUM(L54:M54) -> 0 | O54: =ROUND((+N54*$O$50),2) -> 0 | P54: =SUM(N54:O54) -> 0 | Q54: =IFERROR((+P54/G54),"") | R54: =IFERROR(Q54/H54-1,"")
A55: =A35 | B55: =B35 -> 0 | C55: =C35 -> Senior Analyst | D55: Enter P or S | F55: =G55/AnnualProductiveHours -> 7.8333333 | G55: 15040 | H55: ='Direct Labor Rate Schedule'!H12 -> 0 | I55: =ROUND((+H55*$I$50),2) -> 0 | J55: =ROUND((+H55*$J$50),2) -> 0 | K55: =+H55+SUM(I55:J55) -> 0 | L55: =ROUND((+G55*K55),2) -> 0 | M55: =ROUND((+L55*$M$50),2) -> 0 | N55: =SUM(L55:M55) -> 0 | O55: =ROUND((+N55*$O$50),2) -> 0 | P55: =SUM(N55:O55) -> 0 | Q55: =IFERROR((+P55/G55),"") -> 0 | R55: =IFERROR(Q55/H55-1,"")
A56: =A36 | B56: =B36 -> 0 | C56: =C36 -> Analyst | D56: Enter P or S | F56: =G56/AnnualProductiveHours -> 1.9583333 | G56: 3760 | H56: ='Direct Labor Rate Schedule'!H13 -> 0 | I56: =ROUND((+H56*$I$50),2) -> 0 | J56: =ROUND((+H56*$J$50),2) -> 0 | K56: =+H56+SUM(I56:J56) -> 0 | L56: =ROUND((+G56*K56),2) -> 0 | M56: =ROUND((+L56*$M$50),2) -> 0 | N56: =SUM(L56:M56) -> 0 | O56: =ROUND((+N56*$O$50),2) -> 0 | P56: =SUM(N56:O56) -> 0 | Q56: =IFERROR((+P56/G56),"") -> 0 | R56: =IFERROR(Q56/H56-1,"")
A57: =A37 | B57: =B37 -> 0 | C57: =C37 -> Junior Analyst | D57: Enter P or S | F57: =G57/AnnualProductiveHours -> 0 | G57: 0 | H57: ='Direct Labor Rate Schedule'!H14 -> 0 | I57: =ROUND((+H57*$I$50),2) -> 0 | J57: =ROUND((+H57*$J$50),2) -> 0 | K57: =+H57+SUM(I57:J57) -> 0 | L57: =ROUND((+G57*K57),2) -> 0 | M57: =ROUND((+L57*$M$50),2) -> 0 | N57: =SUM(L57:M57) -> 0 | O57: =ROUND((+N57*$O$50),2) -> 0 | P57: =SUM(N57:O57) -> 0 | Q57: =IFERROR((+P57/G57),"") | R57: =IFERROR(Q57/H57-1,"")
A58: =A38 | B58: =B38 -> 0 | C58: =C38 -> Senior Operations Research Analyst | D58: Enter P or S | F58: =G58/AnnualProductiveHours -> 3.9166667 | G58: 7520 | H58: ='Direct Labor Rate Schedule'!H15 -> 0 | I58: =ROUND((+H58*$I$50),2) -> 0 | J58: =ROUND((+H58*$J$50),2) -> 0 | K58: =+H58+SUM(I58:J58) -> 0 | L58: =ROUND((+G58*K58),2) -> 0 | M58: =ROUND((+L58*$M$50),2) -> 0 | N58: =SUM(L58:M58) -> 0 | O58: =ROUND((+N58*$O$50),2) -> 0 | P58: =SUM(N58:O58) -> 0 | Q58: =IFERROR((+P58/G58),"") -> 0 | R58: =IFERROR(Q58/H58-1,"")
A59: =A39 | B59: =B39 -> 0 | C59: =C39 -> Operations Research Analyst | D59: Enter P or S | F59: =G59/AnnualProductiveHours -> 1.9583333 | G59: 3760 | H59: ='Direct Labor Rate Schedule'!H16 -> 0 | I59: =ROUND((+H59*$I$50),2) -> 0 | J59: =ROUND((+H59*$J$50),2) -> 0 | K59: =+H59+SUM(I59:J59) -> 0 | L59: =ROUND((+G59*K59),2) -> 0 | M59: =ROUND((+L59*$M$50),2) -> 0 | N59: =SUM(L59:M59) -> 0 | O59: =ROUND((+N59*$O$50),2) -> 0 | P59: =SUM(N59:O59) -> 0 | Q59: =IFERROR((+P59/G59),"") -> 0 | R59: =IFERROR(Q59/H59-1,"")
A60: =A40 | B60: =B40 -> 0 | C60: =C40 -> Graphics Design Senior Analyst | D60: Enter P or S | F60: =G60/AnnualProductiveHours -> 0 | G60: 0 | H60: ='Direct Labor Rate Schedule'!H17 -> 0 | I60: =ROUND((+H60*$I$50),2) -> 0 | J60: =ROUND((+H60*$J$50),2) -> 0 | K60: =+H60+SUM(I60:J60) -> 0 | L60: =ROUND((+G60*K60),2) -> 0 | M60: =ROUND((+L60*$M$50),2) -> 0 | N60: =SUM(L60:M60) -> 0 | O60: =ROUND((+N60*$O$50),2) -> 0 | P60: =SUM(N60:O60) -> 0 | Q60: =IFERROR((+P60/G60),"") | R60: =IFERROR(Q60/H60-1,"")
A61: =A41 | B61: =B41 -> 0 | C61: =C41 -> Force Documentation Senior Analyst | D61: Enter P or S | F61: =G61/AnnualProductiveHours -> 0 | G61: 0 | H61: ='Direct Labor Rate Schedule'!H18 -> 0 | I61: =ROUND((+H61*$I$50),2) -> 0 | J61: =ROUND((+H61*$J$50),2) -> 0 | K61: =+H61+SUM(I61:J61) -> 0 | L61: =ROUND((+G61*K61),2) -> 0 | M61: =ROUND((+L61*$M$50),2) -> 0 | N61: =SUM(L61:M61) -> 0 | O61: =ROUND((+N61*$O$50),2) -> 0 | P61: =SUM(N61:O61) -> 0 | Q61: =IFERROR((+P61/G61),"") | R61: =IFERROR(Q61/H61-1,"")
A62: =A42 | B62: =B42 -> 0 | C62: =C42 -> 0 | D62: Enter P or S | F62: =G62/AnnualProductiveHours -> 0 | G62: 0 | H62: ='Direct Labor Rate Schedule'!H19 -> 0 | I62: =ROUND((+H62*$I$50),2) -> 0 | J62: =ROUND((+H62*$J$50),2) -> 0 | K62: =+H62+SUM(I62:J62) -> 0 | L62: =ROUND((+G62*K62),2) -> 0 | M62: =ROUND((+L62*$M$50),2) -> 0 | N62: =SUM(L62:M62) -> 0 | O62: =ROUND((+N62*$O$50),2) -> 0 | P62: =SUM(N62:O62) -> 0 | Q62: =IFERROR((+P62/G62),"") | R62: =IFERROR(Q62/H62-1,"")
A63: =A43 | B63: =B43 -> 0 | C63: =C43 -> 0 | D63: Enter P or S | F63: =G63/AnnualProductiveHours -> 0 | G63: 0 | H63: ='Direct Labor Rate Schedule'!H20 -> 0 | I63: =ROUND((+H63*$I$50),2) -> 0 | J63: =ROUND((+H63*$J$50),2) -> 0 | K63: =+H63+SUM(I63:J63) -> 0 | L63: =ROUND((+G63*K63),2) -> 0 | M63: =ROUND((+L63*$M$50),2) -> 0 | N63: =SUM(L63:M63) -> 0 | O63: =ROUND((+N63*$O$50),2) -> 0 | P63: =SUM(N63:O63) -> 0 | Q63: =IFERROR((+P63/G63),"") | R63: =IFERROR(Q63/H63-1,"")
A64: =A44 | B64: =B44 -> 0 | C64: =C44 -> 0 | D64: Enter P or S | F64: =G64/AnnualProductiveHours -> 0 | G64: 0 | H64: ='Direct Labor Rate Schedule'!H21 -> 0 | I64: =ROUND((+H64*$I$50),2) -> 0 | J64: =ROUND((+H64*$J$50),2) -> 0 | K64: =+H64+SUM(I64:J64) -> 0 | L64: =ROUND((+G64*K64),2) -> 0 | M64: =ROUND((+L64*$M$50),2) -> 0 | N64: =SUM(L64:M64) -> 0 | O64: =ROUND((+N64*$O$50),2) -> 0 | P64: =SUM(N64:O64) -> 0 | Q64: =IFERROR((+P64/G64),"") | R64: =IFERROR(Q64/H64-1,"")
A65: =A45 | B65: =B45 -> 0 | C65: =C45 -> 0 | D65: Enter P or S | F65: =G65/AnnualProductiveHours -> 0 | G65: 0 | H65: ='Direct Labor Rate Schedule'!H22 -> 0 | I65: =ROUND((+H65*$I$50),2) -> 0 | J65: =ROUND((+H65*$J$50),2) -> 0 | K65: =+H65+SUM(I65:J65) -> 0 | L65: =ROUND((+G65*K65),2) -> 0 | M65: =ROUND((+L65*$M$50),2) -> 0 | N65: =SUM(L65:M65) -> 0 | O65: =ROUND((+N65*$O$50),2) -> 0 | P65: =SUM(N65:O65) -> 0 | Q65: =IFERROR((+P65/G65),"") | R65: =IFERROR(Q65/H65-1,"")
A66: Total: | F66: =SUM(F54:F65) -> 15.666667 | G66: =SUM(G54:G65) -> 30080 | H66: =SUMPRODUCT(H54:H65,$G54:$G65) -> 0 | I66: =SUMPRODUCT(I54:I65,$G54:$G65) -> 0 | J66: =SUMPRODUCT(J54:J65,$G54:$G65) -> 0 | K66: =SUMPRODUCT(K54:K65,$G54:$G65) -> 0 | L66: =SUM(L54:L65) -> 0 | M66: =SUM(M54:M65) -> 0 | N66: =SUM(N54:N65) -> 0 | O66: =SUM(O54:O65) -> 0 | P66: =SUM(P54:P65) -> 0 | Q66: =SUMPRODUCT(Q54:Q65,$G54:$G65) -> 0
A67: Weighted Average: | G67: =G66/SUM(F54:F65) -> 1920 | H67: =H66/$G66 -> 0 | I67: =I66/$G66 -> 0 | J67: =J66/$G66 -> 0 | K67: =K66/$G66 -> 0 | L67: =L66/$G66 -> 0 | M67: =M66/$G66 -> 0 | N67: =N66/$G66 -> 0 | O67: =O66/$G66 -> 0 | ... Q67: =Q66/$G66 -> 0 | R67: =Q67/H67 -> #DIV/0!
G69: Direct Cost | I69: Indirect Cost
C70: CLIN 2002 - OY2 Surge Option (FD, PAE, CAA) | I70: ='Indirect Rate Summary'!C24 -> 0 | J70: ='Indirect Rate Summary'!D24 -> 0 | M70: ='Indirect Rate Summary'!E24 -> 0 | O70: ='Indirect Rate Summary'!F24 -> 0
A71: =+A51 -> Location (Note 1) | B71: =+B51 -> Labor Type (Note 2) | C71: =+C51 -> Labor Categories (Note 3) | D71: =+D51 -> Effort To Be Performed By The Prime (P) or Subcontractor (S) (Note 4) | E71: =+E51 -> If Column D=S, Enter Name of Subcontractor(s) (Note 5) | F71: =+F51 -> FTEs (Note 6) | G71: =+G51 -> Total Productive Hours (Note 7) | H71: =+H51 -> Hourly Base Pay Rate (Note 8) | ... R71: =+R51 -> Wrap Rate
A72: =+A52 -> a | B72: =+B52 -> b | C72: =+C52 -> c | D72: =+D52 -> d | E72: =+E52 -> e | F72: =+F52 -> f | G72: =+G52 -> g | H72: =+H52 -> h | ... R72: =+R52 -> r = q/h
A73: =IF('Direct Labor Rate Schedule'!$A$10="","",'Direct Labor Rate Schedule'!$A$10)
A74: =A54 | B74: =B54 -> 0 | C74: =C54 -> Program Manager | D74: Enter P or S | F74: =G74/AnnualProductiveHours -> 0 | G74: 0 | H74: ='Direct Labor Rate Schedule'!J11 -> 0 | I74: =ROUND((+H74*$I$70),2) -> 0 | J74: =ROUND((+H74*$J$70),2) -> 0 | K74: =+H74+SUM(I74:J74) -> 0 | L74: =ROUND((+G74*K74),2) -> 0 | M74: =ROUND((+L74*$M$70),2) -> 0 | N74: =SUM(L74:M74) -> 0 | O74: =ROUND((+N74*$O$70),2) -> 0 | P74: =SUM(N74:O74) -> 0 | Q74: =IFERROR((+P74/G74),"") | R74: =IFERROR(Q74/H74-1,"")
A75: =A55 | B75: =B55 -> 0 | C75: =C55 -> Senior Analyst | D75: Enter P or S | F75: =G75/AnnualProductiveHours -> 11.75 | G75: 22560 | H75: ='Direct Labor Rate Schedule'!J12 -> 0 | I75: =ROUND((+H75*$I$70),2) -> 0 | J75: =ROUND((+H75*$J$70),2) -> 0 | K75: =+H75+SUM(I75:J75) -> 0 | L75: =ROUND((+G75*K75),2) -> 0 | M75: =ROUND((+L75*$M$70),2) -> 0 | N75: =SUM(L75:M75) -> 0 | O75: =ROUND((+N75*$O$70),2) -> 0 | P75: =SUM(N75:O75) -> 0 | Q75: =IFERROR((+P75/G75),"") -> 0 | R75: =IFERROR(Q75/H75-1,"")
A76: =A56 | B76: =B56 -> 0 | C76: =C56 -> Analyst | D76: Enter P or S | F76: =G76/AnnualProductiveHours -> 0 | G76: 0 | H76: ='Direct Labor Rate Schedule'!J13 -> 0 | I76: =ROUND((+H76*$I$70),2) -> 0 | J76: =ROUND((+H76*$J$70),2) -> 0 | K76: =+H76+SUM(I76:J76) -> 0 | L76: =ROUND((+G76*K76),2) -> 0 | M76: =ROUND((+L76*$M$70),2) -> 0 | N76: =SUM(L76:M76) -> 0 | O76: =ROUND((+N76*$O$70),2) -> 0 | P76: =SUM(N76:O76) -> 0 | Q76: =IFERROR((+P76/G76),"") | R76: =IFERROR(Q76/H76-1,"")
A77: =A57 | B77: =B57 -> 0 | C77: =C57 -> Junior Analyst | D77: Enter P or S | F77: =G77/AnnualProductiveHours -> 0 | G77: 0 | H77: ='Direct Labor Rate Schedule'!J14 -> 0 | I77: =ROUND((+H77*$I$70),2) -> 0 | J77: =ROUND((+H77*$J$70),2) -> 0 | K77: =+H77+SUM(I77:J77) -> 0 | L77: =ROUND((+G77*K77),2) -> 0 | M77: =ROUND((+L77*$M$70),2) -> 0 | N77: =SUM(L77:M77) -> 0 | O77: =ROUND((+N77*$O$70),2) -> 0 | P77: =SUM(N77:O77) -> 0 | Q77: =IFERROR((+P77/G77),"") | R77: =IFERROR(Q77/H77-1,"")
A78: =A58 | B78: =B58 -> 0 | C78: =C58 -> Senior Operations Research Analyst | D78: Enter P or S | F78: =G78/AnnualProductiveHours -> 5.875 | G78: 11280 | H78: ='Direct Labor Rate Schedule'!J15 -> 0 | I78: =ROUND((+H78*$I$70),2) -> 0 | J78: =ROUND((+H78*$J$70),2) -> 0 | K78: =+H78+SUM(I78:J78) -> 0 | L78: =ROUND((+G78*K78),2) -> 0 | M78: =ROUND((+L78*$M$70),2) -> 0 | N78: =SUM(L78:M78) -> 0 | O78: =ROUND((+N78*$O$70),2) -> 0 | P78: =SUM(N78:O78) -> 0 | Q78: =IFERROR((+P78/G78),"") -> 0 | R78: =IFERROR(Q78/H78-1,"")
A79: =A59 | B79: =B59 -> 0 | C79: =C59 -> Operations Research Analyst | D79: Enter P or S | F79: =G79/AnnualProductiveHours -> 2.9375 | G79: 5640 | H79: ='Direct Labor Rate Schedule'!J16 -> 0 | I79: =ROUND((+H79*$I$70),2) -> 0 | J79: =ROUND((+H79*$J$70),2) -> 0 | K79: =+H79+SUM(I79:J79) -> 0 | L79: =ROUND((+G79*K79),2) -> 0 | M79: =ROUND((+L79*$M$70),2) -> 0 | N79: =SUM(L79:M79) -> 0 | O79: =ROUND((+N79*$O$70),2) -> 0 | P79: =SUM(N79:O79) -> 0 | Q79: =IFERROR((+P79/G79),"") -> 0 | R79: =IFERROR(Q79/H79-1,"")
A80: =A60 | B80: =B60 -> 0 | C80: =C60 -> Graphics Design Senior Analyst | D80: Enter P or S | F80: =G80/AnnualProductiveHours -> 0 | G80: 0 | H80: ='Direct Labor Rate Schedule'!J17 -> 0 | I80: =ROUND((+H80*$I$70),2) -> 0 | J80: =ROUND((+H80*$J$70),2) -> 0 | K80: =+H80+SUM(I80:J80) -> 0 | L80: =ROUND((+G80*K80),2) -> 0 | M80: =ROUND((+L80*$M$70),2) -> 0 | N80: =SUM(L80:M80) -> 0 | O80: =ROUND((+N80*$O$70),2) -> 0 | P80: =SUM(N80:O80) -> 0 | Q80: =IFERROR((+P80/G80),"") | R80: =IFERROR(Q80/H80-1,"")
A81: =A61 | B81: =B61 -> 0 | C81: =C61 -> Force Documentation Senior Analyst | D81: Enter P or S | F81: =G81/AnnualProductiveHours -> 0 | G81: 0 | H81: ='Direct Labor Rate Schedule'!J18 -> 0 | I81: =ROUND((+H81*$I$70),2) -> 0 | J81: =ROUND((+H81*$J$70),2) -> 0 | K81: =+H81+SUM(I81:J81) -> 0 | L81: =ROUND((+G81*K81),2) -> 0 | M81: =ROUND((+L81*$M$70),2) -> 0 | N81: =SUM(L81:M81) -> 0 | O81: =ROUND((+N81*$O$70),2) -> 0 | P81: =SUM(N81:O81) -> 0 | Q81: =IFERROR((+P81/G81),"") | R81: =IFERROR(Q81/H81-1,"")
A82: =A62 | B82: =B62 -> 0 | C82: =C62 -> 0 | D82: Enter P or S | F82: =G82/AnnualProductiveHours -> 0 | G82: 0 | H82: ='Direct Labor Rate Schedule'!J19 -> 0 | I82: =ROUND((+H82*$I$70),2) -> 0 | J82: =ROUND((+H82*$J$70),2) -> 0 | K82: =+H82+SUM(I82:J82) -> 0 | L82: =ROUND((+G82*K82),2) -> 0 | M82: =ROUND((+L82*$M$70),2) -> 0 | N82: =SUM(L82:M82) -> 0 | O82: =ROUND((+N82*$O$70),2) -> 0 | P82: =SUM(N82:O82) -> 0 | Q82: =IFERROR((+P82/G82),"") | R82: =IFERROR(Q82/H82-1,"")
A83: =A63 | B83: =B63 -> 0 | C83: =C63 -> 0 | D83: Enter P or S | F83: =G83/AnnualProductiveHours -> 0 | G83: 0 | H83: ='Direct Labor Rate Schedule'!J20 -> 0 | I83: =ROUND((+H83*$I$70),2) -> 0 | J83: =ROUND((+H83*$J$70),2) -> 0 | K83: =+H83+SUM(I83:J83) -> 0 | L83: =ROUND((+G83*K83),2) -> 0 | M83: =ROUND((+L83*$M$70),2) -> 0 | N83: =SUM(L83:M83) -> 0 | O83: =ROUND((+N83*$O$70),2) -> 0 | P83: =SUM(N83:O83) -> 0 | Q83: =IFERROR((+P83/G83),"") | R83: =IFERROR(Q83/H83-1,"")
A84: =A64 | B84: =B64 -> 0 | C84: =C64 -> 0 | D84: Enter P or S | F84: =G84/AnnualProductiveHours -> 0 | G84: 0 | H84: ='Direct Labor Rate Schedule'!J21 -> 0 | I84: =ROUND((+H84*$I$70),2) -> 0 | J84: =ROUND((+H84*$J$70),2) -> 0 | K84: =+H84+SUM(I84:J84) -> 0 | L84: =ROUND((+G84*K84),2) -> 0 | M84: =ROUND((+L84*$M$70),2) -> 0 | N84: =SUM(L84:M84) -> 0 | O84: =ROUND((+N84*$O$70),2) -> 0 | P84: =SUM(N84:O84) -> 0 | Q84: =IFERROR((+P84/G84),"") | R84: =IFERROR(Q84/H84-1,"")
A85: =A65 | B85: =B65 -> 0 | C85: =C65 -> 0 | D85: Enter P or S | F85: =G85/AnnualProductiveHours -> 0 | G85: 0 | H85: ='Direct Labor Rate Schedule'!J22 -> 0 | I85: =ROUND((+H85*$I$70),2) -> 0 | J85: =ROUND((+H85*$J$70),2) -> 0 | K85: =+H85+SUM(I85:J85) -> 0 | L85: =ROUND((+G85*K85),2) -> 0 | M85: =ROUND((+L85*$M$70),2) -> 0 | N85: =SUM(L85:M85) -> 0 | O85: =ROUND((+N85*$O$70),2) -> 0 | P85: =SUM(N85:O85) -> 0 | Q85: =IFERROR((+P85/G85),"") | R85: =IFERROR(Q85/H85-1,"")
A86: Total: | F86: =SUM(F74:F85) -> 20.5625 | G86: =SUM(G74:G85) -> 39480 | H86: =SUMPRODUCT(H74:H85,$G74:$G85) -> 0 | I86: =SUMPRODUCT(I74:I85,$G74:$G85) -> 0 | J86: =SUMPRODUCT(J74:J85,$G74:$G85) -> 0 | K86: =SUMPRODUCT(K74:K85,$G74:$G85) -> 0 | L86: =SUM(L74:L85) -> 0 | M86: =SUM(M74:M85) -> 0 | N86: =SUM(N74:N85) -> 0 | O86: =SUM(O74:O85) -> 0 | P86: =SUM(P74:P85) -> 0 | Q86: =SUMPRODUCT(Q74:Q85,$G74:$G85) -> 0
A87: Weighted Average: | G87: =G86/SUM(F74:F85) -> 1920 | H87: =H86/$G86 -> 0 | I87: =I86/$G86 -> 0 | J87: =J86/$G86 -> 0 | K87: =K86/$G86 -> 0 | L87: =L86/$G86 -> 0 | M87: =M86/$G86 -> 0 | N87: =N86/$G86 -> 0 | O87: =O86/$G86 -> 0 | ... Q87: =Q86/$G86 -> 0 | R87: =Q87/H87 -> #DIV/0!
G89: Direct Cost | I89: Indirect Cost
C90: CLIN 3002 - OY3 Surge Option (FD, PAE, CAA) | I90: ='Indirect Rate Summary'!C31 -> 0 | J90: ='Indirect Rate Summary'!D31 -> 0 | M90: ='Indirect Rate Summary'!E31 -> 0 | O90: ='Indirect Rate Summary'!F31 -> 0
A91: =+A71 -> Location (Note 1) | B91: =+B71 -> Labor Type (Note 2) | C91: =+C71 -> Labor Categories (Note 3) | D91: =+D71 -> Effort To Be Performed By The Prime (P) or Subcontractor (S) (Note 4) | E91: =+E71 -> If Column D=S, Enter Name of Subcontractor(s) (Note 5) | F91: =+F71 -> FTEs (Note 6) | G91: =+G71 -> Total Productive Hours (Note 7) | H91: =+H71 -> Hourly Base Pay Rate (Note 8) | ... R91: =+R71 -> Wrap Rate
A92: =+A72 -> a | B92: =+B72 -> b | C92: =+C72 -> c | D92: =+D72 -> d | E92: =+E72 -> e | F92: =+F72 -> f | G92: =+G72 -> g | H92: =+H72 -> h | ... R92: =+R72 -> r = q/h
A93: =IF('Direct Labor Rate Schedule'!$A$10="","",'Direct Labor Rate Schedule'!$A$10)
A94: =A74 | B94: =B74 -> 0 | C94: =C74 -> Program Manager | D94: Enter P or S | F94: =G94/AnnualProductiveHours -> 0 | G94: 0 | H94: ='Direct Labor Rate Schedule'!L11 -> 0 | I94: =ROUND((+H94*$I$90),2) -> 0 | J94: =ROUND((+H94*$J$90),2) -> 0 | K94: =+H94+SUM(I94:J94) -> 0 | L94: =ROUND((+G94*K94),2) -> 0 | M94: =ROUND((+L94*$M$90),2) -> 0 | N94: =SUM(L94:M94) -> 0 | O94: =ROUND((+N94*$O$90),2) -> 0 | P94: =SUM(N94:O94) -> 0 | Q94: =IFERROR((+P94/G94),"") | R94: =IFERROR(Q94/H94-1,"")
A95: =A75 | B95: =B75 -> 0 | C95: =C75 -> Senior Analyst | D95: Enter P or S | F95: =G95/AnnualProductiveHours -> 11.75 | G95: 22560 | H95: ='Direct Labor Rate Schedule'!L12 -> 0 | I95: =ROUND((+H95*$I$90),2) -> 0 | J95: =ROUND((+H95*$J$90),2) -> 0 | K95: =+H95+SUM(I95:J95) -> 0 | L95: =ROUND((+G95*K95),2) -> 0 | M95: =ROUND((+L95*$M$90),2) -> 0 | N95: =SUM(L95:M95) -> 0 | O95: =ROUND((+N95*$O$90),2) -> 0 | P95: =SUM(N95:O95) -> 0 | Q95: =IFERROR((+P95/G95),"") -> 0 | R95: =IFERROR(Q95/H95-1,"")
A96: =A76 | B96: =B76 -> 0 | C96: =C76 -> Analyst | D96: Enter P or S | F96: =G96/AnnualProductiveHours -> 3.9166667 | G96: 7520 | H96: ='Direct Labor Rate Schedule'!L13 -> 0 | I96: =ROUND((+H96*$I$90),2) -> 0 | J96: =ROUND((+H96*$J$90),2) -> 0 | K96: =+H96+SUM(I96:J96) -> 0 | L96: =ROUND((+G96*K96),2) -> 0 | M96: =ROUND((+L96*$M$90),2) -> 0 | N96: =SUM(L96:M96) -> 0 | O96: =ROUND((+N96*$O$90),2) -> 0 | P96: =SUM(N96:O96) -> 0 | Q96: =IFERROR((+P96/G96),"") -> 0 | R96: =IFERROR(Q96/H96-1,"")
A97: =A77 | B97: =B77 -> 0 | C97: =C77 -> Junior Analyst | D97: Enter P or S | F97: =G97/AnnualProductiveHours -> 0 | G97: 0 | H97: ='Direct Labor Rate Schedule'!L14 -> 0 | I97: =ROUND((+H97*$I$90),2) -> 0 | J97: =ROUND((+H97*$J$90),2) -> 0 | K97: =+H97+SUM(I97:J97) -> 0 | L97: =ROUND((+G97*K97),2) -> 0 | M97: =ROUND((+L97*$M$90),2) -> 0 | N97: =SUM(L97:M97) -> 0 | O97: =ROUND((+N97*$O$90),2) -> 0 | P97: =SUM(N97:O97) -> 0 | Q97: =IFERROR((+P97/G97),"") | R97: =IFERROR(Q97/H97-1,"")
A98: =A78 | B98: =B78 -> 0 | C98: =C78 -> Senior Operations Research Analyst | D98: Enter P or S | F98: =G98/AnnualProductiveHours -> 5.875 | G98: 11280 | H98: ='Direct Labor Rate Schedule'!L15 -> 0 | I98: =ROUND((+H98*$I$90),2) -> 0 | J98: =ROUND((+H98*$J$90),2) -> 0 | K98: =+H98+SUM(I98:J98) -> 0 | L98: =ROUND((+G98*K98),2) -> 0 | M98: =ROUND((+L98*$M$90),2) -> 0 | N98: =SUM(L98:M98) -> 0 | O98: =ROUND((+N98*$O$90),2) -> 0 | P98: =SUM(N98:O98) -> 0 | Q98: =IFERROR((+P98/G98),"") -> 0 | R98: =IFERROR(Q98/H98-1,"")
A99: =A79 | B99: =B79 -> 0 | C99: =C79 -> Operations Research Analyst | D99: Enter P or S | F99: =G99/AnnualProductiveHours -> 2.9375 | G99: 5640 | H99: ='Direct Labor Rate Schedule'!L16 -> 0 | I99: =ROUND((+H99*$I$90),2) -> 0 | J99: =ROUND((+H99*$J$90),2) -> 0 | K99: =+H99+SUM(I99:J99) -> 0 | L99: =ROUND((+G99*K99),2) -> 0 | M99: =ROUND((+L99*$M$90),2) -> 0 | N99: =SUM(L99:M99) -> 0 | O99: =ROUND((+N99*$O$90),2) -> 0 | P99: =SUM(N99:O99) -> 0 | Q99: =IFERROR((+P99/G99),"") -> 0 | R99: =IFERROR(Q99/H99-1,"")
A100: =A80 | B100: =B80 -> 0 | C100: =C80 -> Graphics Design Senior Analyst | D100: Enter P or S | F100: =G100/AnnualProductiveHours -> 0 | G100: 0 | H100: ='Direct Labor Rate Schedule'!L17 -> 0 | I100: =ROUND((+H100*$I$90),2) -> 0 | J100: =ROUND((+H100*$J$90),2) -> 0 | K100: =+H100+SUM(I100:J100) -> 0 | L100: =ROUND((+G100*K100),2) -> 0 | M100: =ROUND((+L100*$M$90),2) -> 0 | N100: =SUM(L100:M100) -> 0 | O100: =ROUND((+N100*$O$90),2) -> 0 | P100: =SUM(N100:O100) -> 0 | Q100: =IFERROR((+P100/G100),"") | R100: =IFERROR(Q100/H100-1,"")
A101: =A81 | B101: =B81 -> 0 | C101: =C81 -> Force Documentation Senior Analyst | D101: Enter P or S | F101: =G101/AnnualProductiveHours -> 0 | G101: 0 | H101: ='Direct Labor Rate Schedule'!L18 -> 0 | I101: =ROUND((+H101*$I$90),2) -> 0 | J101: =ROUND((+H101*$J$90),2) -> 0 | K101: =+H101+SUM(I101:J101) -> 0 | L101: =ROUND((+G101*K101),2) -> 0 | M101: =ROUND((+L101*$M$90),2) -> 0 | N101: =SUM(L101:M101) -> 0 | O101: =ROUND((+N101*$O$90),2) -> 0 | P101: =SUM(N101:O101) -> 0 | Q101: =IFERROR((+P101/G101),"") | R101: =IFERROR(Q101/H101-1,"")
A102: =A82 | B102: =B82 -> 0 | C102: =C82 -> 0 | D102: Enter P or S | F102: =G102/AnnualProductiveHours -> 0 | G102: 0 | H102: ='Direct Labor Rate Schedule'!L19 -> 0 | I102: =ROUND((+H102*$I$90),2) -> 0 | J102: =ROUND((+H102*$J$90),2) -> 0 | K102: =+H102+SUM(I102:J102) -> 0 | L102: =ROUND((+G102*K102),2) -> 0 | M102: =ROUND((+L102*$M$90),2) -> 0 | N102: =SUM(L102:M102) -> 0 | O102: =ROUND((+N102*$O$90),2) -> 0 | P102: =SUM(N102:O102) -> 0 | Q102: =IFERROR((+P102/G102),"") | R102: =IFERROR(Q102/H102-1,"")
A103: =A83 | B103: =B83 -> 0 | C103: =C83 -> 0 | D103: Enter P or S | F103: =G103/AnnualProductiveHours -> 0 | G103: 0 | H103: ='Direct Labor Rate Schedule'!L20 -> 0 | I103: =ROUND((+H103*$I$90),2) -> 0 | J103: =ROUND((+H103*$J$90),2) -> 0 | K103: =+H103+SUM(I103:J103) -> 0 | L103: =ROUND((+G103*K103),2) -> 0 | M103: =ROUND((+L103*$M$90),2) -> 0 | N103: =SUM(L103:M103) -> 0 | O103: =ROUND((+N103*$O$90),2) -> 0 | P103: =SUM(N103:O103) -> 0 | Q103: =IFERROR((+P103/G103),"") | R103: =IFERROR(Q103/H103-1,"")
A104: =A84 | B104: =B84 -> 0 | C104: =C84 -> 0 | D104: Enter P or S | F104: =G104/AnnualProductiveHours -> 0 | G104: 0 | H104: ='Direct Labor Rate Schedule'!L21 -> 0 | I104: =ROUND((+H104*$I$90),2) -> 0 | J104: =ROUND((+H104*$J$90),2) -> 0 | K104: =+H104+SUM(I104:J104) -> 0 | L104: =ROUND((+G104*K104),2) -> 0 | M104: =ROUND((+L104*$M$90),2) -> 0 | N104: =SUM(L104:M104) -> 0 | O104: =ROUND((+N104*$O$90),2) -> 0 | P104: =SUM(N104:O104) -> 0 | Q104: =IFERROR((+P104/G104),"") | R104: =IFERROR(Q104/H104-1,"")
A105: =A85 | B105: =B85 -> 0 | C105: =C85 -> 0 | D105: Enter P or S | F105: =G105/AnnualProductiveHours -> 0 | G105: 0 | H105: ='Direct Labor Rate Schedule'!L22 -> 0 | I105: =ROUND((+H105*$I$90),2) -> 0 | J105: =ROUND((+H105*$J$90),2) -> 0 | K105: =+H105+SUM(I105:J105) -> 0 | L105: =ROUND((+G105*K105),2) -> 0 | M105: =ROUND((+L105*$M$90),2) -> 0 | N105: =SUM(L105:M105) -> 0 | O105: =ROUND((+N105*$O$90),2) -> 0 | P105: =SUM(N105:O105) -> 0 | Q105: =IFERROR((+P105/G105),"") | R105: =IFERROR(Q105/H105-1,"")
...

Sheet Phase-in & OES 52.217-8 Labor
A1: Labor Cost Detail Spreadsheet
A2: ="Solicitation Number: "&Instructions!H9&"" -> Solicitation Number: W91CRB-25-R-0002
A3: ="Name of Action: "&Instructions!H10 -> Name of Action: Force Development
A4: ="Prime Contractor/Subcontractor Name/Division: "&Instructions!H15 -> Prime Contractor/Subcontractor Name/Division:
A5: ="Period of Performance: "&Instructions!H11 -> Period of Performance:
A6: ="Date of Proposal:"&IF(ISBLANK(Instructions!H18)," TBD",(TEXT(Instructions!H18," mm/dd/yyyy"))) -> Date of Proposal: TBD
A7: ="Annual Productive Hours: "&AnnualProductiveHours -> Annual Productive Hours: 1920
G9: Direct Labor | I9: Indirect Cost
C10: CLIN 0001-1 Transition-In/Phase-In (1 Month) | I10: ='Indirect Rate Summary'!C10 -> 0 | J10: ='Indirect Rate Summary'!D10 -> 0 | M10: ='Indirect Rate Summary'!E10 -> 0 | O10: ='Indirect Rate Summary'!F10 -> 0
A11: Location (Note 1) | B11: Labor Type (Note 2) | C11: Labor Categories (Note 3) | D11: Effort To Be Performed By The Prime (P) or Subcontractor (S) (Note 4) | E11: If Column D=S, Enter Name of Subcontractor(s) (Note 5) | F11: FTEs (Note 6) | G11: Total Productive Hours (Note 7) | H11: Hourly Base Pay Rate (Note 8) | I11: Fringe (Note 9) | J11: Overhead (Note 10) | K11: Prime/Sub Hourly Rate Before Application Of Prime G&A & Fee (IF Col C=S Enter Sub Rate) (Note 11) | L11: Total Prime & Sub Labor Before Prime G&A & Fee | M11: G&A (Note 12) | N11: Total Cost | O11: Fee | P11: Total Price | Q11: Proposal Fully Burdened Hourly Billing Rate | R11: Wrap Rate
A12: a | B12: b | C12: c | D12: d | E12: e | F12: f | G12: g | H12: h | I12: i | J12: j | K12: k = h + i + j | L12: l = g x k | M12: m | N12: n = l + o | O12: o | P12: p = n + o | Q12: q = p/g | R12: r = q/h
A13: =IF('Direct Labor Rate Schedule'!$A$10="","",'Direct Labor Rate Schedule'!$A$10)
A14: =IF('Direct Labor Rate Schedule'!B18="","",'Direct Labor Rate Schedule'!B11) | B14: ='Direct Labor Rate Schedule'!C11 -> 0 | C14: ='Direct Labor Rate Schedule'!A11 -> Program Manager | D14: Enter P or S | F14: =(G14/AnnualProductiveHours) -> 0.08125 | G14: 156 | H14: ='Direct Labor Rate Schedule'!F11 -> 0 | I14: =ROUND((+H14*$I$10),2) -> 0 | J14: =ROUND((+H14*$J$10),2) -> 0 | K14: =+H14+SUM(I14:J14) -> 0 | L14: =ROUND((+G14*K14),2) -> 0 | M14: =ROUND((+L14*$M$10),2) -> 0 | N14: =SUM(L14:M14) -> 0 | O14: =ROUND((+N14*$O$10),2) -> 0 | P14: =SUM(N14:O14) -> 0 | Q14: =IFERROR((+P14/G14),"") -> 0 | R14: =IFERROR(Q14/H14-1,"")
A15: =IF('Direct Labor Rate Schedule'!B19="","",'Direct Labor Rate Schedule'!B12) | B15: ='Direct Labor Rate Schedule'!C12 -> 0 | C15: ='Direct Labor Rate Schedule'!A12 -> Senior Analyst | D15: Enter P or S | F15: =(G15/AnnualProductiveHours) -> 1.05625 | G15: 2028 | H15: ='Direct Labor Rate Schedule'!F12 -> 0 | I15: =ROUND((+H15*$I$10),2) -> 0 | J15: =ROUND((+H15*$J$10),2) -> 0 | K15: =+H15+SUM(I15:J15) -> 0 | L15: =ROUND((+G15*K15),2) -> 0 | M15: =ROUND((+L15*$M$10),2) -> 0 | N15: =SUM(L15:M15) -> 0 | O15: =ROUND((+N15*$O$10),2) -> 0 | P15: =SUM(N15:O15) -> 0 | Q15: =IFERROR((+P15/G15),"") -> 0 | R15: =IFERROR(Q15/H15-1,"")
A16: =IF('Direct Labor Rate Schedule'!B20="","",'Direct Labor Rate Schedule'!B13) | B16: ='Direct Labor Rate Schedule'!C13 -> 0 | C16: ='Direct Labor Rate Schedule'!A13 -> Analyst | D16: Enter P or S | F16: =(G16/AnnualProductiveHours) -> 0 | G16: 0 | H16: ='Direct Labor Rate Schedule'!F13 -> 0 | I16: =ROUND((+H16*$I$10),2) -> 0 | J16: =ROUND((+H16*$J$10),2) -> 0 | K16: =+H16+SUM(I16:J16) -> 0 | L16: =ROUND((+G16*K16),2) -> 0 | M16: =ROUND((+L16*$M$10),2) -> 0 | N16: =SUM(L16:M16) -> 0 | O16: =ROUND((+N16*$O$10),2) -> 0 | P16: =SUM(N16:O16) -> 0 | Q16: =IFERROR((+P16/G16),"") | R16: =IFERROR(Q16/H16-1,"")
A17: =IF('Direct Labor Rate Schedule'!B21="","",'Direct Labor Rate Schedule'!B14) | B17: ='Direct Labor Rate Schedule'!C14 -> 0 | C17: ='Direct Labor Rate Schedule'!A14 -> Junior Analyst | D17: Enter P or S | F17: =(G17/AnnualProductiveHours) -> 0 | G17: 0 | H17: ='Direct Labor Rate Schedule'!F14 -> 0 | I17: =ROUND((+H17*$I$10),2) -> 0 | J17: =ROUND((+H17*$J$10),2) -> 0 | K17: =+H17+SUM(I17:J17) -> 0 | L17: =ROUND((+G17*K17),2) -> 0 | M17: =ROUND((+L17*$M$10),2) -> 0 | N17: =SUM(L17:M17) -> 0 | O17: =ROUND((+N17*$O$10),2) -> 0 | P17: =SUM(N17:O17) -> 0 | Q17: =IFERROR((+P17/G17),"") | R17: =IFERROR(Q17/H17-1,"")
A18: =IF('Direct Labor Rate Schedule'!B22="","",'Direct Labor Rate Schedule'!B15) | B18: ='Direct Labor Rate Schedule'!C15 -> 0 | C18: ='Direct Labor Rate Schedule'!A15 -> Senior Operations Research Analyst | D18: Enter P or S | F18: =(G18/AnnualProductiveHours) -> 0.08125 | G18: 156 | H18: ='Direct Labor Rate Schedule'!F15 -> 0 | I18: =ROUND((+H18*$I$10),2) -> 0 | J18: =ROUND((+H18*$J$10),2) -> 0 | K18: =+H18+SUM(I18:J18) -> 0 | L18: =ROUND((+G18*K18),2) -> 0 | M18: =ROUND((+L18*$M$10),2) -> 0 | N18: =SUM(L18:M18) -> 0 | O18: =ROUND((+N18*$O$10),2) -> 0 | P18: =SUM(N18:O18) -> 0 | Q18: =IFERROR((+P18/G18),"") -> 0 | R18: =IFERROR(Q18/H18-1,"")
A19: =IF('Direct Labor Rate Schedule'!B23="","",'Direct Labor Rate Schedule'!B16) | B19: ='Direct Labor Rate Schedule'!C16 -> 0 | C19: ='Direct Labor Rate Schedule'!A16 -> Operations Research Analyst | D19: Enter P or S | F19: =(G19/AnnualProductiveHours) -> 0 | G19: 0 | H19: ='Direct Labor Rate Schedule'!F16 -> 0 | I19: =ROUND((+H19*$I$10),2) -> 0 | J19: =ROUND((+H19*$J$10),2) -> 0 | K19: =+H19+SUM(I19:J19) -> 0 | L19: =ROUND((+G19*K19),2) -> 0 | M19: =ROUND((+L19*$M$10),2) -> 0 | N19: =SUM(L19:M19) -> 0 | O19: =ROUND((+N19*$O$10),2) -> 0 | P19: =SUM(N19:O19) -> 0 | Q19: =IFERROR((+P19/G19),"") | R19: =IFERROR(Q19/H19-1,"")
A20: =IF('Direct Labor Rate Schedule'!B24="","",'Direct Labor Rate Schedule'!B17) | B20: ='Direct Labor Rate Schedule'!C17 -> 0 | C20: ='Direct Labor Rate Schedule'!A17 -> Graphics Design Senior Analyst | D20: Enter P or S | F20: =(G20/AnnualProductiveHours) -> 0.08125 | G20: 156 | H20: ='Direct Labor Rate Schedule'!F17 -> 0 | I20: =ROUND((+H20*$I$10),2) -> 0 | J20: =ROUND((+H20*$J$10),2) -> 0 | K20: =+H20+SUM(I20:J20) -> 0 | L20: =ROUND((+G20*K20),2) -> 0 | M20: =ROUND((+L20*$M$10),2) -> 0 | N20: =SUM(L20:M20) -> 0 | O20: =ROUND((+N20*$O$10),2) -> 0 | P20: =SUM(N20:O20) -> 0 | Q20: =IFERROR((+P20/G20),"") -> 0 | R20: =IFERROR(Q20/H20-1,"")
A21: =IF('Direct Labor Rate Schedule'!B25="","",'Direct Labor Rate Schedule'!B18) | B21: ='Direct Labor Rate Schedule'!C18 -> 0 | C21: ='Direct Labor Rate Schedule'!A18 -> Force Documentation Senior Analyst | D21: Enter P or S | F21: =(G21/AnnualProductiveHours) -> 0.08125 | G21: 156 | H21: ='Direct Labor Rate Schedule'!F18 -> 0 | I21: =ROUND((+H21*$I$10),2) -> 0 | J21: =ROUND((+H21*$J$10),2) -> 0 | K21: =+H21+SUM(I21:J21) -> 0 | L21: =ROUND((+G21*K21),2) -> 0 | M21: =ROUND((+L21*$M$10),2) -> 0 | N21: =SUM(L21:M21) -> 0 | O21: =ROUND((+N21*$O$10),2) -> 0 | P21: =SUM(N21:O21) -> 0 | Q21: =IFERROR((+P21/G21),"") -> 0 | R21: =IFERROR(Q21/H21-1,"")
A22: =IF('Direct Labor Rate Schedule'!B26="","",'Direct Labor Rate Schedule'!B19) | B22: ='Direct Labor Rate Schedule'!C19 -> 0 | C22: ='Direct Labor Rate Schedule'!A19 -> 0 | D22: Enter P or S | F22: =(G22/AnnualProductiveHours) -> 0 | G22: 0 | H22: ='Direct Labor Rate Schedule'!F19 -> 0 | I22: =ROUND((+H22*$I$10),2) -> 0 | J22: =ROUND((+H22*$J$10),2) -> 0 | K22: =+H22+SUM(I22:J22) -> 0 | L22: =ROUND((+G22*K22),2) -> 0 | M22: =ROUND((+L22*$M$10),2) -> 0 | N22: =SUM(L22:M22) -> 0 | O22: =ROUND((+N22*$O$10),2) -> 0 | P22: =SUM(N22:O22) -> 0 | Q22: =IFERROR((+P22/G22),"") | R22: =IFERROR(Q22/H22-1,"")
A23: =IF('Direct Labor Rate Schedule'!B27="","",'Direct Labor Rate Schedule'!B20) | B23: ='Direct Labor Rate Schedule'!C20 -> 0 | C23: ='Direct Labor Rate Schedule'!A20 -> 0 | D23: Enter P or S | F23: =(G23/AnnualProductiveHours) -> 0 | G23: 0 | H23: ='Direct Labor Rate Schedule'!F20 -> 0 | I23: =ROUND((+H23*$I$10),2) -> 0 | J23: =ROUND((+H23*$J$10),2) -> 0 | K23: =+H23+SUM(I23:J23) -> 0 | L23: =ROUND((+G23*K23),2) -> 0 | M23: =ROUND((+L23*$M$10),2) -> 0 | N23: =SUM(L23:M23) -> 0 | O23: =ROUND((+N23*$O$10),2) -> 0 | P23: =SUM(N23:O23) -> 0 | Q23: =IFERROR((+P23/G23),"") | R23: =IFERROR(Q23/H23-1,"")
A24: =IF('Direct Labor Rate Schedule'!B28="","",'Direct Labor Rate Schedule'!B21) | B24: ='Direct Labor Rate Schedule'!C21 -> 0 | C24: ='Direct Labor Rate Schedule'!A21 -> 0 | D24: Enter P or S | F24: =(G24/AnnualProductiveHours) -> 0 | G24: 0 | H24: ='Direct Labor Rate Schedule'!F21 -> 0 | I24: =ROUND((+H24*$I$10),2) -> 0 | J24: =ROUND((+H24*$J$10),2) -> 0 | K24: =+H24+SUM(I24:J24) -> 0 | L24: =ROUND((+G24*K24),2) -> 0 | M24: =ROUND((+L24*$M$10),2) -> 0 | N24: =SUM(L24:M24) -> 0 | O24: =ROUND((+N24*$O$10),2) -> 0 | P24: =SUM(N24:O24) -> 0 | Q24: =IFERROR((+P24/G24),"") | R24: =IFERROR(Q24/H24-1,"")
A25: =IF('Direct Labor Rate Schedule'!B29="","",'Direct Labor Rate Schedule'!B22) | B25: ='Direct Labor Rate Schedule'!C22 -> 0 | C25: ='Direct Labor Rate Schedule'!A22 -> 0 | D25: Enter P or S | F25: =(G25/AnnualProductiveHours) -> 0 | G25: 0 | H25: ='Direct Labor Rate Schedule'!F22 -> 0 | I25: =ROUND((+H25*$I$10),2) -> 0 | J25: =ROUND((+H25*$J$10),2) -> 0 | K25: =+H25+SUM(I25:J25) -> 0 | L25: =ROUND((+G25*K25),2) -> 0 | M25: =ROUND((+L25*$M$10),2) -> 0 | N25: =SUM(L25:M25) -> 0 | O25: =ROUND((+N25*$O$10),2) -> 0 | P25: =SUM(N25:O25) -> 0 | Q25: =IFERROR((+P25/G25),"") | R25: =IFERROR(Q25/H25-1,"")
A26: Total: | F26: =SUM(F14:F25) -> 1.38125 | G26: =SUM(G14:G25) -> 2652 | H26: =SUMPRODUCT(H14:H25,$G14:$G25) -> 0 | I26: =SUMPRODUCT(I14:I25,$G14:$G25) -> 0 | J26: =SUMPRODUCT(J14:J25,$G14:$G25) -> 0 | K26: =SUMPRODUCT(K14:K25,$G14:$G25) -> 0 | L26: =SUM(L14:L25) -> 0 | M26: =SUM(M14:M25) -> 0 | N26: =SUM(N14:N25) -> 0 | O26: =SUM(O14:O25) -> 0 | P26: =SUM(P14:P25) -> 0 | Q26: =SUMPRODUCT(Q14:Q25,$G14:$G25) -> 0
A27: Weighted Average: | G27: =G26/SUM(F14:F25) -> 1920 | H27: =H26/$G26 -> 0 | I27: =I26/$G26 -> 0 | J27: =J26/$G26 -> 0 | K27: =K26/$G26 -> 0 | L27: =L26/$G26 -> 0 | M27: =M26/$G26 -> 0 | N27: =N26/$G26 -> 0 | O27: =O26/$G26 -> 0 | ... Q27: =Q26/$G26 -> 0 | R27: =Q27/H27 -> #DIV/0!
G29: Direct Cost | I29: Indirect Cost
I30: ='Indirect Rate Summary'!C10 -> 0 | J30: ='Indirect Rate Summary'!D10 -> 0 | M30: ='Indirect Rate Summary'!E10 -> 0 | O30: ='Indirect Rate Summary'!F10 -> 0
A31: =+A11 -> Location (Note 1) | B31: =+B11 -> Labor Type (Note 2) | C31: =+C11 -> Labor Categories (Note 3) | D31: =+D11 -> Effort To Be Performed By The Prime (P) or Subcontractor (S) (Note 4) | E31: =+E11 -> If Column D=S, Enter Name of Subcontractor(s) (Note 5) | F31: =+F11 -> FTEs (Note 6) | G31: =+G11 -> Total Productive Hours (Note 7) | H31: =+H11 -> Hourly Base Pay Rate (Note 8) | ... R31: =+R11 -> Wrap Rate
A32: =+A12 -> a | B32: =+B12 -> b | C32: =+C12 -> c | D32: =+D12 -> d | E32: =+E12 -> e | F32: =+F12 -> f | G32: =+G12 -> g | H32: =+H12 -> h | ... R32: =+R12 -> r = q/h
A33: =IF('Direct Labor Rate Schedule'!$A$10="","",'Direct Labor Rate Schedule'!$A$10)
A34: =A14 | B34: =B14 -> 0 | C34: =C14 -> Program Manager | D34: Enter P or S | F34: =(G34/AnnualProductiveHours)*(12/11) -> 0 | H34: ='Direct Labor Rate Schedule'!F11 -> 0 | I34: =ROUND((+H34*$I$30),2) -> 0 | J34: =ROUND((+H34*$J$30),2) -> 0 | K34: =+H34+SUM(I34:J34) -> 0 | L34: =ROUND((+G34*K34),2) -> 0 | M34: =ROUND((+L34*$M$30),2) -> 0 | N34: =SUM(L34:M34) -> 0 | O34: =ROUND((+N34*$O$30),2) -> 0 | P34: =SUM(N34:O34) -> 0 | Q34: =IFERROR((+P34/G34),"") | R34: =IFERROR(Q34/H34-1,"")
A35: =A15 | B35: =B15 -> 0 | C35: =C15 -> Senior Analyst | D35: Enter P or S | F35: =(G35/AnnualProductiveHours)*(12/11) -> 0 | H35: ='Direct Labor Rate Schedule'!F12 -> 0 | I35: =ROUND((+H35*$I$30),2) -> 0 | J35: =ROUND((+H35*$J$30),2) -> 0 | K35: =+H35+SUM(I35:J35) -> 0 | L35: =ROUND((+G35*K35),2) -> 0 | M35: =ROUND((+L35*$M$30),2) -> 0 | N35: =SUM(L35:M35) -> 0 | O35: =ROUND((+N35*$O$30),2) -> 0 | P35: =SUM(N35:O35) -> 0 | Q35: =IFERROR((+P35/G35),"") | R35: =IFERROR(Q35/H35-1,"")
A36: =A16 | B36: =B16 -> 0 | C36: =C16 -> Analyst | D36: Enter P or S | F36: =(G36/AnnualProductiveHours)*(12/11) -> 0 | H36: ='Direct Labor Rate Schedule'!F13 -> 0 | I36: =ROUND((+H36*$I$30),2) -> 0 | J36: =ROUND((+H36*$J$30),2) -> 0 | K36: =+H36+SUM(I36:J36) -> 0 | L36: =ROUND((+G36*K36),2) -> 0 | M36: =ROUND((+L36*$M$30),2) -> 0 | N36: =SUM(L36:M36) -> 0 | O36: =ROUND((+N36*$O$30),2) -> 0 | P36: =SUM(N36:O36) -> 0 | Q36: =IFERROR((+P36/G36),"") | R36: =IFERROR(Q36/H36-1,"")
A37: =A17 | B37: =B17 -> 0 | C37: =C17 -> Junior Analyst | D37: Enter P or S | F37: =(G37/AnnualProductiveHours)*(12/11) -> 0 | H37: ='Direct Labor Rate Schedule'!F14 -> 0 | I37: =ROUND((+H37*$I$30),2) -> 0 | J37: =ROUND((+H37*$J$30),2) -> 0 | K37: =+H37+SUM(I37:J37) -> 0 | L37: =ROUND((+G37*K37),2) -> 0 | M37: =ROUND((+L37*$M$30),2) -> 0 | N37: =SUM(L37:M37) -> 0 | O37: =ROUND((+N37*$O$30),2) -> 0 | P37: =SUM(N37:O37) -> 0 | Q37: =IFERROR((+P37/G37),"") | R37: =IFERROR(Q37/H37-1,"")
A38: =A18 | B38: =B18 -> 0 | C38: =C18 -> Senior Operations Research Analyst | D38: Enter P or S | F38: =(G38/AnnualProductiveHours)*(12/11) -> 0 | H38: ='Direct Labor Rate Schedule'!F15 -> 0 | I38: =ROUND((+H38*$I$30),2) -> 0 | J38: =ROUND((+H38*$J$30),2) -> 0 | K38: =+H38+SUM(I38:J38) -> 0 | L38: =ROUND((+G38*K38),2) -> 0 | M38: =ROUND((+L38*$M$30),2) -> 0 | N38: =SUM(L38:M38) -> 0 | O38: =ROUND((+N38*$O$30),2) -> 0 | P38: =SUM(N38:O38) -> 0 | Q38: =IFERROR((+P38/G38),"") | R38: =IFERROR(Q38/H38-1,"")
A39: =A19 | B39: =B19 -> 0 | C39: =C19 -> Operations Research Analyst | D39: Enter P or S | F39: =(G39/AnnualProductiveHours)*(12/11) -> 0 | H39: ='Direct Labor Rate Schedule'!F16 -> 0 | I39: =ROUND((+H39*$I$30),2) -> 0 | J39: =ROUND((+H39*$J$30),2) -> 0 | K39: =+H39+SUM(I39:J39) -> 0 | L39: =ROUND((+G39*K39),2) -> 0 | M39: =ROUND((+L39*$M$30),2) -> 0 | N39: =SUM(L39:M39) -> 0 | O39: =ROUND((+N39*$O$30),2) -> 0 | P39: =SUM(N39:O39) -> 0 | Q39: =IFERROR((+P39/G39),"") | R39: =IFERROR(Q39/H39-1,"")
A40: =A20 | B40: =B20 -> 0 | C40: =C20 -> Graphics Design Senior Analyst | D40: Enter P or S | F40: =(G40/AnnualProductiveHours)*(12/11) -> 0 | H40: ='Direct Labor Rate Schedule'!F17 -> 0 | I40: =ROUND((+H40*$I$30),2) -> 0 | J40: =ROUND((+H40*$J$30),2) -> 0 | K40: =+H40+SUM(I40:J40) -> 0 | L40: =ROUND((+G40*K40),2) -> 0 | M40: =ROUND((+L40*$M$30),2) -> 0 | N40: =SUM(L40:M40) -> 0 | O40: =ROUND((+N40*$O$30),2) -> 0 | P40: =SUM(N40:O40) -> 0 | Q40: =IFERROR((+P40/G40),"") | R40: =IFERROR(Q40/H40-1,"")
A41: =A21 | B41: =B21 -> 0 | C41: =C21 -> Force Documentation Senior Analyst | D41: Enter P or S | F41: =(G41/AnnualProductiveHours)*(12/11) -> 0 | H41: ='Direct Labor Rate Schedule'!F18 -> 0 | I41: =ROUND((+H41*$I$30),2) -> 0 | J41: =ROUND((+H41*$J$30),2) -> 0 | K41: =+H41+SUM(I41:J41) -> 0 | L41: =ROUND((+G41*K41),2) -> 0 | M41: =ROUND((+L41*$M$30),2) -> 0 | N41: =SUM(L41:M41) -> 0 | O41: =ROUND((+N41*$O$30),2) -> 0 | P41: =SUM(N41:O41) -> 0 | Q41: =IFERROR((+P41/G41),"") | R41: =IFERROR(Q41/H41-1,"")
A42: =A22 | B42: =B22 -> 0 | C42: =C22 -> 0 | D42: Enter P or S | F42: =(G42/AnnualProductiveHours)*(12/11) -> 0 | H42: ='Direct Labor Rate Schedule'!F19 -> 0 | I42: =ROUND((+H42*$I$30),2) -> 0 | J42: =ROUND((+H42*$J$30),2) -> 0 | K42: =+H42+SUM(I42:J42) -> 0 | L42: =ROUND((+G42*K42),2) -> 0 | M42: =ROUND((+L42*$M$30),2) -> 0 | N42: =SUM(L42:M42) -> 0 | O42: =ROUND((+N42*$O$30),2) -> 0 | P42: =SUM(N42:O42) -> 0 | Q42: =IFERROR((+P42/G42),"") | R42: =IFERROR(Q42/H42-1,"")
A43: =A23 | B43: =B23 -> 0 | C43: =C23 -> 0 | D43: Enter P or S | F43: =(G43/AnnualProductiveHours)*(12/11) -> 0 | H43: ='Direct Labor Rate Schedule'!F20 -> 0 | I43: =ROUND((+H43*$I$30),2) -> 0 | J43: =ROUND((+H43*$J$30),2) -> 0 | K43: =+H43+SUM(I43:J43) -> 0 | L43: =ROUND((+G43*K43),2) -> 0 | M43: =ROUND((+L43*$M$30),2) -> 0 | N43: =SUM(L43:M43) -> 0 | O43: =ROUND((+N43*$O$30),2) -> 0 | P43: =SUM(N43:O43) -> 0 | Q43: =IFERROR((+P43/G43),"") | R43: =IFERROR(Q43/H43-1,"")
A44: =A24 | B44: =B24 -> 0 | C44: =C24 -> 0 | D44: Enter P or S | F44: =(G44/AnnualProductiveHours)*(12/11) -> 0 | H44: ='Direct Labor Rate Schedule'!F21 -> 0 | I44: =ROUND((+H44*$I$30),2) -> 0 | J44: =ROUND((+H44*$J$30),2) -> 0 | K44: =+H44+SUM(I44:J44) -> 0 | L44: =ROUND((+G44*K44),2) -> 0 | M44: =ROUND((+L44*$M$30),2) -> 0 | N44: =SUM(L44:M44) -> 0 | O44: =ROUND((+N44*$O$30),2) -> 0 | P44: =SUM(N44:O44) -> 0 | Q44: =IFERROR((+P44/G44),"") | R44: =IFERROR(Q44/H44-1,"")
A45: =A25 | B45: =B25 -> 0 | C45: =C25 -> 0 | D45: Enter P or S | F45: =(G45/AnnualProductiveHours)*(12/11) -> 0 | H45: ='Direct Labor Rate Schedule'!F22 -> 0 | I45: =ROUND((+H45*$I$30),2) -> 0 | J45: =ROUND((+H45*$J$30),2) -> 0 | K45: =+H45+SUM(I45:J45) -> 0 | L45: =ROUND((+G45*K45),2) -> 0 | M45: =ROUND((+L45*$M$30),2) -> 0 | N45: =SUM(L45:M45) -> 0 | O45: =ROUND((+N45*$O$30),2) -> 0 | P45: =SUM(N45:O45) -> 0 | Q45: =IFERROR((+P45/G45),"") | R45: =IFERROR(Q45/H45-1,"")
A46: Total: | F46: =SUM(F34:F45) -> 0 | G46: =SUM(G34:G45) -> 0 | H46: =SUMPRODUCT(H34:H45,$G34:$G45) -> 0 | I46: =SUMPRODUCT(I34:I45,$G34:$G45) -> 0 | J46: =SUMPRODUCT(J34:J45,$G34:$G45) -> 0 | K46: =SUMPRODUCT(K34:K45,$G34:$G45) -> 0 | L46: =SUM(L34:L45) -> 0 | M46: =SUM(M34:M45) -> 0 | N46: =SUM(N34:N45) -> 0 | O46: =SUM(O34:O45) -> 0 | P46: =SUM(P34:P45) -> 0 | Q46: =SUMPRODUCT(Q34:Q45,$G34:$G45) -> 0
A47: Weighted Average: | G47: =G46/SUM(F34:F45) -> #DIV/0! | H47: =H46/$G46 -> #DIV/0! | I47: =I46/$G46 -> #DIV/0! | J47: =J46/$G46 -> #DIV/0! | K47: =K46/$G46 -> #DIV/0! | L47: =L46/$G46 -> #DIV/0! | M47: =M46/$G46 -> #DIV/0! | N47: =N46/$G46 -> #DIV/0! | O47: =O46/$G46 -> #DIV/0! | ... Q47: =Q46/$G46 -> #DIV/0! | R47: =Q47/H47 -> #DIV/0!
G49: Direct Cost | I49: Indirect Cost
C50: CLIN 5001 - FAR 52.217-8 Optional Extension of Services (OES) Regular Labor | I50: ='Indirect Rate Summary'!C38 -> 0 | J50: ='Indirect Rate Summary'!D38 -> 0 | M50: ='Indirect Rate Summary'!E38 -> 0 | O50: ='Indirect Rate Summary'!F38 -> 0
A51: =+A31 -> Location (Note 1) | B51: =+B31 -> Labor Type (Note 2) | C51: =+C31 -> Labor Categories (Note 3) | D51: =+D31 -> Effort To Be Performed By The Prime (P) or Subcontractor (S) (Note 4) | E51: =+E31 -> If Column D=S, Enter Name of Subcontractor(s) (Note 5) | F51: =+F31 -> FTEs (Note 6) | G51: =+G31 -> Total Productive Hours (Note 7) | H51: =+H31 -> Hourly Base Pay Rate (Note 8) | ... R51: =+R31 -> Wrap Rate
A52: =+A32 -> a | B52: =+B32 -> b | C52: =+C32 -> c | D52: =+D32 -> d | E52: =+E32 -> e | F52: =+F32 -> f | G52: =+G32 -> g | H52: =+H32 -> h | ... R52: =+R32 -> r = q/h
A53: =IF('Direct Labor Rate Schedule'!$A$10="","",'Direct Labor Rate Schedule'!$A$10)
A54: =A34 | B54: =B34 -> 0 | C54: =C34 -> Program Manager | D54: Enter P or S | F54: =G54/AnnualProductiveHours -> 0.48958333 | G54: 940 | H54: ='Direct Labor Rate Schedule'!N11 -> 0 | I54: =ROUND((+H54*$I$50),2) -> 0 | J54: =ROUND((+H54*$J$50),2) -> 0 | K54: =+H54+SUM(I54:J54) -> 0 | L54: =ROUND((+G54*K54),2) -> 0 | M54: =ROUND((+L54*$M$50),2) -> 0 | N54: =SUM(L54:M54) -> 0 | O54: =ROUND((+N54*$O$50),2) -> 0 | P54: =SUM(N54:O54) -> 0 | Q54: =IFERROR((+P54/G54),"") -> 0 | R54: =IFERROR(Q54/H54-1,"")
A55: =A35 | B55: =B35 -> 0 | C55: =C35 -> Senior Analyst | D55: Enter P or S | F55: =G55/AnnualProductiveHours -> 23.002604 | G55: 44165 | H55: ='Direct Labor Rate Schedule'!N12 -> 0 | I55: =ROUND((+H55*$I$50),2) -> 0 | J55: =ROUND((+H55*$J$50),2) -> 0 | K55: =+H55+SUM(I55:J55) -> 0 | L55: =ROUND((+G55*K55),2) -> 0 | M55: =ROUND((+L55*$M$50),2) -> 0 | N55: =SUM(L55:M55) -> 0 | O55: =ROUND((+N55*$O$50),2) -> 0 | P55: =SUM(N55:O55) -> 0 | Q55: =IFERROR((+P55/G55),"") -> 0 | R55: =IFERROR(Q55/H55-1,"")
A56: =A36 | B56: =B36 -> 0 | C56: =C36 -> Analyst | D56: Enter P or S | F56: =G56/AnnualProductiveHours -> 1.46875 | G56: 2820 | H56: ='Direct Labor Rate Schedule'!N13 -> 0 | I56: =ROUND((+H56*$I$50),2) -> 0 | J56: =ROUND((+H56*$J$50),2) -> 0 | K56: =+H56+SUM(I56:J56) -> 0 | L56: =ROUND((+G56*K56),2) -> 0 | M56: =ROUND((+L56*$M$50),2) -> 0 | N56: =SUM(L56:M56) -> 0 | O56: =ROUND((+N56*$O$50),2) -> 0 | P56: =SUM(N56:O56) -> 0 | Q56: =IFERROR((+P56/G56),"") -> 0 | R56: =IFERROR(Q56/H56-1,"")
A57: =A37 | B57: =B37 -> 0 | C57: =C37 -> Junior Analyst | D57: Enter P or S | F57: =G57/AnnualProductiveHours -> 1.46875 | G57: 2820 | H57: ='Direct Labor Rate Schedule'!N14 -> 0 | I57: =ROUND((+H57*$I$50),2) -> 0 | J57: =ROUND((+H57*$J$50),2) -> 0 | K57: =+H57+SUM(I57:J57) -> 0 | L57: =ROUND((+G57*K57),2) -> 0 | M57: =ROUND((+L57*$M$50),2) -> 0 | N57: =SUM(L57:M57) -> 0 | O57: =ROUND((+N57*$O$50),2) -> 0 | P57: =SUM(N57:O57) -> 0 | Q57: =IFERROR((+P57/G57),"") -> 0 | R57: =IFERROR(Q57/H57-1,"")
A58: =A38 | B58: =B38 -> 0 | C58: =C38 -> Senior Operations Research Analyst | D58: Enter P or S | F58: =G58/AnnualProductiveHours -> 1.46875 | G58: 2820 | H58: ='Direct Labor Rate Schedule'!N15 -> 0 | I58: =ROUND((+H58*$I$50),2) -> 0 | J58: =ROUND((+H58*$J$50),2) -> 0 | K58: =+H58+SUM(I58:J58) -> 0 | L58: =ROUND((+G58*K58),2) -> 0 | M58: =ROUND((+L58*$M$50),2) -> 0 | N58: =SUM(L58:M58) -> 0 | O58: =ROUND((+N58*$O$50),2) -> 0 | P58: =SUM(N58:O58) -> 0 | Q58: =IFERROR((+P58/G58),"") -> 0 | R58: =IFERROR(Q58/H58-1,"")
A59: =A39 | B59: =B39 -> 0 | C59: =C39 -> Operations Research Analyst | D59: Enter P or S | F59: =G59/AnnualProductiveHours -> 0.97916667 | G59: 1880 | H59: ='Direct Labor Rate Schedule'!N16 -> 0 | I59: =ROUND((+H59*$I$50),2) -> 0 | J59: =ROUND((+H59*$J$50),2) -> 0 | K59: =+H59+SUM(I59:J59) -> 0 | L59: =ROUND((+G59*K59),2) -> 0 | M59: =ROUND((+L59*$M$50),2) -> 0 | N59: =SUM(L59:M59) -> 0 | O59: =ROUND((+N59*$O$50),2) -> 0 | P59: =SUM(N59:O59) -> 0 | Q59: =IFERROR((+P59/G59),"") -> 0 | R59: =IFERROR(Q59/H59-1,"")
A60: =A40 | B60: =B40 -> 0 | C60: =C40 -> Graphics Design Senior Analyst | D60: Enter P or S | F60: =G60/AnnualProductiveHours -> 0.48958333 | G60: 940 | H60: ='Direct Labor Rate Schedule'!N17 -> 0 | I60: =ROUND((+H60*$I$50),2) -> 0 | J60: =ROUND((+H60*$J$50),2) -> 0 | K60: =+H60+SUM(I60:J60) -> 0 | L60: =ROUND((+G60*K60),2) -> 0 | M60: =ROUND((+L60*$M$50),2) -> 0 | N60: =SUM(L60:M60) -> 0 | O60: =ROUND((+N60*$O$50),2) -> 0 | P60: =SUM(N60:O60) -> 0 | Q60: =IFERROR((+P60/G60),"") -> 0 | R60: =IFERROR(Q60/H60-1,"")
A61: =A41 | B61: =B41 -> 0 | C61: =C41 -> Force Documentation Senior Analyst | D61: Enter P or S | F61: =G61/AnnualProductiveHours -> 0.48958333 | G61: 940 | H61: ='Direct Labor Rate Schedule'!N18 -> 0 | I61: =ROUND((+H61*$I$50),2) -> 0 | J61: =ROUND((+H61*$J$50),2) -> 0 | K61: =+H61+SUM(I61:J61) -> 0 | L61: =ROUND((+G61*K61),2) -> 0 | M61: =ROUND((+L61*$M$50),2) -> 0 | N61: =SUM(L61:M61) -> 0 | O61: =ROUND((+N61*$O$50),2) -> 0 | P61: =SUM(N61:O61) -> 0 | Q61: =IFERROR((+P61/G61),"") -> 0 | R61: =IFERROR(Q61/H61-1,"")
A62: =A42 | B62: =B42 -> 0 | C62: =C42 -> 0 | D62: Enter P or S | F62: =G62/AnnualProductiveHours -> 0 | G62: 0 | H62: ='Direct Labor Rate Schedule'!N19 -> 0 | I62: =ROUND((+H62*$I$50),2) -> 0 | J62: =ROUND((+H62*$J$50),2) -> 0 | K62: =+H62+SUM(I62:J62) -> 0 | L62: =ROUND((+G62*K62),2) -> 0 | M62: =ROUND((+L62*$M$50),2) -> 0 | N62: =SUM(L62:M62) -> 0 | O62: =ROUND((+N62*$O$50),2) -> 0 | P62: =SUM(N62:O62) -> 0 | Q62: =IFERROR((+P62/G62),"") | R62: =IFERROR(Q62/H62-1,"")
A63: =A43 | B63: =B43 -> 0 | C63: =C43 -> 0 | D63: Enter P or S | F63: =G63/AnnualProductiveHours -> 0 | G63: 0 | H63: ='Direct Labor Rate Schedule'!N20 -> 0 | I63: =ROUND((+H63*$I$50),2) -> 0 | J63: =ROUND((+H63*$J$50),2) -> 0 | K63: =+H63+SUM(I63:J63) -> 0 | L63: =ROUND((+G63*K63),2) -> 0 | M63: =ROUND((+L63*$M$50),2) -> 0 | N63: =SUM(L63:M63) -> 0 | O63: =ROUND((+N63*$O$50),2) -> 0 | P63: =SUM(N63:O63) -> 0 | Q63: =IFERROR((+P63/G63),"") | R63: =IFERROR(Q63/H63-1,"")
A64: =A44 | B64: =B44 -> 0 | C64: =C44 -> 0 | D64: Enter P or S | F64: =G64/AnnualProductiveHours -> 0 | G64: 0 | H64: ='Direct Labor Rate Schedule'!N21 -> 0 | I64: =ROUND((+H64*$I$50),2) -> 0 | J64: =ROUND((+H64*$J$50),2) -> 0 | K64: =+H64+SUM(I64:J64) -> 0 | L64: =ROUND((+G64*K64),2) -> 0 | M64: =ROUND((+L64*$M$50),2) -> 0 | N64: =SUM(L64:M64) -> 0 | O64: =ROUND((+N64*$O$50),2) -> 0 | P64: =SUM(N64:O64) -> 0 | Q64: =IFERROR((+P64/G64),"") | R64: =IFERROR(Q64/H64-1,"")
A65: =A45 | B65: =B45 -> 0 | C65: =C45 -> 0 | D65: Enter P or S | F65: =G65/AnnualProductiveHours -> 0 | G65: 0 | H65: ='Direct Labor Rate Schedule'!N22 -> 0 | I65: =ROUND((+H65*$I$50),2) -> 0 | J65: =ROUND((+H65*$J$50),2) -> 0 | K65: =+H65+SUM(I65:J65) -> 0 | L65: =ROUND((+G65*K65),2) -> 0 | M65: =ROUND((+L65*$M$50),2) -> 0 | N65: =SUM(L65:M65) -> 0 | O65: =ROUND((+N65*$O$50),2) -> 0 | P65: =SUM(N65:O65) -> 0 | Q65: =IFERROR((+P65/G65),"") | R65: =IFERROR(Q65/H65-1,"")
A66: Total: | F66: =SUM(F54:F65) -> 29.856771 | G66: =SUM(G54:G65) -> 57325 | H66: =SUMPRODUCT(H54:H65,$G54:$G65) -> 0 | I66: =SUMPRODUCT(I54:I65,$G54:$G65) -> 0 | J66: =SUMPRODUCT(J54:J65,$G54:$G65) -> 0 | K66: =SUMPRODUCT(K54:K65,$G54:$G65) -> 0 | L66: =SUM(L54:L65) -> 0 | M66: =SUM(M54:M65) -> 0 | N66: =SUM(N54:N65) -> 0 | O66: =SUM(O54:O65) -> 0 | P66: =SUM(P54:P65) -> 0 | Q66: =SUMPRODUCT(Q54:Q65,$G54:$G65) -> 0
A67: Weighted Average: | G67: =G66/SUM(F54:F65) -> 1920 | H67: =H66/$G66 -> 0 | I67: =I66/$G66 -> 0 | J67: =J66/$G66 -> 0 | K67: =K66/$G66 -> 0 | L67: =L66/$G66 -> 0 | M67: =M66/$G66 -> 0 | N67: =N66/$G66 -> 0 | O67: =O66/$G66 -> 0 | ... Q67: =Q66/$G66 -> 0 | R67: =Q67/H67 -> #DIV/0!
G69: Direct Cost | I69: Indirect Cost
C70: CLIN 5002 - FAR 52.217-8 Optional Extension of Services (OES) Optional Surge Labor | I70: =I50 -> 0 | J70: =J50 -> 0 | M70: =M50 -> 0 | O70: =O50 -> 0
A71: =+A51 -> Location (Note 1) | B71: =+B51 -> Labor Type (Note 2) | C71: =+C51 -> Labor Categories (Note 3) | D71: =+D51 -> Effort To Be Performed By The Prime (P) or Subcontractor (S) (Note 4) | E71: =+E51 -> If Column D=S, Enter Name of Subcontractor(s) (Note 5) | F71: =+F51 -> FTEs (Note 6) | G71: =+G51 -> Total Productive Hours (Note 7) | H71: =+H51 -> Hourly Base Pay Rate (Note 8) | ... R71: =+R51 -> Wrap Rate
A72: =+A52 -> a | B72: =+B52 -> b | C72: =+C52 -> c | D72: =+D52 -> d | E72: =+E52 -> e | F72: =+F52 -> f | G72: =+G52 -> g | H72: =+H52 -> h | ... R72: =+R52 -> r = q/h
A73: =IF('Direct Labor Rate Schedule'!$A$10="","",'Direct Labor Rate Schedule'!$A$10)
A74: =A54 | B74: =B54 -> 0 | C74: =C54 -> Program Manager | D74: Enter P or S | F74: =G74/AnnualProductiveHours -> 0 | G74: 0 | H74: =H54 -> 0 | I74: =ROUND((+H74*$I$70),2) -> 0 | J74: =ROUND((+H74*$J$70),2) -> 0 | K74: =+H74+SUM(I74:J74) -> 0 | L74: =ROUND((+G74*K74),2) -> 0 | M74: =ROUND((+L74*$M$70),2) -> 0 | N74: =SUM(L74:M74) -> 0 | O74: =ROUND((+N74*$O$70),2) -> 0 | P74: =SUM(N74:O74) -> 0 | Q74: =IFERROR((+P74/G74),"") | R74: =IFERROR(Q74/H74-1,"")
A75: =A55 | B75: =B55 -> 0 | C75: =C55 -> Senior Analyst | D75: Enter P or S | F75: =G75/AnnualProductiveHours -> 5.875 | G75: 11280 | H75: =H55 -> 0 | I75: =ROUND((+H75*$I$70),2) -> 0 | J75: =ROUND((+H75*$J$70),2) -> 0 | K75: =+H75+SUM(I75:J75) -> 0 | L75: =ROUND((+G75*K75),2) -> 0 | M75: =ROUND((+L75*$M$70),2) -> 0 | N75: =SUM(L75:M75) -> 0 | O75: =ROUND((+N75*$O$70),2) -> 0 | P75: =SUM(N75:O75) -> 0 | Q75: =IFERROR((+P75/G75),"") -> 0 | R75: =IFERROR(Q75/H75-1,"")
A76: =A56 | B76: =B56 -> 0 | C76: =C56 -> Analyst | D76: Enter P or S | F76: =G76/AnnualProductiveHours -> 1.9583333 | G76: 3760 | H76: =H56 -> 0 | I76: =ROUND((+H76*$I$70),2) -> 0 | J76: =ROUND((+H76*$J$70),2) -> 0 | K76: =+H76+SUM(I76:J76) -> 0 | L76: =ROUND((+G76*K76),2) -> 0 | M76: =ROUND((+L76*$M$70),2) -> 0 | N76: =SUM(L76:M76) -> 0 | O76: =ROUND((+N76*$O$70),2) -> 0 | P76: =SUM(N76:O76) -> 0 | Q76: =IFERROR((+P76/G76),"") -> 0 | R76: =IFERROR(Q76/H76-1,"")
A77: =A57 | B77: =B57 -> 0 | C77: =C57 -> Junior Analyst | D77: Enter P or S | F77: =G77/AnnualProductiveHours -> 0 | G77: 0 | H77: =H57 -> 0 | I77: =ROUND((+H77*$I$70),2) -> 0 | J77: =ROUND((+H77*$J$70),2) -> 0 | K77: =+H77+SUM(I77:J77) -> 0 | L77: =ROUND((+G77*K77),2) -> 0 | M77: =ROUND((+L77*$M$70),2) -> 0 | N77: =SUM(L77:M77) -> 0 | O77: =ROUND((+N77*$O$70),2) -> 0 | P77: =SUM(N77:O77) -> 0 | Q77: =IFERROR((+P77/G77),"") | R77: =IFERROR(Q77/H77-1,"")
A78: =A58 | B78: =B58 -> 0 | C78: =C58 -> Senior Operations Research Analyst | D78: Enter P or S | F78: =G78/AnnualProductiveHours -> 2.9375 | G78: 5640 | H78: =H58 -> 0 | I78: =ROUND((+H78*$I$70),2) -> 0 | J78: =ROUND((+H78*$J$70),2) -> 0 | K78: =+H78+SUM(I78:J78) -> 0 | L78: =ROUND((+G78*K78),2) -> 0 | M78: =ROUND((+L78*$M$70),2) -> 0 | N78: =SUM(L78:M78) -> 0 | O78: =ROUND((+N78*$O$70),2) -> 0 | P78: =SUM(N78:O78) -> 0 | Q78: =IFERROR((+P78/G78),"") -> 0 | R78: =IFERROR(Q78/H78-1,"")
A79: =A59 | B79: =B59 -> 0 | C79: =C59 -> Operations Research Analyst | D79: Enter P or S | F79: =G79/AnnualProductiveHours -> 1.46875 | G79: 2820 | H79: =H59 -> 0 | I79: =ROUND((+H79*$I$70),2) -> 0 | J79: =ROUND((+H79*$J$70),2) -> 0 | K79: =+H79+SUM(I79:J79) -> 0 | L79: =ROUND((+G79*K79),2) -> 0 | M79: =ROUND((+L79*$M$70),2) -> 0 | N79: =SUM(L79:M79) -> 0 | O79: =ROUND((+N79*$O$70),2) -> 0 | P79: =SUM(N79:O79) -> 0 | Q79: =IFERROR((+P79/G79),"") -> 0 | R79: =IFERROR(Q79/H79-1,"")
A80: =A60 | B80: =B60 -> 0 | C80: =C60 -> Graphics Design Senior Analyst | D80: Enter P or S | F80: =G80/AnnualProductiveHours -> 0 | G80: 0 | H80: =H60 -> 0 | I80: =ROUND((+H80*$I$70),2) -> 0 | J80: =ROUND((+H80*$J$70),2) -> 0 | K80: =+H80+SUM(I80:J80) -> 0 | L80: =ROUND((+G80*K80),2) -> 0 | M80: =ROUND((+L80*$M$70),2) -> 0 | N80: =SUM(L80:M80) -> 0 | O80: =ROUND((+N80*$O$70),2) -> 0 | P80: =SUM(N80:O80) -> 0 | Q80: =IFERROR((+P80/G80),"") | R80: =IFERROR(Q80/H80-1,"")
A81: =A61 | B81: =B61 -> 0 | C81: =C61 -> Force Documentation Senior Analyst | D81: Enter P or S | F81: =G81/AnnualProductiveHours -> 0 | G81: 0 | H81: =H61 -> 0 | I81: =ROUND((+H81*$I$70),2) -> 0 | J81: =ROUND((+H81*$J$70),2) -> 0 | K81: =+H81+SUM(I81:J81) -> 0 | L81: =ROUND((+G81*K81),2) -> 0 | M81: =ROUND((+L81*$M$70),2) -> 0 | N81: =SUM(L81:M81) -> 0 | O81: =ROUND((+N81*$O$70),2) -> 0 | P81: =SUM(N81:O81) -> 0 | Q81: =IFERROR((+P81/G81),"") | R81: =IFERROR(Q81/H81-1,"")
A82: =A62 | B82: =B62 -> 0 | C82: =C62 -> 0 | D82: Enter P or S | F82: =G82/AnnualProductiveHours -> 0 | G82: 0 | H82: =H62 -> 0 | I82: =ROUND((+H82*$I$70),2) -> 0 | J82: =ROUND((+H82*$J$70),2) -> 0 | K82: =+H82+SUM(I82:J82) -> 0 | L82: =ROUND((+G82*K82),2) -> 0 | M82: =ROUND((+L82*$M$70),2) -> 0 | N82: =SUM(L82:M82) -> 0 | O82: =ROUND((+N82*$O$70),2) -> 0 | P82: =SUM(N82:O82) -> 0 | Q82: =IFERROR((+P82/G82),"") | R82: =IFERROR(Q82/H82-1,"")
A83: =A63 | B83: =B63 -> 0 | C83: =C63 -> 0 | D83: Enter P or S | F83: =G83/AnnualProductiveHours -> 0 | G83: 0 | H83: =H63 -> 0 | I83: =ROUND((+H83*$I$70),2) -> 0 | J83: =ROUND((+H83*$J$70),2) -> 0 | K83: =+H83+SUM(I83:J83) -> 0 | L83: =ROUND((+G83*K83),2) -> 0 | M83: =ROUND((+L83*$M$70),2) -> 0 | N83: =SUM(L83:M83) -> 0 | O83: =ROUND((+N83*$O$70),2) -> 0 | P83: =SUM(N83:O83) -> 0 | Q83: =IFERROR((+P83/G83),"") | R83: =IFERROR(Q83/H83-1,"")
A84: =A64 | B84: =B64 -> 0 | C84: =C64 -> 0 | D84: Enter P or S | F84: =G84/AnnualProductiveHours -> 0 | G84: 0 | H84: =H64 -> 0 | I84: =ROUND((+H84*$I$70),2) -> 0 | J84: =ROUND((+H84*$J$70),2) -> 0 | K84: =+H84+SUM(I84:J84) -> 0 | L84: =ROUND((+G84*K84),2) -> 0 | M84: =ROUND((+L84*$M$70),2) -> 0 | N84: =SUM(L84:M84) -> 0 | O84: =ROUND((+N84*$O$70),2) -> 0 | P84: =SUM(N84:O84) -> 0 | Q84: =IFERROR((+P84/G84),"") | R84: =IFERROR(Q84/H84-1,"")
A85: =A65 | B85: =B65 -> 0 | C85: =C65 -> 0 | D85: Enter P or S | F85: =G85/AnnualProductiveHours -> 0 | G85: 0 | H85: =H65 -> 0 | I85: =ROUND((+H85*$I$70),2) -> 0 | J85: =ROUND((+H85*$J$70),2) -> 0 | K85: =+H85+SUM(I85:J85) -> 0 | L85: =ROUND((+G85*K85),2) -> 0 | M85: =ROUND((+L85*$M$70),2) -> 0 | N85: =SUM(L85:M85) -> 0 | O85: =ROUND((+N85*$O$70),2) -> 0 | P85: =SUM(N85:O85) -> 0 | Q85: =IFERROR((+P85/G85),"") | R85: =IFERROR(Q85/H85-1,"")
A86: Total: | F86: =SUM(F74:F85) -> 12.239583 | G86: =SUM(G74:G85) -> 23500 | H86: =SUMPRODUCT(H74:H85,$G74:$G85) -> 0 | I86: =SUMPRODUCT(I74:I85,$G74:$G85) -> 0 | J86: =SUMPRODUCT(J74:J85,$G74:$G85) -> 0 | K86: =SUMPRODUCT(K74:K85,$G74:$G85) -> 0 | L86: =SUM(L74:L85) -> 0 | M86: =SUM(M74:M85) -> 0 | N86: =SUM(N74:N85) -> 0 | O86: =SUM(O74:O85) -> 0 | P86: =SUM(P74:P85) -> 0 | Q86: =SUMPRODUCT(Q74:Q85,$G74:$G85) -> 0
A87: Weighted Average: | G87: =G86/SUM(F74:F85) -> 1920 | H87: =H86/$G86 -> 0 | I87: =I86/$G86 -> 0 | J87: =J86/$G86 -> 0 | K87: =K86/$G86 -> 0 | L87: =L86/$G86 -> 0 | M87: =M86/$G86 -> 0 | N87: =N86/$G86 -> 0 | O87: =O86/$G86 -> 0 | ... Q87: =Q86/$G86 -> 0 | R87: =Q87/H87 -> #DIV/0!
A90: Total: | G90: =G86+G66+G46+G26 -> 83477 | H90: =H86+H66+H46+H26 -> 0 | I90: =I86+I66+I46+I26 -> 0 | J90: =J86+J66+J46+J26 -> 0 | K90: =K86+K66+K46+K26 -> 0 | L90: =L86+L66+L46+L26 -> 0 | M90: =M86+M66+M46+M26 -> 0 | N90: =N86+N66+N46+N26 -> 0 | ... Q90: =Q86+Q66+Q46+Q26 -> 0
A91: Weighted Average: | H91: =H90/$G$90 -> 0 | I91: =I90/$G$90 -> 0 | J91: =J90/$G$90 -> 0 | K91: =K90/$G$90 -> 0 | L91: =L90/$G$90 -> 0 | M91: =M90/$G$90 -> 0 | N91: =N90/$G$90 -> 0 | O91: =O90/$G$90 -> 0 | ... Q91: =Q90/$G$90 -> 0 | R91: =Q91/H91 -> #DIV/0!

Sheet ODC Cost Detail
A1: ODC Cost Detail Spreadsheet (Note 13)
A2: ="Solicitation Number: "&Instructions!H9&"" -> Solicitation Number: W91CRB-25-R-0002
A3: ="Name of Action: "&Instructions!H10 -> Name of Action: Force Development
A4: ="Prime Contractor/Subcontractor Name/Division: "&Instructions!H15 -> Prime Contractor/Subcontractor Name/Division:
A5: ="Period of Performance: "&Instructions!H11 -> Period of Performance:
A6: ="Date of Proposal:"&IF(ISBLANK(Instructions!H18)," TBD",(TEXT(Instructions!H18," mm/dd/yyyy"))) -> Date of Proposal: TBD
A8: CLIN | B8: Description | C8: ODCs Ceiling (Normalized) | D8: Burdens, G&A Rate | E8: G&A, Burdens | F8: Total ODCs
A9: a | B9: b | C9: c | D9: d | E9: e = c x d | F9: f = c + e
A10: 0003 | B10: Travel & ODCs Base Period | C10: 100000 | E10: =ROUND((+C10*D10),2) -> 0 | F10: =C10+E10 -> 100000
A11: 1003 | B11: Travel & ODCs Option Year (OY) 1 | C11: 100000 | E11: =ROUND((+C11*D11),2) -> 0 | F11: =C11+E11 -> 100000
A12: 2003 | B12: Travel & ODCs OY2 | C12: 100000 | E12: =ROUND((+C12*D12),2) -> 0 | F12: =C12+E12 -> 100000
A13: 3003 | B13: Travel & ODCs OY3 | C13: 100000 | E13: =ROUND((+C13*D13),2) -> 0 | F13: =C13+E13 -> 100000
A14: 4003 | B14: Travel & ODCs OY4 | C14: 100000 | E14: =ROUND((+C14*D14),2) -> 0 | F14: =C14+E14 -> 100000
A15: 5003 | B15: Travel & ODCs Optional Ext. of Services | C15: 50000 | E15: =ROUND((+C15*D15),2) -> 0 | F15: =C15+E15 -> 50000
B16: Total: | C16: =SUM(C10:C15) -> 550000 | E16: =SUM(E10:E15) -> 0 | F16: =SUM(F10:F15) -> 550000
C17: (To Section B) | D17: =SUMPRODUCT(C10:C15,D10:D15)/C16 -> 0 | E17: Average Burden

Sheet Fringe Benefit Worksheet
A1: Fringe Benefits Worksheet
A2: ="Solicitation Number: "&Instructions!H9&"" -> Solicitation Number: W91CRB-25-R-0002
A3: ="Name of Action: "&Instructions!H10 -> Name of Action: Force Development
A4: ="Prime Contractor/Subcontractor Name/Division: "&Instructions!H15 -> Prime Contractor/Subcontractor Name/Division:
A5: ="Period of Performance: "&Instructions!H11 -> Period of Performance:
A6: ="Date of Proposal:"&IF(ISBLANK(Instructions!H18)," TBD",(TEXT(Instructions!H18," mm/dd/yyyy"))) -> Date of Proposal: TBD
A8: Statutory Fringe Benefits:* | B8: Enter %**
A9: FICA | B9: 0
A10: FUTA | B10: 0
A11: SUTA | B11: 0
A12: Workman's Compensation | B12: 0
A13: Etc - Enter Additional Categories As Needed | B13: 0
A16: Fringe Benefits:* | B16: Fringe benefit offered to all professional employees? (Yes/No) (Explain, if no) | C16: Employer Share | D16: Employee Share, if applicable | E16: Enter %** | F16: Describe fringe benefit and enter any additional comments
A17: Paid Leave/Vacation | E17: 0
A18: Holidays | E18: 0
A19: Sick Leave | E19: 0
A20: Jury Duty | E20: 0
A21: Military Leave | E21: 0
A22: Bereavement Leave | E22: 0
A23: Health Insurance | E23: 0
A24: Health/Flexible Spending Account | E24: 0
A25: Dental Insurance | E25: 0
A26: Vision Insurance | E26: 0
A27: Health Reimbursement | E27: 0
A28: Disability Insurance Short & Term | E28: 0
... A34: Etc - Enter Additional Categories As Needed | E34: 0
A37: Paid Leave/Vacation (PTO, Sick, Military, etc.) | B37: Years of Experience | C37: Hours Alloted Per Year
A49: *Please enter all the fringe benefit categories to be offered to professional FLSA exempt employees under this contract. Please complete this sheet for each fringe benefit pool if multiple pools exist.
A50: **What % of the fringe benefit category contributes to the overall fringe benefit rate?

Sheet Fringe Worksheet
A1: Fringe Rate Worksheet
A2: ="Solicitation Number: "&Instructions!H9&"" -> Solicitation Number: W91CRB-25-R-0002
A3: ="Name of Action: "&Instructions!H10 -> Name of Action: Force Development
A4: ="Prime Contractor/Subcontractor Name/Division: "&Instructions!H15 -> Prime Contractor/Subcontractor Name/Division:
A5: ="Period of Performance: "&Instructions!H11 -> Period of Performance:
A6: ="Date of Proposal:"&IF(ISBLANK(Instructions!H18)," TBD",(TEXT(Instructions!H18," mm/dd/yyyy"))) -> Date of Proposal: TBD
A8: Fringe Expenses: | B8: FY2021 Actual | C8: FY2022 Actual | D8: FY2023 Actual | E8: Estimated Year 1 | F8: Estimated Year 2 | G8: Estimated Year 3 | H8: Estimated Year 4 | I8: Estimated Year 5 | J8: Estimated Months 61-66 | K8: Explanation
A9: Indirect payroll | B9: 0 | C9: 0 | D9: 0 | E9: 0 | F9: 0 | G9: 0 | H9: 0 | I9: 0 | J9: 0
A10: Payroll taxes (FICA, FUTA, SUTA, Workmans Comp) | B10: 0 | C10: 0 | D10: 0 | E10: 0 | F10: 0 | G10: 0 | H10: 0 | I10: 0 | J10: 0
A11: Vacation (PTO) | B11: 0 | C11: 0 | D11: 0 | E11: 0 | F11: 0 | G11: 0 | H11: 0 | I11: 0 | J11: 0
A12: Holiday | B12: 0 | C12: 0 | D12: 0 | E12: 0 | F12: 0 | G12: 0 | H12: 0 | I12: 0 | J12: 0
A13: Sick Leave | B13: 0 | C13: 0 | D13: 0 | E13: 0 | F13: 0 | G13: 0 | H13: 0 | I13: 0 | J13: 0
A14: Health/Disability Ins | B14: 0 | C14: 0 | D14: 0 | E14: 0 | F14: 0 | G14: 0 | H14: 0 | I14: 0 | J14: 0
A15: Workmans Compensation/Defense Base Act | B15: 0 | C15: 0 | D15: 0 | E15: 0 | F15: 0 | G15: 0 | H15: 0 | I15: 0 | J15: 0
A16: Bonuses | B16: 0 | C16: 0 | D16: 0 | E16: 0 | F16: 0 | G16: 0 | H16: 0 | I16: 0 | J16: 0
A17: Retention Pay | B17: 0 | C17: 0 | D17: 0 | E17: 0 | F17: 0 | G17: 0 | H17: 0 | I17: 0 | J17: 0
A18: 401k Match | B18: 0 | C18: 0 | D18: 0 | E18: 0 | F18: 0 | G18: 0 | H18: 0 | I18: 0 | J18: 0
A19: Mil Leave | B19: 0 | C19: 0 | D19: 0 | E19: 0 | F19: 0 | G19: 0 | H19: 0 | I19: 0 | J19: 0
A20: Administrative Leave | B20: 0 | C20: 0 | D20: 0 | E20: 0 | F20: 0 | G20: 0 | H20: 0 | I20: 0 | J20: 0
A21: Insurance | B21: 0 | C21: 0 | D21: 0 | E21: 0 | F21: 0 | G21: 0 | H21: 0 | I21: 0 | J21: 0
A22: Total Pool | B22: =SUM(B9:B21) -> 0 | C22: =SUM(C9:C21) -> 0 | D22: =SUM(D9:D21) -> 0 | E22: =SUM(E9:E21) -> 0 | F22: =SUM(F9:F21) -> 0 | G22: =SUM(G9:G21) -> 0 | H22: =SUM(H9:H21) -> 0 | I22: =SUM(I9:I21) -> 0 | J22: =SUM(J9:J21) -> 0
A24: Less: FAR 31 Unallowable Cost
A25: Entertainment, etc. | B25: 0 | C25: 0 | D25: 0 | E25: 0 | F25: 0 | G25: 0 | H25: 0 | I25: 0 | J25: 0
A26: Total Unallowable Costs | B26: =SUM(B25) -> 0 | C26: =SUM(C25) -> 0 | D26: =SUM(D25) -> 0 | E26: =SUM(E25) -> 0 | F26: 0 | G26: =SUM(G25) -> 0 | H26: 0 | I26: =SUM(I25) -> 0 | J26: 0
A27: Net Allowable cost | B27: =B22-B26 -> 0 | C27: =C22-C26 -> 0 | D27: =D22-D26 -> 0 | E27: =E22-E26 -> 0 | F27: =F22-F26 -> 0 | G27: =G22-G26 -> 0 | H27: =H22-H26 -> 0 | I27: =I22-I26 -> 0 | J27: =J22-J26 -> 0
A29: Labor Base
A30: Direct Labor | B30: 0 | C30: 0 | D30: 0 | E30: 0 | F30: 0 | G30: 0 | H30: 0 | I30: 0 | J30: 0
A31: OH Labor | B31: 0 | C31: 0 | D31: 0 | E31: 0 | F31: 0 | G31: 0 | H31: 0 | I31: 0 | J31: 0
A32: G&A Labor | B32: 0 | C32: 0 | D32: 0 | E32: 0 | F32: 0 | G32: 0 | H32: 0 | I32: 0 | J32: 0
A33: Total Labor Base | B33: =SUM(B30:B32) -> 0 | C33: =SUM(C30:C32) -> 0 | D33: =SUM(D30:D32) -> 0 | E33: =SUM(E30:E32) -> 0 | F33: =SUM(F30:F32) -> 0 | G33: =SUM(G30:G32) -> 0 | H33: =SUM(H30:H32) -> 0 | I33: =SUM(I30:I32) -> 0 | J33: =SUM(J30:J32) -> 0
A35: Rate | B35: =ROUND(+B27/B33,4) -> #DIV/0! | C35: =ROUND(+C27/C33,4) -> #DIV/0! | D35: =ROUND(+D27/D33,4) -> #DIV/0! | E35: =ROUND(+E27/E33,4) -> #DIV/0! | F35: =ROUND(+F27/F33,4) -> #DIV/0! | G35: =ROUND(+G27/G33,4) -> #DIV/0! | H35: =ROUND(+H27/H33,4) -> #DIV/0! | I35: =ROUND(+I27/I33,4) -> #DIV/0! | J35: =ROUND(+J27/J33,4) -> #DIV/0!

Sheet Overhead Worksheet
A1: Overhead Rate Worksheet
A2: ="Solicitation Number: "&Instructions!H9&"" -> Solicitation Number: W91CRB-25-R-0002
A3: ="Name of Action: "&Instructions!H10 -> Name of Action: Force Development
A4: ="Prime Contractor/Subcontractor Name/Division: "&Instructions!H15 -> Prime Contractor/Subcontractor Name/Division:
A5: ="Period of Performance: "&Instructions!H11 -> Period of Performance:
A6: ="Date of Proposal:"&IF(ISBLANK(Instructions!H18)," TBD",(TEXT(Instructions!H18," mm/dd/yyyy"))) -> Date of Proposal: TBD
A8: Overhead Expenses: | B8: FY2021 Actual | C8: FY2022 Actual | D8: FY2023 Actual | E8: Estimated Year 1 | F8: Estimated Year 2 | G8: Estimated Year 3 | H8: Estimated Option Year 4 | I8: Estimated Option Year 5 | J8: Estimated Months 61-66 | K8: Explanation
A9: Labor | B9: 0 | C9: 0 | D9: 0 | E9: 0 | F9: 0 | G9: 0 | H9: 0 | I9: 0 | J9: 0
A10: Travel | B10: 0 | C10: 0 | D10: 0 | E10: 0 | F10: 0 | G10: 0 | H10: 0 | I10: 0 | J10: 0
A11: Transportation Costs | B11: 0 | C11: 0 | D11: 0 | E11: 0 | F11: 0 | G11: 0 | H11: 0 | I11: 0 | J11: 0
A12: Supplies | B12: 0 | C12: 0 | D12: 0 | E12: 0 | F12: 0 | G12: 0 | H12: 0 | I12: 0 | J12: 0
A13: Employment Advertising & Screening | B13: 0 | C13: 0 | D13: 0 | E13: 0 | F13: 0 | G13: 0 | H13: 0 | I13: 0 | J13: 0
A14: Telephone | B14: 0 | C14: 0 | D14: 0 | E14: 0 | F14: 0 | G14: 0 | H14: 0 | I14: 0 | J14: 0
A15: Uniforms | B15: 0 | C15: 0 | D15: 0 | E15: 0 | F15: 0 | G15: 0 | H15: 0 | I15: 0 | J15: 0
A16: Postage | B16: 0 | C16: 0 | D16: 0 | E16: 0 | F16: 0 | G16: 0 | H16: 0 | I16: 0 | J16: 0
A17: Auto Repair & Maintenance | B17: 0 | C17: 0 | D17: 0 | E17: 0 | F17: 0 | G17: 0 | H17: 0 | I17: 0 | J17: 0
B18: 0 | C18: 0 | D18: 0 | E18: 0 | F18: 0 | G18: 0 | H18: 0 | I18: 0 | J18: 0
B19: 0 | C19: 0 | D19: 0 | E19: 0 | F19: 0 | G19: 0 | H19: 0 | I19: 0 | J19: 0
B20: 0 | C20: 0 | D20: 0 | E20: 0 | F20: 0 | G20: 0 | H20: 0 | I20: 0 | J20: 0
B21: 0 | C21: 0 | D21: 0 | E21: 0 | F21: 0 | G21: 0 | H21: 0 | I21: 0 | J21: 0
B22: =SUM(B9:B21) -> 0 | C22: =SUM(C9:C21) -> 0 | D22: =SUM(D9:D21) -> 0 | E22: =SUM(E9:E21) -> 0 | F22: =SUM(F9:F21) -> 0 | G22: =SUM(G9:G21) -> 0 | H22: =SUM(H9:H21) -> 0 | I22: =SUM(I9:I21) -> 0 | J22: =SUM(J9:J21) -> 0
A24: Less: FAR 31 Unallowable Cost
A25: Entertainment, etc. | B25: 0 | C25: 0 | D25: 0 | E25: 0 | F25: 0 | G25: 0 | H25: 0 | I25: 0 | J25: 0
A26: Total Unallowable Costs | B26: =SUM(B25) -> 0 | C26: =SUM(C25) -> 0 | D26: =SUM(D25) -> 0 | E26: =SUM(E25) -> 0 | F26: 0 | G26: =SUM(G25) -> 0 | H26: 0 | I26: 0 | J26: =SUM(J25) -> 0
A27: Net Allowable cost | B27: =B22-B26 -> 0 | C27: =C22-C26 -> 0 | D27: =D22-D26 -> 0 | E27: =E22-E26 -> 0 | F27: =F22-F26 -> 0 | G27: =G22-G26 -> 0 | H27: =H22-H26 -> 0 | I27: =I22-I26 -> 0 | J27: =J22-J26 -> 0
A29: Labor Base
A30: Direct Labor | B30: 0 | C30: 0 | D30: 0 | E30: 0 | F30: 0 | G30: 0 | H30: 0 | I30: 0 | J30: 0
A31: OH Labor | B31: 0 | C31: 0 | D31: 0 | E31: 0 | F31: 0 | G31: 0 | H31: 0 | I31: 0 | J31: 0
A32: B&P Labor | B32: 0 | C32: 0 | D32: 0 | E32: 0 | F32: 0 | G32: 0 | H32: 0 | I32: 0 | J32: 0
A33: Total Labor Base | B33: =SUM(B30:B32) -> 0 | C33: =SUM(C30:C32) -> 0 | D33: =SUM(D30:D32) -> 0 | E33: =SUM(E30:E32) -> 0 | F33: =SUM(F30:F32) -> 0 | G33: =SUM(G30:G32) -> 0 | H33: =SUM(H30:H32) -> 0 | I33: =SUM(I30:I32) -> 0 | J33: =SUM(J30:J32) -> 0
A35: Rate | B35: =ROUND(+B27/B33,4) -> #DIV/0! | C35: =ROUND(+C27/C33,4) -> #DIV/0! | D35: =ROUND(+D27/D33,4) -> #DIV/0! | E35: =ROUND(+E27/E33,4) -> #DIV/0! | F35: =ROUND(+F27/F33,4) -> #DIV/0! | G35: =ROUND(+G27/G33,4) -> #DIV/0! | H35: =ROUND(+H27/H33,4) -> #DIV/0! | I35: =ROUND(+I27/I33,4) -> #DIV/0! | J35: =ROUND(+J27/J33,4) -> #DIV/0!

Sheet G&A Worksheet
A1: G&A Rate Worksheet
A2: ="Solicitation Number: "&Instructions!H9&"" -> Solicitation Number: W91CRB-25-R-0002
A3: ="Name of Action: "&Instructions!H10 -> Name of Action: Force Development
A4: ="Prime Contractor/Subcontractor Name/Division: "&Instructions!H15 -> Prime Contractor/Subcontractor Name/Division:
A5: ="Period of Performance: "&Instructions!H11 -> Period of Performance:
A6: ="Date of Proposal:"&IF(ISBLANK(Instructions!H18)," TBD",(TEXT(Instructions!H18," mm/dd/yyyy"))) -> Date of Proposal: TBD
A8: G&A Expenses: | B8: FY2021 Actual | C8: FY2022 Actual | D8: FY2023 Actual | E8: Estimated Year 1 | F8: Estimated Year 2 | G8: Estimated Year 3 | H8: Estimated Year 4 | I8: Estimated Year 5 | J8: Estimated Months 61-66 | K8: Explanation
A9: Labor | B9: 0 | C9: 0 | D9: 0 | E9: 0 | F9: 0 | G9: 0 | H9: 0 | I9: 0 | J9: 0
A10: Fringe | B10: 0 | C10: 0 | D10: 0 | E10: 0 | F10: 0 | G10: 0 | H10: 0 | I10: 0 | J10: 0
A11: Subscriptions | B11: 0 | C11: 0 | D11: 0 | E11: 0 | F11: 0 | G11: 0 | H11: 0 | I11: 0 | J11: 0
A12: Postage | B12: 0 | C12: 0 | D12: 0 | E12: 0 | F12: 0 | G12: 0 | H12: 0 | I12: 0 | J12: 0
A13: Printing | B13: 0 | C13: 0 | D13: 0 | E13: 0 | F13: 0 | G13: 0 | H13: 0 | I13: 0 | J13: 0
A14: Supplies | B14: 0 | C14: 0 | D14: 0 | E14: 0 | F14: 0 | G14: 0 | H14: 0 | I14: 0 | J14: 0
A15: Telephone & Internet | B15: 0 | C15: 0 | D15: 0 | E15: 0 | F15: 0 | G15: 0 | H15: 0 | I15: 0 | J15: 0
A16: Travel | B16: 0 | C16: 0 | D16: 0 | E16: 0 | F16: 0 | G16: 0 | H16: 0 | I16: 0 | J16: 0
A17: Misc | B17: 0 | C17: 0 | D17: 0 | E17: 0 | F17: 0 | G17: 0 | H17: 0 | I17: 0 | J17: 0
A18: Training | B18: 0 | C18: 0 | D18: 0 | E18: 0 | F18: 0 | G18: 0 | H18: 0 | I18: 0 | J18: 0
A19: Payroll Processing Fees | B19: 0 | C19: 0 | D19: 0 | E19: 0 | F19: 0 | G19: 0 | H19: 0 | I19: 0 | J19: 0
A20: Equipment Maintenance | B20: 0 | C20: 0 | D20: 0 | E20: 0 | F20: 0 | G20: 0 | H20: 0 | I20: 0 | J20: 0
... A25: Accounting & Legal Fees | B25: 0 | C25: 0 | D25: 0 | E25: 0 | F25: 0 | G25: 0 | H25: 0 | I25: 0 | J25: 0
A26: Total G&A | B26: =SUM(B9:B25) -> 0 | C26: =SUM(C9:C25) -> 0 | D26: =SUM(D9:D25) -> 0 | E26: =SUM(E9:E25) -> 0 | F26: =SUM(F9:F25) -> 0 | G26: =SUM(G9:G25) -> 0 | H26: =SUM(H9:H25) -> 0 | I26: =SUM(I9:I25) -> 0 | J26: =SUM(J9:J25) -> 0
A28: Less: FAR 31 Unallowable Costs
A29: Interest | B29: 0 | C29: 0 | D29: 0 | E29: 0 | F29: 0 | G29: 0 | H29: 0 | I29: 0 | J29: 0
A30: Contributions | B30: 0 | C30: 0 | D30: 0 | E30: 0 | F30: 0 | G30: 0 | H30: 0 | I30: 0 | J30: 0
A31: Advertising, etc. | B31: 0 | C31: 0 | D31: 0 | E31: 0 | F31: 0 | G31: 0 | H31: 0 | I31: 0 | J31: 0
A32: Total Unallowable Costs | B32: =SUM(B29:B31) -> 0 | C32: =SUM(C29:C31) -> 0 | D32: =SUM(D29:D31) -> 0 | E32: =SUM(E29:E31) -> 0 | F32: =SUM(F29:F31) -> 0 | G32: =SUM(G29:G31) -> 0 | H32: =SUM(H29:H31) -> 0 | I32: =SUM(I29:I31) -> 0 | J32: =SUM(J29:J31) -> 0
A33: G&A Pool After Deducting Unallowable Cost | B33: =+B26-B32 -> 0 | C33: =+C26-C32 -> 0 | D33: =+D26-D32 -> 0 | E33: =+E26-E32 -> 0 | F33: =+F26-F32 -> 0 | G33: =+G26-G32 -> 0 | H33: =+H26-H32 -> 0 | I33: =+I26-I32 -> 0 | J33: =+J26-J32 -> 0
A35: Allocation Base
A36: Direct Labor | B36: 0 | C36: 0 | D36: 0 | E36: 0 | F36: 0 | G36: 0 | H36: 0 | I36: 0 | J36: 0
A37: Fringe | B37: 0 | C37: 0 | D37: 0 | E37: 0 | F37: 0 | G37: 0 | H37: 0 | I37: 0 | J37: 0
A38: Overhead (including any unallowable cost) | B38: 0 | C38: 0 | D38: 0 | E38: 0 | F38: 0 | G38: 0 | H38: 0 | I38: 0 | J38: 0
A39: Other Direct Costs (including any unallowable cost) | B39: 0 | C39: 0 | D39: 0 | E39: 0 | F39: 0 | G39: 0 | H39: 0 | I39: 0 | J39: 0
A40: Total G&A Allocation Base | B40: =SUM(B36:B39) -> 0 | C40: =SUM(C36:C39) -> 0 | D40: =SUM(D36:D39) -> 0 | E40: =SUM(E36:E39) -> 0 | F40: =SUM(F36:F39) -> 0 | G40: =SUM(G36:G39) -> 0 | H40: =SUM(H36:H39) -> 0 | I40: =SUM(I36:I39) -> 0 | J40: =SUM(J36:J39) -> 0
A42: Rate | B42: =ROUND(+B33/B40,3) -> #DIV/0! | C42: =ROUND(+C33/C40,3) -> #DIV/0! | D42: =ROUND(+D33/D40,3) -> #DIV/0! | E42: =ROUND(+E33/E40,3) -> #DIV/0! | F42: =ROUND(+F33/F40,3) -> #DIV/0! | G42: =ROUND(+G33/G40,3) -> #DIV/0! | H42: =ROUND(+H33/H40,3) -> #DIV/0! | I42: =ROUND(+I33/I40,3) -> #DIV/0! | J42: =ROUND(+J33/J40,3) -> #DIV/0!
